Workbook

Sheet Dashboard
B2: GL-Agent | Publication simulator v1.0
B3: How much control should an AI agent carry, and where do you stop? This workbook computes the turning points.
B4: Synthetic scenarios • 7 September 2026 • no empirical calibration
B6: Editable input | C6: the dial | D6: calculated automatically | E6: key results
B8: INPUTS • annual units • blue cells are editable
B9: Attack campaigns per year (lambda) | C9: 40 | H9: Fatigue | I9: =1/(1+EXP(MIN(700,MAX(-700,($C$17*$C$24-$C$18)/$C$19)))) -> 0.66075637
B10: Baseline success prob. per campaign (q0) | C10: 0.2 | H10: Detection | I10: =$C$15*(1-EXP(-$C$16*$C$24)) -> 0.50569645
B11: Loss per successful campaign (L0) | C11: 50000 | H11: h | I11: =I9*I10 -> 0.33414215
B12: Defence productivity γ (per unit x) | C12: 0.35 | H12: h derivative | I12: =$C$15*($C$16*EXP(-$C$16*$C$24)*I9-(1-EXP(-$C$16*$C$24))*$C$17/$C$19*I9*(1-I9)) -> -0.053909321
B13: Cash-cost slope c (currency/year per x) | C13: 20000 | H13: Risk derivative | I13: =$C$27*EXP(-$C$12*$C$24)*(-$C$12*(1-I11)-I12)+2*$C$20*$C$24 -> -3583.5008
B14: Utility-tax slope τ (currency/year per x) | C14: 30000 | H14: Welfare derivative | I14: =-I13-$C$28 -> -46416.499
B15: Max review effectiveness (h_max) | C15: 0.8 | H15: Input validity | I15: =IF(AND(C9>=0,C10>=0,C10<=1,C11>=0,C12>=0,C13>=0,C14>=0,C13+C14>0,C15>=0,C15<=1,C16>=0,C17>=0,C18>=0,C19>0,C20>=0,C21>=0,C24>=0,C24<=10),"VALID","CHECK INPUTS") -> VALID
B16: Detection responsiveness κ_d (per unit x) | C16: 0.5 | H16: Deploy vs outside option | I16: =IF(I15<>"VALID","Check inputs",IF(C39>C40,"Deployment worthwhile","Outside option preferred")) -> Deployment worthwhile
B17: Alert-load slope v₀ (alerts/year per x) | C17: 800
B18: Review capacity A_c (alerts/year) | C18: 2000
B19: Fatigue smoothness s (alerts/year) | C19: 600
B20: Displacement coefficient d (currency/year per x²) | C20: 8000
B21: Baseline delivered benefit B₀ (currency/year) | C21: 1500000
B23: THE DIAL
B24: Control intensity x (0–10) | C24: 2
B26: RESULTS (calculated automatically - nothing to change below)
B27: Baseline attack loss R₀ | C27: =C9*C10*C11 -> 400000
B28: All-in slope k = c + τ | C28: =C13+C14 -> 50000
B29: q-only solution | C29: =IF(C12*C27>C28,"Interior","Corner: no q-only investment") -> Interior
B30: q-only optimal intensity | C30: =IF(AND(C12>0,C28>0,C12*C27>C28),LN(C12*C27/C28)/C12,0) -> 2.9417698
B31: q-only optimized residual risk | C31: =C27*EXP(-C12*C30) -> 142857.14
B32: Full-model welfare optimum (0.01 grid) | C32: =INDEX(Curves!A2:A1002,MATCH(MAX(Curves!M2:M1002),Curves!M2:M1002,0)) -> 1.45
B33: Full-model global risk minimum (0.01 grid) | C33: =INDEX(Curves!A2:A1002,MATCH(MIN(Curves!I2:I1002),Curves!I2:I1002,0)) -> 2.06
B34: Attack loss at welfare optimum | C34: =INDEX(Curves!G2:G1002,MATCH(C32,Curves!A2:A1002,0)) -> 161110.93
B35: Displacement at welfare optimum | C35: =C20*C32^2 -> 16820
B36: q-only all-in burden / R₀ | C36: =IF(C27>0,C28*C30/C27,0) -> 0.36772122
B37: Conditional 1/e check | C37: =IF(C36<=1/EXP(1)+0.000000001,"PASS (restricted q-only model)","CHECK") -> PASS (restricted q-only model)
B38: Full-model burden / R₀ (not bounded by 1/e) | C38: =IF(C27>0,C28*C32/C27,0) -> 0.18125
B39: Maximum welfare on grid | C39: =MAX(Curves!M2:M1002) -> 1249569.1
B40: Outside option (non-deployment) | C40: =0 -> 0
B41: Search-range diagnostic | C41: =IF(OR(C32>=10,C33>=10),"Upper edge: extend grid",IF(C32=0,"Welfare corner at zero","Interior grid optima")) -> Interior grid optima
B42: Welfare at selected x | C42: =C21-C28*C24-C27*EXP(-C12*C24)*(1-I11)-C20*C24^2 -> 1235737.9
B43: Total risk at selected x | C43: =C27*EXP(-C12*C24)*(1-I11)+C20*C24^2 -> 164262.09
B44: Marginal welfare at selected x | C44: =IF(I14>0.000001,"Increasing",IF(I14< -0.000001,"Decreasing","Stationary")) -> Decreasing
B45: Marginal risk at selected x | C45: =IF(I13>0.000001,"Increasing",IF(I13< -0.000001,"Decreasing","Stationary")) -> Decreasing
B46: Selected-point interpretation | C46: =IF(I15<>"VALID","Invalid input: do not interpret",IF(C24>C33,"Beyond global grid risk minimum","Use marginal signs; inspect entire curve")) -> Use marginal signs; inspect entire curve
B48: SCENARIO PRESETS (live from the Examples sheet)
B49: Transcribe a preset's inputs on the Examples sheet into the blue cells above. Turning points shown here update automatically.
B50: Synthetic preset | C50: R₀ | D50: x welfare | E50: x risk | F50: Evidence status
B51: Summarization | C51: =Examples!C20 -> 600000 | D51: =Examples!C25 -> 1.35 | E51: =Examples!C26 -> 1.51 | F51: Illustrative only
B52: MCP DevOps | C52: =Examples!D20 -> 6000000 | D52: =Examples!D25 -> 6.93 | E52: =Examples!D26 -> 7.84 | F52: Illustrative only
B53: Finance | C53: =Examples!E20 -> 2700000 | D53: =Examples!E25 -> 2.98 | E53: =Examples!E26 -> 5.09 | F53: Illustrative only
B54: Drafting | C54: =Examples!F20 -> 17500 | D54: =Examples!F25 -> 0 | E54: =Examples!F26 -> 0.17 | F54: Illustrative only
B55: High-loss / smooth | C55: =Examples!G20 -> 2000000 | D55: =Examples!G25 -> 2.59 | E55: =Examples!G26 -> 5.69 | F55: Illustrative only
B56: High-loss / steep | C56: =Examples!H20 -> 2000000 | D56: =Examples!H25 -> 2.02 | E56: =Examples!H26 -> 5.78 | F56: Illustrative only

Sheet Curves
A1: Intensity x | B1: q(x) | C1: Alerts / year | D1: Detection ceiling | E1: Fatigue factor | F1: Prevented fraction h | G1: Attack loss / year | H1: Displacement increment | I1: Total risk / year | J1: Cash cost / year | K1: Utility tax / year | L1: Delivered benefit | M1: Welfare / year | N1: All-in burden | O1: h derivative | P1: Risk derivative | Q1: Welfare derivative
A2: =(2-2)/100 -> 0 | B2: =Dashboard!$C$10*EXP(-Dashboard!$C$12*A2) -> 0.2 | C2: =Dashboard!$C$17*A2 -> 0 | D2: =Dashboard!$C$15*(1-EXP(-Dashboard!$C$16*A2)) -> 0 | E2: =1/(1+EXP(MIN(700,MAX(-700,(C2-Dashboard!$C$18)/Dashboard!$C$19)))) -> 0.9655548 | F2: =D2*E2 -> 0 | G2: =Dashboard!$C$9*B2*Dashboard!$C$11*(1-F2) -> 400000 | H2: =Dashboard!$C$20*A2^2 -> 0 | I2: =G2+H2 -> 400000 | J2: =Dashboard!$C$13*A2 -> 0 | K2: =Dashboard!$C$14*A2 -> 0 | L2: =Dashboard!$C$21-K2 -> 1500000 | M2: =L2-I2-J2 -> 1100000 | N2: =J2+K2 -> 0 | O2: =Dashboard!$C$15*(Dashboard!$C$16*EXP(-Dashboard!$C$16*A2)*E2-(1-EXP(-Dashboard!$C$16*A2))*Dashboard!$C$17/Dashboard!$C$19*E2*(1-E2)) -> 0.38622192 | P2: =Dashboard!$C$9*B2*Dashboard!$C$11*(-Dashboard!$C$12*(1-F2)-O2)+2*Dashboard!$C$20*A2 -> -294488.77 | Q2: =-P2-Dashboard!$C$13-Dashboard!$C$14 -> 244488.77
A3: =(3-2)/100 -> 0.01 | B3: =Dashboard!$C$10*EXP(-Dashboard!$C$12*A3) -> 0.19930122 | C3: =Dashboard!$C$17*A3 -> 8 | D3: =Dashboard!$C$15*(1-EXP(-Dashboard!$C$16*A3)) -> 0.0039900166 | E3: =1/(1+EXP(MIN(700,MAX(-700,(C3-Dashboard!$C$18)/Dashboard!$C$19)))) -> 0.96510859 | F3: =D3*E3 -> 0.0038507993 | G3: =Dashboard!$C$9*B3*Dashboard!$C$11*(1-F3) -> 397067.51 | H3: =Dashboard!$C$20*A3^2 -> 0.8 | I3: =G3+H3 -> 397068.31 | J3: =Dashboard!$C$13*A3 -> 200 | K3: =Dashboard!$C$14*A3 -> 300 | L3: =Dashboard!$C$21-K3 -> 1499700 | M3: =L3-I3-J3 -> 1102431.7 | N3: =J3+K3 -> 500 | O3: =Dashboard!$C$15*(Dashboard!$C$16*EXP(-Dashboard!$C$16*A3)*E3-(1-EXP(-Dashboard!$C$16*A3))*Dashboard!$C$17/Dashboard!$C$19*E3*(1-E3)) -> 0.38393889 | P3: =Dashboard!$C$9*B3*Dashboard!$C$11*(-Dashboard!$C$12*(1-F3)-O3)+2*Dashboard!$C$20*A3 -> -291852.61 | Q3: =-P3-Dashboard!$C$13-Dashboard!$C$14 -> 241852.61
A4: =(4-2)/100 -> 0.02 | B4: =Dashboard!$C$10*EXP(-Dashboard!$C$12*A4) -> 0.19860489 | C4: =Dashboard!$C$17*A4 -> 16 | D4: =Dashboard!$C$15*(1-EXP(-Dashboard!$C$16*A4)) -> 0.007960133 | E4: =1/(1+EXP(MIN(700,MAX(-700,(C4-Dashboard!$C$18)/Dashboard!$C$19)))) -> 0.96465681 | F4: =D4*E4 -> 0.0076787965 | G4: =Dashboard!$C$9*B4*Dashboard!$C$11*(1-F4) -> 394159.68 | H4: =Dashboard!$C$20*A4^2 -> 3.2 | I4: =G4+H4 -> 394162.88 | J4: =Dashboard!$C$13*A4 -> 400 | K4: =Dashboard!$C$14*A4 -> 600 | L4: =Dashboard!$C$21-K4 -> 1499400 | M4: =L4-I4-J4 -> 1104837.1 | N4: =J4+K4 -> 1000 | O4: =Dashboard!$C$15*(Dashboard!$C$16*EXP(-Dashboard!$C$16*A4)*E4-(1-EXP(-Dashboard!$C$16*A4))*Dashboard!$C$17/Dashboard!$C$19*E4*(1-E4)) -> 0.38166147 | P4: =Dashboard!$C$9*B4*Dashboard!$C$11*(-Dashboard!$C$12*(1-F4)-O4)+2*Dashboard!$C$20*A4 -> -289235.56 | Q4: =-P4-Dashboard!$C$13-Dashboard!$C$14 -> 239235.56
A5: =(5-2)/100 -> 0.03 | B5: =Dashboard!$C$10*EXP(-Dashboard!$C$12*A5) -> 0.19791099 | C5: =Dashboard!$C$17*A5 -> 24 | D5: =Dashboard!$C$15*(1-EXP(-Dashboard!$C$16*A5)) -> 0.011910448 | E5: =1/(1+EXP(MIN(700,MAX(-700,(C5-Dashboard!$C$18)/Dashboard!$C$19)))) -> 0.9641994 | F5: =D5*E5 -> 0.011484047 | G5: =Dashboard!$C$9*B5*Dashboard!$C$11*(1-F5) -> 391276.33 | H5: =Dashboard!$C$20*A5^2 -> 7.2 | I5: =G5+H5 -> 391283.53 | J5: =Dashboard!$C$13*A5 -> 600 | K5: =Dashboard!$C$14*A5 -> 900 | L5: =Dashboard!$C$21-K5 -> 1499100 | M5: =L5-I5-J5 -> 1107216.5 | N5: =J5+K5 -> 1500 | O5: =Dashboard!$C$15*(Dashboard!$C$16*EXP(-Dashboard!$C$16*A5)*E5-(1-EXP(-Dashboard!$C$16*A5))*Dashboard!$C$17/Dashboard!$C$19*E5*(1-E5)) -> 0.37938955 | P5: =Dashboard!$C$9*B5*Dashboard!$C$11*(-Dashboard!$C$12*(1-F5)-O5)+2*Dashboard!$C$20*A5 -> -286637.44 | Q5: =-P5-Dashboard!$C$13-Dashboard!$C$14 -> 236637.44
A6: =(6-2)/100 -> 0.04 | B6: =Dashboard!$C$10*EXP(-Dashboard!$C$12*A6) -> 0.19721951 | C6: =Dashboard!$C$17*A6 -> 32 | D6: =Dashboard!$C$15*(1-EXP(-Dashboard!$C$16*A6)) -> 0.015841061 | E6: =1/(1+EXP(MIN(700,MAX(-700,(C6-Dashboard!$C$18)/Dashboard!$C$19)))) -> 0.96373628 | F6: =D6*E6 -> 0.015266606 | G6: =Dashboard!$C$9*B6*Dashboard!$C$11*(1-F6) -> 388417.27 | H6: =Dashboard!$C$20*A6^2 -> 12.8 | I6: =G6+H6 -> 388430.07 | J6: =Dashboard!$C$13*A6 -> 800 | K6: =Dashboard!$C$14*A6 -> 1200 | L6: =Dashboard!$C$21-K6 -> 1498800 | M6: =L6-I6-J6 -> 1109569.9 | N6: =J6+K6 -> 2000 | O6: =Dashboard!$C$15*(Dashboard!$C$16*EXP(-Dashboard!$C$16*A6)*E6-(1-EXP(-Dashboard!$C$16*A6))*Dashboard!$C$17/Dashboard!$C$19*E6*(1-E6)) -> 0.37712305 | P6: =Dashboard!$C$9*B6*Dashboard!$C$11*(-Dashboard!$C$12*(1-F6)-O6)+2*Dashboard!$C$20*A6 -> -284058.09 | Q6: =-P6-Dashboard!$C$13-Dashboard!$C$14 -> 234058.09
A7: =(7-2)/100 -> 0.05 | B7: =Dashboard!$C$10*EXP(-Dashboard!$C$12*A7) -> 0.19653045 | C7: =Dashboard!$C$17*A7 -> 40 | D7: =Dashboard!$C$15*(1-EXP(-Dashboard!$C$16*A7)) -> 0.01975207 | E7: =1/(1+EXP(MIN(700,MAX(-700,(C7-Dashboard!$C$18)/Dashboard!$C$19)))) -> 0.96326741 | F7: =D7*E7 -> 0.019026526 | G7: =Dashboard!$C$9*B7*Dashboard!$C$11*(1-F7) -> 385582.31 | H7: =Dashboard!$C$20*A7^2 -> 20 | I7: =G7+H7 -> 385602.31 | J7: =Dashboard!$C$13*A7 -> 1000 | K7: =Dashboard!$C$14*A7 -> 1500 | L7: =Dashboard!$C$21-K7 -> 1498500 | M7: =L7-I7-J7 -> 1111897.7 | N7: =J7+K7 -> 2500 | O7: =Dashboard!$C$15*(Dashboard!$C$16*EXP(-Dashboard!$C$16*A7)*E7-(1-EXP(-Dashboard!$C$16*A7))*Dashboard!$C$17/Dashboard!$C$19*E7*(1-E7)) -> 0.37486184 | P7: =Dashboard!$C$9*B7*Dashboard!$C$11*(-Dashboard!$C$12*(1-F7)-O7)+2*Dashboard!$C$20*A7 -> -281497.34 | Q7: =-P7-Dashboard!$C$13-Dashboard!$C$14 -> 231497.34
A8: =(8-2)/100 -> 0.06 | B8: =Dashboard!$C$10*EXP(-Dashboard!$C$12*A8) -> 0.19584379 | C8: =Dashboard!$C$17*A8 -> 48 | D8: =Dashboard!$C$15*(1-EXP(-Dashboard!$C$16*A8)) -> 0.023643573 | E8: =1/(1+EXP(MIN(700,MAX(-700,(C8-Dashboard!$C$18)/Dashboard!$C$19)))) -> 0.96279271 | F8: =D8*E8 -> 0.02276386 | G8: =Dashboard!$C$9*B8*Dashboard!$C$11*(1-F8) -> 382771.26 | H8: =Dashboard!$C$20*A8^2 -> 28.8 | I8: =G8+H8 -> 382800.06 | J8: =Dashboard!$C$13*A8 -> 1200 | K8: =Dashboard!$C$14*A8 -> 1800 | L8: =Dashboard!$C$21-K8 -> 1498200 | M8: =L8-I8-J8 -> 1114199.9 | N8: =J8+K8 -> 3000 | O8: =Dashboard!$C$15*(Dashboard!$C$16*EXP(-Dashboard!$C$16*A8)*E8-(1-EXP(-Dashboard!$C$16*A8))*Dashboard!$C$17/Dashboard!$C$19*E8*(1-E8)) -> 0.37260584 | P8: =Dashboard!$C$9*B8*Dashboard!$C$11*(-Dashboard!$C$12*(1-F8)-O8)+2*Dashboard!$C$20*A8 -> -278955.03 | Q8: =-P8-Dashboard!$C$13-Dashboard!$C$14 -> 228955.03
A9: =(9-2)/100 -> 0.07 | B9: =Dashboard!$C$10*EXP(-Dashboard!$C$12*A9) -> 0.19515954 | C9: =Dashboard!$C$17*A9 -> 56 | D9: =Dashboard!$C$15*(1-EXP(-Dashboard!$C$16*A9)) -> 0.027515667 | E9: =1/(1+EXP(MIN(700,MAX(-700,(C9-Dashboard!$C$18)/Dashboard!$C$19)))) -> 0.96231211 | F9: =D9*E9 -> 0.02647866 | G9: =Dashboard!$C$9*B9*Dashboard!$C$11*(1-F9) -> 379983.95 | H9: =Dashboard!$C$20*A9^2 -> 39.2 | I9: =G9+H9 -> 380023.15 | J9: =Dashboard!$C$13*A9 -> 1400 | K9: =Dashboard!$C$14*A9 -> 2100 | L9: =Dashboard!$C$21-K9 -> 1497900 | M9: =L9-I9-J9 -> 1116476.9 | N9: =J9+K9 -> 3500 | O9: =Dashboard!$C$15*(Dashboard!$C$16*EXP(-Dashboard!$C$16*A9)*E9-(1-EXP(-Dashboard!$C$16*A9))*Dashboard!$C$17/Dashboard!$C$19*E9*(1-E9)) -> 0.37035495 | P9: =Dashboard!$C$9*B9*Dashboard!$C$11*(-Dashboard!$C$12*(1-F9)-O9)+2*Dashboard!$C$20*A9 -> -276430.98 | Q9: =-P9-Dashboard!$C$13-Dashboard!$C$14 -> 226430.98
A10: =(10-2)/100 -> 0.08 | B10: =Dashboard!$C$10*EXP(-Dashboard!$C$12*A10) -> 0.19447767 | C10: =Dashboard!$C$17*A10 -> 64 | D10: =Dashboard!$C$15*(1-EXP(-Dashboard!$C$16*A10)) -> 0.031368449 | E10: =1/(1+EXP(MIN(700,MAX(-700,(C10-Dashboard!$C$18)/Dashboard!$C$19)))) -> 0.96182555 | F10: =D10*E10 -> 0.030170975 | G10: =Dashboard!$C$9*B10*Dashboard!$C$11*(1-F10) -> 377220.18 | H10: =Dashboard!$C$20*A10^2 -> 51.2 | I10: =G10+H10 -> 377271.38 | J10: =Dashboard!$C$13*A10 -> 1600 | K10: =Dashboard!$C$14*A10 -> 2400 | L10: =Dashboard!$C$21-K10 -> 1497600 | M10: =L10-I10-J10 -> 1118728.6 | N10: =J10+K10 -> 4000 | O10: =Dashboard!$C$15*(Dashboard!$C$16*EXP(-Dashboard!$C$16*A10)*E10-(1-EXP(-Dashboard!$C$16*A10))*Dashboard!$C$17/Dashboard!$C$19*E10*(1-E10)) -> 0.36810905 | P10: =Dashboard!$C$9*B10*Dashboard!$C$11*(-Dashboard!$C$12*(1-F10)-O10)+2*Dashboard!$C$20*A10 -> -273925.05 | Q10: =-P10-Dashboard!$C$13-Dashboard!$C$14 -> 223925.05
A11: =(11-2)/100 -> 0.09 | B11: =Dashboard!$C$10*EXP(-Dashboard!$C$12*A11) -> 0.19379819 | C11: =Dashboard!$C$17*A11 -> 72 | D11: =Dashboard!$C$15*(1-EXP(-Dashboard!$C$16*A11)) -> 0.035202015 | E11: =1/(1+EXP(MIN(700,MAX(-700,(C11-Dashboard!$C$18)/Dashboard!$C$19)))) -> 0.96133296 | F11: =D11*E11 -> 0.033840857 | G11: =Dashboard!$C$9*B11*Dashboard!$C$11*(1-F11) -> 374479.79 | H11: =Dashboard!$C$20*A11^2 -> 64.8 | I11: =G11+H11 -> 374544.59 | J11: =Dashboard!$C$13*A11 -> 1800 | K11: =Dashboard!$C$14*A11 -> 2700 | L11: =Dashboard!$C$21-K11 -> 1497300 | M11: =L11-I11-J11 -> 1120955.4 | N11: =J11+K11 -> 4500 | O11: =Dashboard!$C$15*(Dashboard!$C$16*EXP(-Dashboard!$C$16*A11)*E11-(1-EXP(-Dashboard!$C$16*A11))*Dashboard!$C$17/Dashboard!$C$19*E11*(1-E11)) -> 0.36586806 | P11: =Dashboard!$C$9*B11*Dashboard!$C$11*(-Dashboard!$C$12*(1-F11)-O11)+2*Dashboard!$C$20*A11 -> -271437.06 | Q11: =-P11-Dashboard!$C$13-Dashboard!$C$14 -> 221437.06
A12: =(12-2)/100 -> 0.1 | B12: =Dashboard!$C$10*EXP(-Dashboard!$C$12*A12) -> 0.19312108 | C12: =Dashboard!$C$17*A12 -> 80 | D12: =Dashboard!$C$15*(1-EXP(-Dashboard!$C$16*A12)) -> 0.03901646 | E12: =1/(1+EXP(MIN(700,MAX(-700,(C12-Dashboard!$C$18)/Dashboard!$C$19)))) -> 0.96083428 | F12: =D12*E12 -> 0.037488353 | G12: =Dashboard!$C$9*B12*Dashboard!$C$11*(1-F12) -> 371762.58 | H12: =Dashboard!$C$20*A12^2 -> 80 | I12: =G12+H12 -> 371842.58 | J12: =Dashboard!$C$13*A12 -> 2000 | K12: =Dashboard!$C$14*A12 -> 3000 | L12: =Dashboard!$C$21-K12 -> 1497000 | M12: =L12-I12-J12 -> 1123157.4 | N12: =J12+K12 -> 5000 | O12: =Dashboard!$C$15*(Dashboard!$C$16*EXP(-Dashboard!$C$16*A12)*E12-(1-EXP(-Dashboard!$C$16*A12))*Dashboard!$C$17/Dashboard!$C$19*E12*(1-E12)) -> 0.36363186 | P12: =Dashboard!$C$9*B12*Dashboard!$C$11*(-Dashboard!$C$12*(1-F12)-O12)+2*Dashboard!$C$20*A12 -> -268966.86 | Q12: =-P12-Dashboard!$C$13-Dashboard!$C$14 -> 218966.86
A13: =(13-2)/100 -> 0.11 | B13: =Dashboard!$C$10*EXP(-Dashboard!$C$12*A13) -> 0.19244634 | C13: =Dashboard!$C$17*A13 -> 88 | D13: =Dashboard!$C$15*(1-EXP(-Dashboard!$C$16*A13)) -> 0.042811882 | E13: =1/(1+EXP(MIN(700,MAX(-700,(C13-Dashboard!$C$18)/Dashboard!$C$19)))) -> 0.96032943 | F13: =D13*E13 -> 0.04111351 | G13: =Dashboard!$C$9*B13*Dashboard!$C$11*(1-F13) -> 369068.39 | H13: =Dashboard!$C$20*A13^2 -> 96.8 | I13: =G13+H13 -> 369165.19 | J13: =Dashboard!$C$13*A13 -> 2200 | K13: =Dashboard!$C$14*A13 -> 3300 | L13: =Dashboard!$C$21-K13 -> 1496700 | M13: =L13-I13-J13 -> 1125334.8 | N13: =J13+K13 -> 5500 | O13: =Dashboard!$C$15*(Dashboard!$C$16*EXP(-Dashboard!$C$16*A13)*E13-(1-EXP(-Dashboard!$C$16*A13))*Dashboard!$C$17/Dashboard!$C$19*E13*(1-E13)) -> 0.36140035 | P13: =Dashboard!$C$9*B13*Dashboard!$C$11*(-Dashboard!$C$12*(1-F13)-O13)+2*Dashboard!$C$20*A13 -> -266514.29 | Q13: =-P13-Dashboard!$C$13-Dashboard!$C$14 -> 216514.29
A14: =(14-2)/100 -> 0.12 | B14: =Dashboard!$C$10*EXP(-Dashboard!$C$12*A14) -> 0.19177396 | C14: =Dashboard!$C$17*A14 -> 96 | D14: =Dashboard!$C$15*(1-EXP(-Dashboard!$C$16*A14)) -> 0.046588373 | E14: =1/(1+EXP(MIN(700,MAX(-700,(C14-Dashboard!$C$18)/Dashboard!$C$19)))) -> 0.95981834 | F14: =D14*E14 -> 0.044716375 | G14: =Dashboard!$C$9*B14*Dashboard!$C$11*(1-F14) -> 366397.04 | H14: =Dashboard!$C$20*A14^2 -> 115.2 | I14: =G14+H14 -> 366512.24 | J14: =Dashboard!$C$13*A14 -> 2400 | K14: =Dashboard!$C$14*A14 -> 3600 | L14: =Dashboard!$C$21-K14 -> 1496400 | M14: =L14-I14-J14 -> 1127487.8 | N14: =J14+K14 -> 6000 | O14: =Dashboard!$C$15*(Dashboard!$C$16*EXP(-Dashboard!$C$16*A14)*E14-(1-EXP(-Dashboard!$C$16*A14))*Dashboard!$C$17/Dashboard!$C$19*E14*(1-E14)) -> 0.35917344 | P14: =Dashboard!$C$9*B14*Dashboard!$C$11*(-Dashboard!$C$12*(1-F14)-O14)+2*Dashboard!$C$20*A14 -> -264079.19 | Q14: =-P14-Dashboard!$C$13-Dashboard!$C$14 -> 214079.19
A15: =(15-2)/100 -> 0.13 | B15: =Dashboard!$C$10*EXP(-Dashboard!$C$12*A15) -> 0.19110392 | C15: =Dashboard!$C$17*A15 -> 104 | D15: =Dashboard!$C$15*(1-EXP(-Dashboard!$C$16*A15)) -> 0.050346029 | E15: =1/(1+EXP(MIN(700,MAX(-700,(C15-Dashboard!$C$18)/Dashboard!$C$19)))) -> 0.95930095 | F15: =D15*E15 -> 0.048296994 | G15: =Dashboard!$C$9*B15*Dashboard!$C$11*(1-F15) -> 363748.35 | H15: =Dashboard!$C$20*A15^2 -> 135.2 | I15: =G15+H15 -> 363883.55 | J15: =Dashboard!$C$13*A15 -> 2600 | K15: =Dashboard!$C$14*A15 -> 3900 | L15: =Dashboard!$C$21-K15 -> 1496100 | M15: =L15-I15-J15 -> 1129616.4 | N15: =J15+K15 -> 6500 | O15: =Dashboard!$C$15*(Dashboard!$C$16*EXP(-Dashboard!$C$16*A15)*E15-(1-EXP(-Dashboard!$C$16*A15))*Dashboard!$C$17/Dashboard!$C$19*E15*(1-E15)) -> 0.35695103 | P15: =Dashboard!$C$9*B15*Dashboard!$C$11*(-Dashboard!$C$12*(1-F15)-O15)+2*Dashboard!$C$20*A15 -> -261661.4 | Q15: =-P15-Dashboard!$C$13-Dashboard!$C$14 -> 211661.4
A16: =(16-2)/100 -> 0.14 | B16: =Dashboard!$C$10*EXP(-Dashboard!$C$12*A16) -> 0.19043623 | C16: =Dashboard!$C$17*A16 -> 112 | D16: =Dashboard!$C$15*(1-EXP(-Dashboard!$C$16*A16)) -> 0.054084944 | E16: =1/(1+EXP(MIN(700,MAX(-700,(C16-Dashboard!$C$18)/Dashboard!$C$19)))) -> 0.95877718 | F16: =D16*E16 -> 0.05185541 | G16: =Dashboard!$C$9*B16*Dashboard!$C$11*(1-F16) -> 361122.15 | H16: =Dashboard!$C$20*A16^2 -> 156.8 | I16: =G16+H16 -> 361278.95 | J16: =Dashboard!$C$13*A16 -> 2800 | K16: =Dashboard!$C$14*A16 -> 4200 | L16: =Dashboard!$C$21-K16 -> 1495800 | M16: =L16-I16-J16 -> 1131721 | N16: =J16+K16 -> 7000 | O16: =Dashboard!$C$15*(Dashboard!$C$16*EXP(-Dashboard!$C$16*A16)*E16-(1-EXP(-Dashboard!$C$16*A16))*Dashboard!$C$17/Dashboard!$C$19*E16*(1-E16)) -> 0.354733 | P16: =Dashboard!$C$9*B16*Dashboard!$C$11*(-Dashboard!$C$12*(1-F16)-O16)+2*Dashboard!$C$20*A16 -> -259260.78 | Q16: =-P16-Dashboard!$C$13-Dashboard!$C$14 -> 209260.78
A17: =(17-2)/100 -> 0.15 | B17: =Dashboard!$C$10*EXP(-Dashboard!$C$12*A17) -> 0.18977086 | C17: =Dashboard!$C$17*A17 -> 120 | D17: =Dashboard!$C$15*(1-EXP(-Dashboard!$C$16*A17)) -> 0.057805211 | E17: =1/(1+EXP(MIN(700,MAX(-700,(C17-Dashboard!$C$18)/Dashboard!$C$19)))) -> 0.95824696 | F17: =D17*E17 -> 0.055391668 | G17: =Dashboard!$C$9*B17*Dashboard!$C$11*(1-F17) -> 358518.28 | H17: =Dashboard!$C$20*A17^2 -> 180 | I17: =G17+H17 -> 358698.28 | J17: =Dashboard!$C$13*A17 -> 3000 | K17: =Dashboard!$C$14*A17 -> 4500 | L17: =Dashboard!$C$21-K17 -> 1495500 | M17: =L17-I17-J17 -> 1133801.7 | N17: =J17+K17 -> 7500 | O17: =Dashboard!$C$15*(Dashboard!$C$16*EXP(-Dashboard!$C$16*A17)*E17-(1-EXP(-Dashboard!$C$16*A17))*Dashboard!$C$17/Dashboard!$C$19*E17*(1-E17)) -> 0.35251926 | P17: =Dashboard!$C$9*B17*Dashboard!$C$11*(-Dashboard!$C$12*(1-F17)-O17)+2*Dashboard!$C$20*A17 -> -256877.17 | Q17: =-P17-Dashboard!$C$13-Dashboard!$C$14 -> 206877.17
A18: =(18-2)/100 -> 0.16 | B18: =Dashboard!$C$10*EXP(-Dashboard!$C$12*A18) -> 0.18910783 | C18: =Dashboard!$C$17*A18 -> 128 | D18: =Dashboard!$C$15*(1-EXP(-Dashboard!$C$16*A18)) -> 0.061506923 | E18: =1/(1+EXP(MIN(700,MAX(-700,(C18-Dashboard!$C$18)/Dashboard!$C$19)))) -> 0.95771023 | F18: =D18*E18 -> 0.058905809 | G18: =Dashboard!$C$9*B18*Dashboard!$C$11*(1-F18) -> 355936.56 | H18: =Dashboard!$C$20*A18^2 -> 204.8 | I18: =G18+H18 -> 356141.36 | J18: =Dashboard!$C$13*A18 -> 3200 | K18: =Dashboard!$C$14*A18 -> 4800 | L18: =Dashboard!$C$21-K18 -> 1495200 | M18: =L18-I18-J18 -> 1135858.6 | N18: =J18+K18 -> 8000 | O18: =Dashboard!$C$15*(Dashboard!$C$16*EXP(-Dashboard!$C$16*A18)*E18-(1-EXP(-Dashboard!$C$16*A18))*Dashboard!$C$17/Dashboard!$C$19*E18*(1-E18)) -> 0.3503097 | P18: =Dashboard!$C$9*B18*Dashboard!$C$11*(-Dashboard!$C$12*(1-F18)-O18)+2*Dashboard!$C$20*A18 -> -254510.41 | Q18: =-P18-Dashboard!$C$13-Dashboard!$C$14 -> 204510.41
A19: =(19-2)/100 -> 0.17 | B19: =Dashboard!$C$10*EXP(-Dashboard!$C$12*A19) -> 0.18844711 | C19: =Dashboard!$C$17*A19 -> 136 | D19: =Dashboard!$C$15*(1-EXP(-Dashboard!$C$16*A19)) -> 0.065190172 | E19: =1/(1+EXP(MIN(700,MAX(-700,(C19-Dashboard!$C$18)/Dashboard!$C$19)))) -> 0.9571669 | F19: =D19*E19 -> 0.062397875 | G19: =Dashboard!$C$9*B19*Dashboard!$C$11*(1-F19) -> 353376.82 | H19: =Dashboard!$C$20*A19^2 -> 231.2 | I19: =G19+H19 -> 353608.02 | J19: =Dashboard!$C$13*A19 -> 3400 | K19: =Dashboard!$C$14*A19 -> 5100 | L19: =Dashboard!$C$21-K19 -> 1494900 | M19: =L19-I19-J19 -> 1137892 | N19: =J19+K19 -> 8500 | O19: =Dashboard!$C$15*(Dashboard!$C$16*EXP(-Dashboard!$C$16*A19)*E19-(1-EXP(-Dashboard!$C$16*A19))*Dashboard!$C$17/Dashboard!$C$19*E19*(1-E19)) -> 0.34810423 | P19: =Dashboard!$C$9*B19*Dashboard!$C$11*(-Dashboard!$C$12*(1-F19)-O19)+2*Dashboard!$C$20*A19 -> -252160.36 | Q19: =-P19-Dashboard!$C$13-Dashboard!$C$14 -> 202160.36
A20: =(20-2)/100 -> 0.18 | B20: =Dashboard!$C$10*EXP(-Dashboard!$C$12*A20) -> 0.18778869 | C20: =Dashboard!$C$17*A20 -> 144 | D20: =Dashboard!$C$15*(1-EXP(-Dashboard!$C$16*A20)) -> 0.068855052 | E20: =1/(1+EXP(MIN(700,MAX(-700,(C20-Dashboard!$C$18)/Dashboard!$C$19)))) -> 0.95661691 | F20: =D20*E20 -> 0.065867907 | G20: =Dashboard!$C$9*B20*Dashboard!$C$11*(1-F20) -> 350838.89 | H20: =Dashboard!$C$20*A20^2 -> 259.2 | I20: =G20+H20 -> 351098.09 | J20: =Dashboard!$C$13*A20 -> 3600 | K20: =Dashboard!$C$14*A20 -> 5400 | L20: =Dashboard!$C$21-K20 -> 1494600 | M20: =L20-I20-J20 -> 1139901.9 | N20: =J20+K20 -> 9000 | O20: =Dashboard!$C$15*(Dashboard!$C$16*EXP(-Dashboard!$C$16*A20)*E20-(1-EXP(-Dashboard!$C$16*A20))*Dashboard!$C$17/Dashboard!$C$19*E20*(1-E20)) -> 0.34590274 | P20: =Dashboard!$C$9*B20*Dashboard!$C$11*(-Dashboard!$C$12*(1-F20)-O20)+2*Dashboard!$C$20*A20 -> -249826.86 | Q20: =-P20-Dashboard!$C$13-Dashboard!$C$14 -> 199826.86
A21: =(21-2)/100 -> 0.19 | B21: =Dashboard!$C$10*EXP(-Dashboard!$C$12*A21) -> 0.18713258 | C21: =Dashboard!$C$17*A21 -> 152 | D21: =Dashboard!$C$15*(1-EXP(-Dashboard!$C$16*A21)) -> 0.072501652 | E21: =1/(1+EXP(MIN(700,MAX(-700,(C21-Dashboard!$C$18)/Dashboard!$C$19)))) -> 0.95606018 | F21: =D21*E21 -> 0.069315943 | G21: =Dashboard!$C$9*B21*Dashboard!$C$11*(1-F21) -> 348322.62 | H21: =Dashboard!$C$20*A21^2 -> 288.8 | I21: =G21+H21 -> 348611.42 | J21: =Dashboard!$C$13*A21 -> 3800 | K21: =Dashboard!$C$14*A21 -> 5700 | L21: =Dashboard!$C$21-K21 -> 1494300 | M21: =L21-I21-J21 -> 1141888.6 | N21: =J21+K21 -> 9500 | O21: =Dashboard!$C$15*(Dashboard!$C$16*EXP(-Dashboard!$C$16*A21)*E21-(1-EXP(-Dashboard!$C$16*A21))*Dashboard!$C$17/Dashboard!$C$19*E21*(1-E21)) -> 0.34370513 | P21: =Dashboard!$C$9*B21*Dashboard!$C$11*(-Dashboard!$C$12*(1-F21)-O21)+2*Dashboard!$C$20*A21 -> -247509.78 | Q21: =-P21-Dashboard!$C$13-Dashboard!$C$14 -> 197509.78
A22: =(22-2)/100 -> 0.2 | B22: =Dashboard!$C$10*EXP(-Dashboard!$C$12*A22) -> 0.18647876 | C22: =Dashboard!$C$17*A22 -> 160 | D22: =Dashboard!$C$15*(1-EXP(-Dashboard!$C$16*A22)) -> 0.076130066 | E22: =1/(1+EXP(MIN(700,MAX(-700,(C22-Dashboard!$C$18)/Dashboard!$C$19)))) -> 0.95549664 | F22: =D22*E22 -> 0.072742022 | G22: =Dashboard!$C$9*B22*Dashboard!$C$11*(1-F22) -> 345827.84 | H22: =Dashboard!$C$20*A22^2 -> 320 | I22: =G22+H22 -> 346147.84 | J22: =Dashboard!$C$13*A22 -> 4000 | K22: =Dashboard!$C$14*A22 -> 6000 | L22: =Dashboard!$C$21-K22 -> 1494000 | M22: =L22-I22-J22 -> 1143852.2 | N22: =J22+K22 -> 10000 | O22: =Dashboard!$C$15*(Dashboard!$C$16*EXP(-Dashboard!$C$16*A22)*E22-(1-EXP(-Dashboard!$C$16*A22))*Dashboard!$C$17/Dashboard!$C$19*E22*(1-E22)) -> 0.34151129 | P22: =Dashboard!$C$9*B22*Dashboard!$C$11*(-Dashboard!$C$12*(1-F22)-O22)+2*Dashboard!$C$20*A22 -> -245208.95 | Q22: =-P22-Dashboard!$C$13-Dashboard!$C$14 -> 195208.95
A23: =(23-2)/100 -> 0.21 | B23: =Dashboard!$C$10*EXP(-Dashboard!$C$12*A23) -> 0.18582723 | C23: =Dashboard!$C$17*A23 -> 168 | D23: =Dashboard!$C$15*(1-EXP(-Dashboard!$C$16*A23)) -> 0.079740382 | E23: =1/(1+EXP(MIN(700,MAX(-700,(C23-Dashboard!$C$18)/Dashboard!$C$19)))) -> 0.95492622 | F23: =D23*E23 -> 0.076146181 | G23: =Dashboard!$C$9*B23*Dashboard!$C$11*(1-F23) -> 343354.39 | H23: =Dashboard!$C$20*A23^2 -> 352.8 | I23: =G23+H23 -> 343707.19 | J23: =Dashboard!$C$13*A23 -> 4200 | K23: =Dashboard!$C$14*A23 -> 6300 | L23: =Dashboard!$C$21-K23 -> 1493700 | M23: =L23-I23-J23 -> 1145792.8 | N23: =J23+K23 -> 10500 | O23: =Dashboard!$C$15*(Dashboard!$C$16*EXP(-Dashboard!$C$16*A23)*E23-(1-EXP(-Dashboard!$C$16*A23))*Dashboard!$C$17/Dashboard!$C$19*E23*(1-E23)) -> 0.33932113 | P23: =Dashboard!$C$9*B23*Dashboard!$C$11*(-Dashboard!$C$12*(1-F23)-O23)+2*Dashboard!$C$20*A23 -> -242924.25 | Q23: =-P23-Dashboard!$C$13-Dashboard!$C$14 -> 192924.25
A24: =(24-2)/100 -> 0.22 | B24: =Dashboard!$C$10*EXP(-Dashboard!$C$12*A24) -> 0.18517797 | C24: =Dashboard!$C$17*A24 -> 176 | D24: =Dashboard!$C$15*(1-EXP(-Dashboard!$C$16*A24)) -> 0.083332692 | E24: =1/(1+EXP(MIN(700,MAX(-700,(C24-Dashboard!$C$18)/Dashboard!$C$19)))) -> 0.95434883 | F24: =D24*E24 -> 0.079528457 | G24: =Dashboard!$C$9*B24*Dashboard!$C$11*(1-F24) -> 340902.1 | H24: =Dashboard!$C$20*A24^2 -> 387.2 | I24: =G24+H24 -> 341289.3 | J24: =Dashboard!$C$13*A24 -> 4400 | K24: =Dashboard!$C$14*A24 -> 6600 | L24: =Dashboard!$C$21-K24 -> 1493400 | M24: =L24-I24-J24 -> 1147710.7 | N24: =J24+K24 -> 11000 | O24: =Dashboard!$C$15*(Dashboard!$C$16*EXP(-Dashboard!$C$16*A24)*E24-(1-EXP(-Dashboard!$C$16*A24))*Dashboard!$C$17/Dashboard!$C$19*E24*(1-E24)) -> 0.33713455 | P24: =Dashboard!$C$9*B24*Dashboard!$C$11*(-Dashboard!$C$12*(1-F24)-O24)+2*Dashboard!$C$20*A24 -> -240655.52 | Q24: =-P24-Dashboard!$C$13-Dashboard!$C$14 -> 190655.52
A25: =(25-2)/100 -> 0.23 | B25: =Dashboard!$C$10*EXP(-Dashboard!$C$12*A25) -> 0.18453098 | C25: =Dashboard!$C$17*A25 -> 184 | D25: =Dashboard!$C$15*(1-EXP(-Dashboard!$C$16*A25)) -> 0.086907085 | E25: =1/(1+EXP(MIN(700,MAX(-700,(C25-Dashboard!$C$18)/Dashboard!$C$19)))) -> 0.9537644 | F25: =D25*E25 -> 0.082888884 | G25: =Dashboard!$C$9*B25*Dashboard!$C$11*(1-F25) -> 338470.83 | H25: =Dashboard!$C$20*A25^2 -> 423.2 | I25: =G25+H25 -> 338894.03 | J25: =Dashboard!$C$13*A25 -> 4600 | K25: =Dashboard!$C$14*A25 -> 6900 | L25: =Dashboard!$C$21-K25 -> 1493100 | M25: =L25-I25-J25 -> 1149606 | N25: =J25+K25 -> 11500 | O25: =Dashboard!$C$15*(Dashboard!$C$16*EXP(-Dashboard!$C$16*A25)*E25-(1-EXP(-Dashboard!$C$16*A25))*Dashboard!$C$17/Dashboard!$C$19*E25*(1-E25)) -> 0.33495143 | P25: =Dashboard!$C$9*B25*Dashboard!$C$11*(-Dashboard!$C$12*(1-F25)-O25)+2*Dashboard!$C$20*A25 -> -238402.62 | Q25: =-P25-Dashboard!$C$13-Dashboard!$C$14 -> 188402.62
A26: =(26-2)/100 -> 0.24 | B26: =Dashboard!$C$10*EXP(-Dashboard!$C$12*A26) -> 0.18388625 | C26: =Dashboard!$C$17*A26 -> 192 | D26: =Dashboard!$C$15*(1-EXP(-Dashboard!$C$16*A26)) -> 0.090463651 | E26: =1/(1+EXP(MIN(700,MAX(-700,(C26-Dashboard!$C$18)/Dashboard!$C$19)))) -> 0.95317286 | F26: =D26*E26 -> 0.086227497 | G26: =Dashboard!$C$9*B26*Dashboard!$C$11*(1-F26) -> 336060.4 | H26: =Dashboard!$C$20*A26^2 -> 460.8 | I26: =G26+H26 -> 336521.2 | J26: =Dashboard!$C$13*A26 -> 4800 | K26: =Dashboard!$C$14*A26 -> 7200 | L26: =Dashboard!$C$21-K26 -> 1492800 | M26: =L26-I26-J26 -> 1151478.8 | N26: =J26+K26 -> 12000 | O26: =Dashboard!$C$15*(Dashboard!$C$16*EXP(-Dashboard!$C$16*A26)*E26-(1-EXP(-Dashboard!$C$16*A26))*Dashboard!$C$17/Dashboard!$C$19*E26*(1-E26)) -> 0.33277168 | P26: =Dashboard!$C$9*B26*Dashboard!$C$11*(-Dashboard!$C$12*(1-F26)-O26)+2*Dashboard!$C$20*A26 -> -236165.41 | Q26: =-P26-Dashboard!$C$13-Dashboard!$C$14 -> 186165.41
A27: =(27-2)/100 -> 0.25 | B27: =Dashboard!$C$10*EXP(-Dashboard!$C$12*A27) -> 0.18324377 | C27: =Dashboard!$C$17*A27 -> 200 | D27: =Dashboard!$C$15*(1-EXP(-Dashboard!$C$16*A27)) -> 0.094002478 | E27: =1/(1+EXP(MIN(700,MAX(-700,(C27-Dashboard!$C$18)/Dashboard!$C$19)))) -> 0.95257413 | F27: =D27*E27 -> 0.089544328 | G27: =Dashboard!$C$9*B27*Dashboard!$C$11*(1-F27) -> 333670.67 | H27: =Dashboard!$C$20*A27^2 -> 500 | I27: =G27+H27 -> 334170.67 | J27: =Dashboard!$C$13*A27 -> 5000 | K27: =Dashboard!$C$14*A27 -> 7500 | L27: =Dashboard!$C$21-K27 -> 1492500 | M27: =L27-I27-J27 -> 1153329.3 | N27: =J27+K27 -> 12500 | O27: =Dashboard!$C$15*(Dashboard!$C$16*EXP(-Dashboard!$C$16*A27)*E27-(1-EXP(-Dashboard!$C$16*A27))*Dashboard!$C$17/Dashboard!$C$19*E27*(1-E27)) -> 0.3305952 | P27: =Dashboard!$C$9*B27*Dashboard!$C$11*(-Dashboard!$C$12*(1-F27)-O27)+2*Dashboard!$C$20*A27 -> -233943.76 | Q27: =-P27-Dashboard!$C$13-Dashboard!$C$14 -> 183943.76
A28: =(28-2)/100 -> 0.26 | B28: =Dashboard!$C$10*EXP(-Dashboard!$C$12*A28) -> 0.18260354 | C28: =Dashboard!$C$17*A28 -> 208 | D28: =Dashboard!$C$15*(1-EXP(-Dashboard!$C$16*A28)) -> 0.097523655 | E28: =1/(1+EXP(MIN(700,MAX(-700,(C28-Dashboard!$C$18)/Dashboard!$C$19)))) -> 0.95196812 | F28: =D28*E28 -> 0.092839411 | G28: =Dashboard!$C$9*B28*Dashboard!$C$11*(1-F28) -> 331301.47 | H28: =Dashboard!$C$20*A28^2 -> 540.8 | I28: =G28+H28 -> 331842.27 | J28: =Dashboard!$C$13*A28 -> 5200 | K28: =Dashboard!$C$14*A28 -> 7800 | L28: =Dashboard!$C$21-K28 -> 1492200 | M28: =L28-I28-J28 -> 1155157.7 | N28: =J28+K28 -> 13000 | O28: =Dashboard!$C$15*(Dashboard!$C$16*EXP(-Dashboard!$C$16*A28)*E28-(1-EXP(-Dashboard!$C$16*A28))*Dashboard!$C$17/Dashboard!$C$19*E28*(1-E28)) -> 0.32842188 | P28: =Dashboard!$C$9*B28*Dashboard!$C$11*(-Dashboard!$C$12*(1-F28)-O28)+2*Dashboard!$C$20*A28 -> -231737.51 | Q28: =-P28-Dashboard!$C$13-Dashboard!$C$14 -> 181737.51
A29: =(29-2)/100 -> 0.27 | B29: =Dashboard!$C$10*EXP(-Dashboard!$C$12*A29) -> 0.18196555 | C29: =Dashboard!$C$17*A29 -> 216 | D29: =Dashboard!$C$15*(1-EXP(-Dashboard!$C$16*A29)) -> 0.10102727 | E29: =1/(1+EXP(MIN(700,MAX(-700,(C29-Dashboard!$C$18)/Dashboard!$C$19)))) -> 0.95135477 | F29: =D29*E29 -> 0.096112776 | G29: =Dashboard!$C$9*B29*Dashboard!$C$11*(1-F29) -> 328952.67 | H29: =Dashboard!$C$20*A29^2 -> 583.2 | I29: =G29+H29 -> 329535.87 | J29: =Dashboard!$C$13*A29 -> 5400 | K29: =Dashboard!$C$14*A29 -> 8100 | L29: =Dashboard!$C$21-K29 -> 1491900 | M29: =L29-I29-J29 -> 1156964.1 | N29: =J29+K29 -> 13500 | O29: =Dashboard!$C$15*(Dashboard!$C$16*EXP(-Dashboard!$C$16*A29)*E29-(1-EXP(-Dashboard!$C$16*A29))*Dashboard!$C$17/Dashboard!$C$19*E29*(1-E29)) -> 0.32625162 | P29: =Dashboard!$C$9*B29*Dashboard!$C$11*(-Dashboard!$C$12*(1-F29)-O29)+2*Dashboard!$C$20*A29 -> -229546.54 | Q29: =-P29-Dashboard!$C$13-Dashboard!$C$14 -> 179546.54
A30: =(30-2)/100 -> 0.28 | B30: =Dashboard!$C$10*EXP(-Dashboard!$C$12*A30) -> 0.18132978 | C30: =Dashboard!$C$17*A30 -> 224 | D30: =Dashboard!$C$15*(1-EXP(-Dashboard!$C$16*A30)) -> 0.10451341 | E30: =1/(1+EXP(MIN(700,MAX(-700,(C30-Dashboard!$C$18)/Dashboard!$C$19)))) -> 0.95073399 | F30: =D30*E30 -> 0.099364453 | G30: =Dashboard!$C$9*B30*Dashboard!$C$11*(1-F30) -> 326624.09 | H30: =Dashboard!$C$20*A30^2 -> 627.2 | I30: =G30+H30 -> 327251.29 | J30: =Dashboard!$C$13*A30 -> 5600 | K30: =Dashboard!$C$14*A30 -> 8400 | L30: =Dashboard!$C$21-K30 -> 1491600 | M30: =L30-I30-J30 -> 1158748.7 | N30: =J30+K30 -> 14000 | O30: =Dashboard!$C$15*(Dashboard!$C$16*EXP(-Dashboard!$C$16*A30)*E30-(1-EXP(-Dashboard!$C$16*A30))*Dashboard!$C$17/Dashboard!$C$19*E30*(1-E30)) -> 0.32408432 | P30: =Dashboard!$C$9*B30*Dashboard!$C$11*(-Dashboard!$C$12*(1-F30)-O30)+2*Dashboard!$C$20*A30 -> -227370.71 | Q30: =-P30-Dashboard!$C$13-Dashboard!$C$14 -> 177370.71
A31: =(31-2)/100 -> 0.29 | B31: =Dashboard!$C$10*EXP(-Dashboard!$C$12*A31) -> 0.18069624 | C31: =Dashboard!$C$17*A31 -> 232 | D31: =Dashboard!$C$15*(1-EXP(-Dashboard!$C$16*A31)) -> 0.10798217 | E31: =1/(1+EXP(MIN(700,MAX(-700,(C31-Dashboard!$C$18)/Dashboard!$C$19)))) -> 0.95010571 | F31: =D31*E31 -> 0.10259447 | G31: =Dashboard!$C$9*B31*Dashboard!$C$11*(1-F31) -> 324315.6 | H31: =Dashboard!$C$20*A31^2 -> 672.8 | I31: =G31+H31 -> 324988.4 | J31: =Dashboard!$C$13*A31 -> 5800 | K31: =Dashboard!$C$14*A31 -> 8700 | L31: =Dashboard!$C$21-K31 -> 1491300 | M31: =L31-I31-J31 -> 1160511.6 | N31: =J31+K31 -> 14500 | O31: =Dashboard!$C$15*(Dashboard!$C$16*EXP(-Dashboard!$C$16*A31)*E31-(1-EXP(-Dashboard!$C$16*A31))*Dashboard!$C$17/Dashboard!$C$19*E31*(1-E31)) -> 0.32191988 | P31: =Dashboard!$C$9*B31*Dashboard!$C$11*(-Dashboard!$C$12*(1-F31)-O31)+2*Dashboard!$C$20*A31 -> -225209.88 | Q31: =-P31-Dashboard!$C$13-Dashboard!$C$14 -> 175209.88
A32: =(32-2)/100 -> 0.3 | B32: =Dashboard!$C$10*EXP(-Dashboard!$C$12*A32) -> 0.1800649 | C32: =Dashboard!$C$17*A32 -> 240 | D32: =Dashboard!$C$15*(1-EXP(-Dashboard!$C$16*A32)) -> 0.11143362 | E32: =1/(1+EXP(MIN(700,MAX(-700,(C32-Dashboard!$C$18)/Dashboard!$C$19)))) -> 0.94946984 | F32: =D32*E32 -> 0.10580286 | G32: =Dashboard!$C$9*B32*Dashboard!$C$11*(1-F32) -> 322027.05 | H32: =Dashboard!$C$20*A32^2 -> 720 | I32: =G32+H32 -> 322747.05 | J32: =Dashboard!$C$13*A32 -> 6000 | K32: =Dashboard!$C$14*A32 -> 9000 | L32: =Dashboard!$C$21-K32 -> 1491000 | M32: =L32-I32-J32 -> 1162253 | N32: =J32+K32 -> 15000 | O32: =Dashboard!$C$15*(Dashboard!$C$16*EXP(-Dashboard!$C$16*A32)*E32-(1-EXP(-Dashboard!$C$16*A32))*Dashboard!$C$17/Dashboard!$C$19*E32*(1-E32)) -> 0.31975819 | P32: =Dashboard!$C$9*B32*Dashboard!$C$11*(-Dashboard!$C$12*(1-F32)-O32)+2*Dashboard!$C$20*A32 -> -223063.92 | Q32: =-P32-Dashboard!$C$13-Dashboard!$C$14 -> 173063.92
A33: =(33-2)/100 -> 0.31 | B33: =Dashboard!$C$10*EXP(-Dashboard!$C$12*A33) -> 0.17943578 | C33: =Dashboard!$C$17*A33 -> 248 | D33: =Dashboard!$C$15*(1-EXP(-Dashboard!$C$16*A33)) -> 0.11486786 | E33: =1/(1+EXP(MIN(700,MAX(-700,(C33-Dashboard!$C$18)/Dashboard!$C$19)))) -> 0.9488263 | F33: =D33*E33 -> 0.10898964 | G33: =Dashboard!$C$9*B33*Dashboard!$C$11*(1-F33) -> 319758.27 | H33: =Dashboard!$C$20*A33^2 -> 768.8 | I33: =G33+H33 -> 320527.07 | J33: =Dashboard!$C$13*A33 -> 6200 | K33: =Dashboard!$C$14*A33 -> 9300 | L33: =Dashboard!$C$21-K33 -> 1490700 | M33: =L33-I33-J33 -> 1163972.9 | N33: =J33+K33 -> 15500 | O33: =Dashboard!$C$15*(Dashboard!$C$16*EXP(-Dashboard!$C$16*A33)*E33-(1-EXP(-Dashboard!$C$16*A33))*Dashboard!$C$17/Dashboard!$C$19*E33*(1-E33)) -> 0.31759916 | P33: =Dashboard!$C$9*B33*Dashboard!$C$11*(-Dashboard!$C$12*(1-F33)-O33)+2*Dashboard!$C$20*A33 -> -220932.7 | Q33: =-P33-Dashboard!$C$13-Dashboard!$C$14 -> 170932.7
A34: =(34-2)/100 -> 0.32 | B34: =Dashboard!$C$10*EXP(-Dashboard!$C$12*A34) -> 0.17880885 | C34: =Dashboard!$C$17*A34 -> 256 | D34: =Dashboard!$C$15*(1-EXP(-Dashboard!$C$16*A34)) -> 0.11828497 | E34: =1/(1+EXP(MIN(700,MAX(-700,(C34-Dashboard!$C$18)/Dashboard!$C$19)))) -> 0.94817501 | F34: =D34*E34 -> 0.11215485 | G34: =Dashboard!$C$9*B34*Dashboard!$C$11*(1-F34) -> 317509.14 | H34: =Dashboard!$C$20*A34^2 -> 819.2 | I34: =G34+H34 -> 318328.34 | J34: =Dashboard!$C$13*A34 -> 6400 | K34: =Dashboard!$C$14*A34 -> 9600 | L34: =Dashboard!$C$21-K34 -> 1490400 | M34: =L34-I34-J34 -> 1165671.7 | N34: =J34+K34 -> 16000 | O34: =Dashboard!$C$15*(Dashboard!$C$16*EXP(-Dashboard!$C$16*A34)*E34-(1-EXP(-Dashboard!$C$16*A34))*Dashboard!$C$17/Dashboard!$C$19*E34*(1-E34)) -> 0.31544268 | P34: =Dashboard!$C$9*B34*Dashboard!$C$11*(-Dashboard!$C$12*(1-F34)-O34)+2*Dashboard!$C$20*A34 -> -218816.09 | Q34: =-P34-Dashboard!$C$13-Dashboard!$C$14 -> 168816.09
A35: =(35-2)/100 -> 0.33 | B35: =Dashboard!$C$10*EXP(-Dashboard!$C$12*A35) -> 0.17818411 | C35: =Dashboard!$C$17*A35 -> 264 | D35: =Dashboard!$C$15*(1-EXP(-Dashboard!$C$16*A35)) -> 0.12168504 | E35: =1/(1+EXP(MIN(700,MAX(-700,(C35-Dashboard!$C$18)/Dashboard!$C$19)))) -> 0.94751589 | F35: =D35*E35 -> 0.11529851 | G35: =Dashboard!$C$9*B35*Dashboard!$C$11*(1-F35) -> 315279.5 | H35: =Dashboard!$C$20*A35^2 -> 871.2 | I35: =G35+H35 -> 316150.7 | J35: =Dashboard!$C$13*A35 -> 6600 | K35: =Dashboard!$C$14*A35 -> 9900 | L35: =Dashboard!$C$21-K35 -> 1490100 | M35: =L35-I35-J35 -> 1167349.3 | N35: =J35+K35 -> 16500 | O35: =Dashboard!$C$15*(Dashboard!$C$16*EXP(-Dashboard!$C$16*A35)*E35-(1-EXP(-Dashboard!$C$16*A35))*Dashboard!$C$17/Dashboard!$C$19*E35*(1-E35)) -> 0.31328865 | P35: =Dashboard!$C$9*B35*Dashboard!$C$11*(-Dashboard!$C$12*(1-F35)-O35)+2*Dashboard!$C$20*A35 -> -216713.95 | Q35: =-P35-Dashboard!$C$13-Dashboard!$C$14 -> 166713.95
A36: =(36-2)/100 -> 0.34 | B36: =Dashboard!$C$10*EXP(-Dashboard!$C$12*A36) -> 0.17756156 | C36: =Dashboard!$C$17*A36 -> 272 | D36: =Dashboard!$C$15*(1-EXP(-Dashboard!$C$16*A36)) -> 0.12506815 | E36: =1/(1+EXP(MIN(700,MAX(-700,(C36-Dashboard!$C$18)/Dashboard!$C$19)))) -> 0.94684886 | F36: =D36*E36 -> 0.11842063 | G36: =Dashboard!$C$9*B36*Dashboard!$C$11*(1-F36) -> 313069.22 | H36: =Dashboard!$C$20*A36^2 -> 924.8 | I36: =G36+H36 -> 313994.02 | J36: =Dashboard!$C$13*A36 -> 6800 | K36: =Dashboard!$C$14*A36 -> 10200 | L36: =Dashboard!$C$21-K36 -> 1489800 | M36: =L36-I36-J36 -> 1169006 | N36: =J36+K36 -> 17000 | O36: =Dashboard!$C$15*(Dashboard!$C$16*EXP(-Dashboard!$C$16*A36)*E36-(1-EXP(-Dashboard!$C$16*A36))*Dashboard!$C$17/Dashboard!$C$19*E36*(1-E36)) -> 0.31113697 | P36: =Dashboard!$C$9*B36*Dashboard!$C$11*(-Dashboard!$C$12*(1-F36)-O36)+2*Dashboard!$C$20*A36 -> -214626.16 | Q36: =-P36-Dashboard!$C$13-Dashboard!$C$14 -> 164626.16
A37: =(37-2)/100 -> 0.35 | B37: =Dashboard!$C$10*EXP(-Dashboard!$C$12*A37) -> 0.17694118 | C37: =Dashboard!$C$17*A37 -> 280 | D37: =Dashboard!$C$15*(1-EXP(-Dashboard!$C$16*A37)) -> 0.12843438 | E37: =1/(1+EXP(MIN(700,MAX(-700,(C37-Dashboard!$C$18)/Dashboard!$C$19)))) -> 0.94617384 | F37: =D37*E37 -> 0.12152125 | G37: =Dashboard!$C$9*B37*Dashboard!$C$11*(1-F37) -> 310878.13 | H37: =Dashboard!$C$20*A37^2 -> 980 | I37: =G37+H37 -> 311858.13 | J37: =Dashboard!$C$13*A37 -> 7000 | K37: =Dashboard!$C$14*A37 -> 10500 | L37: =Dashboard!$C$21-K37 -> 1489500 | M37: =L37-I37-J37 -> 1170641.9 | N37: =J37+K37 -> 17500 | O37: =Dashboard!$C$15*(Dashboard!$C$16*EXP(-Dashboard!$C$16*A37)*E37-(1-EXP(-Dashboard!$C$16*A37))*Dashboard!$C$17/Dashboard!$C$19*E37*(1-E37)) -> 0.30898754 | P37: =Dashboard!$C$9*B37*Dashboard!$C$11*(-Dashboard!$C$12*(1-F37)-O37)+2*Dashboard!$C$20*A37 -> -212552.59 | Q37: =-P37-Dashboard!$C$13-Dashboard!$C$14 -> 162552.59
A38: =(38-2)/100 -> 0.36 | B38: =Dashboard!$C$10*EXP(-Dashboard!$C$12*A38) -> 0.17632297 | C38: =Dashboard!$C$17*A38 -> 288 | D38: =Dashboard!$C$15*(1-EXP(-Dashboard!$C$16*A38)) -> 0.13178383 | E38: =1/(1+EXP(MIN(700,MAX(-700,(C38-Dashboard!$C$18)/Dashboard!$C$19)))) -> 0.94549073 | F38: =D38*E38 -> 0.12460039 | G38: =Dashboard!$C$9*B38*Dashboard!$C$11*(1-F38) -> 308706.12 | H38: =Dashboard!$C$20*A38^2 -> 1036.8 | I38: =G38+H38 -> 309742.92 | J38: =Dashboard!$C$13*A38 -> 7200 | K38: =Dashboard!$C$14*A38 -> 10800 | L38: =Dashboard!$C$21-K38 -> 1489200 | M38: =L38-I38-J38 -> 1172257.1 | N38: =J38+K38 -> 18000 | O38: =Dashboard!$C$15*(Dashboard!$C$16*EXP(-Dashboard!$C$16*A38)*E38-(1-EXP(-Dashboard!$C$16*A38))*Dashboard!$C$17/Dashboard!$C$19*E38*(1-E38)) -> 0.30684026 | P38: =Dashboard!$C$9*B38*Dashboard!$C$11*(-Dashboard!$C$12*(1-F38)-O38)+2*Dashboard!$C$20*A38 -> -210493.11 | Q38: =-P38-Dashboard!$C$13-Dashboard!$C$14 -> 160493.11
A39: =(39-2)/100 -> 0.37 | B39: =Dashboard!$C$10*EXP(-Dashboard!$C$12*A39) -> 0.17570692 | C39: =Dashboard!$C$17*A39 -> 296 | D39: =Dashboard!$C$15*(1-EXP(-Dashboard!$C$16*A39)) -> 0.13511657 | E39: =1/(1+EXP(MIN(700,MAX(-700,(C39-Dashboard!$C$18)/Dashboard!$C$19)))) -> 0.94479946 | F39: =D39*E39 -> 0.12765807 | G39: =Dashboard!$C$9*B39*Dashboard!$C$11*(1-F39) -> 306553.02 | H39: =Dashboard!$C$20*A39^2 -> 1095.2 | I39: =G39+H39 -> 307648.22 | J39: =Dashboard!$C$13*A39 -> 7400 | K39: =Dashboard!$C$14*A39 -> 11100 | L39: =Dashboard!$C$21-K39 -> 1488900 | M39: =L39-I39-J39 -> 1173851.8 | N39: =J39+K39 -> 18500 | O39: =Dashboard!$C$15*(Dashboard!$C$16*EXP(-Dashboard!$C$16*A39)*E39-(1-EXP(-Dashboard!$C$16*A39))*Dashboard!$C$17/Dashboard!$C$19*E39*(1-E39)) -> 0.30469503 | P39: =Dashboard!$C$9*B39*Dashboard!$C$11*(-Dashboard!$C$12*(1-F39)-O39)+2*Dashboard!$C$20*A39 -> -208447.61 | Q39: =-P39-Dashboard!$C$13-Dashboard!$C$14 -> 158447.61
A40: =(40-2)/100 -> 0.38 | B40: =Dashboard!$C$10*EXP(-Dashboard!$C$12*A40) -> 0.17509302 | C40: =Dashboard!$C$17*A40 -> 304 | D40: =Dashboard!$C$15*(1-EXP(-Dashboard!$C$16*A40)) -> 0.13843269 | E40: =1/(1+EXP(MIN(700,MAX(-700,(C40-Dashboard!$C$18)/Dashboard!$C$19)))) -> 0.94409994 | F40: =D40*E40 -> 0.1306943 | G40: =Dashboard!$C$9*B40*Dashboard!$C$11*(1-F40) -> 304418.72 | H40: =Dashboard!$C$20*A40^2 -> 1155.2 | I40: =G40+H40 -> 305573.92 | J40: =Dashboard!$C$13*A40 -> 7600 | K40: =Dashboard!$C$14*A40 -> 11400 | L40: =Dashboard!$C$21-K40 -> 1488600 | M40: =L40-I40-J40 -> 1175426.1 | N40: =J40+K40 -> 19000 | O40: =Dashboard!$C$15*(Dashboard!$C$16*EXP(-Dashboard!$C$16*A40)*E40-(1-EXP(-Dashboard!$C$16*A40))*Dashboard!$C$17/Dashboard!$C$19*E40*(1-E40)) -> 0.30255174 | P40: =Dashboard!$C$9*B40*Dashboard!$C$11*(-Dashboard!$C$12*(1-F40)-O40)+2*Dashboard!$C$20*A40 -> -206415.95 | Q40: =-P40-Dashboard!$C$13-Dashboard!$C$14 -> 156415.95
A41: =(41-2)/100 -> 0.39 | B41: =Dashboard!$C$10*EXP(-Dashboard!$C$12*A41) -> 0.17448126 | C41: =Dashboard!$C$17*A41 -> 312 | D41: =Dashboard!$C$15*(1-EXP(-Dashboard!$C$16*A41)) -> 0.14173227 | E41: =1/(1+EXP(MIN(700,MAX(-700,(C41-Dashboard!$C$18)/Dashboard!$C$19)))) -> 0.94339209 | F41: =D41*E41 -> 0.13370911 | G41: =Dashboard!$C$9*B41*Dashboard!$C$11*(1-F41) -> 302303.06 | H41: =Dashboard!$C$20*A41^2 -> 1216.8 | I41: =G41+H41 -> 303519.86 | J41: =Dashboard!$C$13*A41 -> 7800 | K41: =Dashboard!$C$14*A41 -> 11700 | L41: =Dashboard!$C$21-K41 -> 1488300 | M41: =L41-I41-J41 -> 1176980.1 | N41: =J41+K41 -> 19500 | O41: =Dashboard!$C$15*(Dashboard!$C$16*EXP(-Dashboard!$C$16*A41)*E41-(1-EXP(-Dashboard!$C$16*A41))*Dashboard!$C$17/Dashboard!$C$19*E41*(1-E41)) -> 0.30041029 | P41: =Dashboard!$C$9*B41*Dashboard!$C$11*(-Dashboard!$C$12*(1-F41)-O41)+2*Dashboard!$C$20*A41 -> -204398.01 | Q41: =-P41-Dashboard!$C$13-Dashboard!$C$14 -> 154398.01
A42: =(42-2)/100 -> 0.4 | B42: =Dashboard!$C$10*EXP(-Dashboard!$C$12*A42) -> 0.17387165 | C42: =Dashboard!$C$17*A42 -> 320 | D42: =Dashboard!$C$15*(1-EXP(-Dashboard!$C$16*A42)) -> 0.1450154 | E42: =1/(1+EXP(MIN(700,MAX(-700,(C42-Dashboard!$C$18)/Dashboard!$C$19)))) -> 0.94267582 | F42: =D42*E42 -> 0.13670251 | G42: =Dashboard!$C$9*B42*Dashboard!$C$11*(1-F42) -> 300205.91 | H42: =Dashboard!$C$20*A42^2 -> 1280 | I42: =G42+H42 -> 301485.91 | J42: =Dashboard!$C$13*A42 -> 8000 | K42: =Dashboard!$C$14*A42 -> 12000 | L42: =Dashboard!$C$21-K42 -> 1488000 | M42: =L42-I42-J42 -> 1178514.1 | N42: =J42+K42 -> 20000 | O42: =Dashboard!$C$15*(Dashboard!$C$16*EXP(-Dashboard!$C$16*A42)*E42-(1-EXP(-Dashboard!$C$16*A42))*Dashboard!$C$17/Dashboard!$C$19*E42*(1-E42)) -> 0.2982706 | P42: =Dashboard!$C$9*B42*Dashboard!$C$11*(-Dashboard!$C$12*(1-F42)-O42)+2*Dashboard!$C$20*A42 -> -202393.67 | Q42: =-P42-Dashboard!$C$13-Dashboard!$C$14 -> 152393.67
A43: =(43-2)/100 -> 0.41 | B43: =Dashboard!$C$10*EXP(-Dashboard!$C$12*A43) -> 0.17326416 | C43: =Dashboard!$C$17*A43 -> 328 | D43: =Dashboard!$C$15*(1-EXP(-Dashboard!$C$16*A43)) -> 0.14828215 | E43: =1/(1+EXP(MIN(700,MAX(-700,(C43-Dashboard!$C$18)/Dashboard!$C$19)))) -> 0.94195105 | F43: =D43*E43 -> 0.13967452 | G43: =Dashboard!$C$9*B43*Dashboard!$C$11*(1-F43) -> 298127.14 | H43: =Dashboard!$C$20*A43^2 -> 1344.8 | I43: =G43+H43 -> 299471.94 | J43: =Dashboard!$C$13*A43 -> 8200 | K43: =Dashboard!$C$14*A43 -> 12300 | L43: =Dashboard!$C$21-K43 -> 1487700 | M43: =L43-I43-J43 -> 1180028.1 | N43: =J43+K43 -> 20500 | O43: =Dashboard!$C$15*(Dashboard!$C$16*EXP(-Dashboard!$C$16*A43)*E43-(1-EXP(-Dashboard!$C$16*A43))*Dashboard!$C$17/Dashboard!$C$19*E43*(1-E43)) -> 0.29613254 | P43: =Dashboard!$C$9*B43*Dashboard!$C$11*(-Dashboard!$C$12*(1-F43)-O43)+2*Dashboard!$C$20*A43 -> -200402.81 | Q43: =-P43-Dashboard!$C$13-Dashboard!$C$14 -> 150402.81
A44: =(44-2)/100 -> 0.42 | B44: =Dashboard!$C$10*EXP(-Dashboard!$C$12*A44) -> 0.1726588 | C44: =Dashboard!$C$17*A44 -> 336 | D44: =Dashboard!$C$15*(1-EXP(-Dashboard!$C$16*A44)) -> 0.1515326 | E44: =1/(1+EXP(MIN(700,MAX(-700,(C44-Dashboard!$C$18)/Dashboard!$C$19)))) -> 0.94121768 | F44: =D44*E44 -> 0.14262517 | G44: =Dashboard!$C$9*B44*Dashboard!$C$11*(1-F44) -> 296066.61 | H44: =Dashboard!$C$20*A44^2 -> 1411.2 | I44: =G44+H44 -> 297477.81 | J44: =Dashboard!$C$13*A44 -> 8400 | K44: =Dashboard!$C$14*A44 -> 12600 | L44: =Dashboard!$C$21-K44 -> 1487400 | M44: =L44-I44-J44 -> 1181522.2 | N44: =J44+K44 -> 21000 | O44: =Dashboard!$C$15*(Dashboard!$C$16*EXP(-Dashboard!$C$16*A44)*E44-(1-EXP(-Dashboard!$C$16*A44))*Dashboard!$C$17/Dashboard!$C$19*E44*(1-E44)) -> 0.29399604 | P44: =Dashboard!$C$9*B44*Dashboard!$C$11*(-Dashboard!$C$12*(1-F44)-O44)+2*Dashboard!$C$20*A44 -> -198425.32 | Q44: =-P44-Dashboard!$C$13-Dashboard!$C$14 -> 148425.32
A45: =(45-2)/100 -> 0.43 | B45: =Dashboard!$C$10*EXP(-Dashboard!$C$12*A45) -> 0.17205555 | C45: =Dashboard!$C$17*A45 -> 344 | D45: =Dashboard!$C$15*(1-EXP(-Dashboard!$C$16*A45)) -> 0.15476685 | E45: =1/(1+EXP(MIN(700,MAX(-700,(C45-Dashboard!$C$18)/Dashboard!$C$19)))) -> 0.94047563 | F45: =D45*E45 -> 0.14555445 | G45: =Dashboard!$C$9*B45*Dashboard!$C$11*(1-F45) -> 294024.19 | H45: =Dashboard!$C$20*A45^2 -> 1479.2 | I45: =G45+H45 -> 295503.39 | J45: =Dashboard!$C$13*A45 -> 8600 | K45: =Dashboard!$C$14*A45 -> 12900 | L45: =Dashboard!$C$21-K45 -> 1487100 | M45: =L45-I45-J45 -> 1182996.6 | N45: =J45+K45 -> 21500 | O45: =Dashboard!$C$15*(Dashboard!$C$16*EXP(-Dashboard!$C$16*A45)*E45-(1-EXP(-Dashboard!$C$16*A45))*Dashboard!$C$17/Dashboard!$C$19*E45*(1-E45)) -> 0.29186098 | P45: =Dashboard!$C$9*B45*Dashboard!$C$11*(-Dashboard!$C$12*(1-F45)-O45)+2*Dashboard!$C$20*A45 -> -196461.07 | Q45: =-P45-Dashboard!$C$13-Dashboard!$C$14 -> 146461.07
A46: =(46-2)/100 -> 0.44 | B46: =Dashboard!$C$10*EXP(-Dashboard!$C$12*A46) -> 0.1714544 | C46: =Dashboard!$C$17*A46 -> 352 | D46: =Dashboard!$C$15*(1-EXP(-Dashboard!$C$16*A46)) -> 0.15798496 | E46: =1/(1+EXP(MIN(700,MAX(-700,(C46-Dashboard!$C$18)/Dashboard!$C$19)))) -> 0.93972482 | F46: =D46*E46 -> 0.14846239 | G46: =Dashboard!$C$9*B46*Dashboard!$C$11*(1-F46) -> 291999.75 | H46: =Dashboard!$C$20*A46^2 -> 1548.8 | I46: =G46+H46 -> 293548.55 | J46: =Dashboard!$C$13*A46 -> 8800 | K46: =Dashboard!$C$14*A46 -> 13200 | L46: =Dashboard!$C$21-K46 -> 1486800 | M46: =L46-I46-J46 -> 1184451.5 | N46: =J46+K46 -> 22000 | O46: =Dashboard!$C$15*(Dashboard!$C$16*EXP(-Dashboard!$C$16*A46)*E46-(1-EXP(-Dashboard!$C$16*A46))*Dashboard!$C$17/Dashboard!$C$19*E46*(1-E46)) -> 0.28972727 | P46: =Dashboard!$C$9*B46*Dashboard!$C$11*(-Dashboard!$C$12*(1-F46)-O46)+2*Dashboard!$C$20*A46 -> -194509.94 | Q46: =-P46-Dashboard!$C$13-Dashboard!$C$14 -> 144509.94
A47: =(47-2)/100 -> 0.45 | B47: =Dashboard!$C$10*EXP(-Dashboard!$C$12*A47) -> 0.17085536 | C47: =Dashboard!$C$17*A47 -> 360 | D47: =Dashboard!$C$15*(1-EXP(-Dashboard!$C$16*A47)) -> 0.16118702 | E47: =1/(1+EXP(MIN(700,MAX(-700,(C47-Dashboard!$C$18)/Dashboard!$C$19)))) -> 0.93896515 | F47: =D47*E47 -> 0.151349 | G47: =Dashboard!$C$9*B47*Dashboard!$C$11*(1-F47) -> 289993.15 | H47: =Dashboard!$C$20*A47^2 -> 1620 | I47: =G47+H47 -> 291613.15 | J47: =Dashboard!$C$13*A47 -> 9000 | K47: =Dashboard!$C$14*A47 -> 13500 | L47: =Dashboard!$C$21-K47 -> 1486500 | M47: =L47-I47-J47 -> 1185886.9 | N47: =J47+K47 -> 22500 | O47: =Dashboard!$C$15*(Dashboard!$C$16*EXP(-Dashboard!$C$16*A47)*E47-(1-EXP(-Dashboard!$C$16*A47))*Dashboard!$C$17/Dashboard!$C$19*E47*(1-E47)) -> 0.28759481 | P47: =Dashboard!$C$9*B47*Dashboard!$C$11*(-Dashboard!$C$12*(1-F47)-O47)+2*Dashboard!$C$20*A47 -> -192571.83 | Q47: =-P47-Dashboard!$C$13-Dashboard!$C$14 -> 142571.83
A48: =(48-2)/100 -> 0.46 | B48: =Dashboard!$C$10*EXP(-Dashboard!$C$12*A48) -> 0.17025841 | C48: =Dashboard!$C$17*A48 -> 368 | D48: =Dashboard!$C$15*(1-EXP(-Dashboard!$C$16*A48)) -> 0.16437312 | E48: =1/(1+EXP(MIN(700,MAX(-700,(C48-Dashboard!$C$18)/Dashboard!$C$19)))) -> 0.93819653 | F48: =D48*E48 -> 0.15421429 | G48: =Dashboard!$C$9*B48*Dashboard!$C$11*(1-F48) -> 288004.27 | H48: =Dashboard!$C$20*A48^2 -> 1692.8 | I48: =G48+H48 -> 289697.07 | J48: =Dashboard!$C$13*A48 -> 9200 | K48: =Dashboard!$C$14*A48 -> 13800 | L48: =Dashboard!$C$21-K48 -> 1486200 | M48: =L48-I48-J48 -> 1187302.9 | N48: =J48+K48 -> 23000 | O48: =Dashboard!$C$15*(Dashboard!$C$16*EXP(-Dashboard!$C$16*A48)*E48-(1-EXP(-Dashboard!$C$16*A48))*Dashboard!$C$17/Dashboard!$C$19*E48*(1-E48)) -> 0.2854635 | P48: =Dashboard!$C$9*B48*Dashboard!$C$11*(-Dashboard!$C$12*(1-F48)-O48)+2*Dashboard!$C$20*A48 -> -190646.62 | Q48: =-P48-Dashboard!$C$13-Dashboard!$C$14 -> 140646.62
A49: =(49-2)/100 -> 0.47 | B49: =Dashboard!$C$10*EXP(-Dashboard!$C$12*A49) -> 0.16966355 | C49: =Dashboard!$C$17*A49 -> 376 | D49: =Dashboard!$C$15*(1-EXP(-Dashboard!$C$16*A49)) -> 0.16754332 | E49: =1/(1+EXP(MIN(700,MAX(-700,(C49-Dashboard!$C$18)/Dashboard!$C$19)))) -> 0.93741888 | F49: =D49*E49 -> 0.15705827 | G49: =Dashboard!$C$9*B49*Dashboard!$C$11*(1-F49) -> 286032.97 | H49: =Dashboard!$C$20*A49^2 -> 1767.2 | I49: =G49+H49 -> 287800.17 | J49: =Dashboard!$C$13*A49 -> 9400 | K49: =Dashboard!$C$14*A49 -> 14100 | L49: =Dashboard!$C$21-K49 -> 1485900 | M49: =L49-I49-J49 -> 1188699.8 | N49: =J49+K49 -> 23500 | O49: =Dashboard!$C$15*(Dashboard!$C$16*EXP(-Dashboard!$C$16*A49)*E49-(1-EXP(-Dashboard!$C$16*A49))*Dashboard!$C$17/Dashboard!$C$19*E49*(1-E49)) -> 0.28333324 | P49: =Dashboard!$C$9*B49*Dashboard!$C$11*(-Dashboard!$C$12*(1-F49)-O49)+2*Dashboard!$C$20*A49 -> -188734.19 | Q49: =-P49-Dashboard!$C$13-Dashboard!$C$14 -> 138734.19
A50: =(50-2)/100 -> 0.48 | B50: =Dashboard!$C$10*EXP(-Dashboard!$C$12*A50) -> 0.16907077 | C50: =Dashboard!$C$17*A50 -> 384 | D50: =Dashboard!$C$15*(1-EXP(-Dashboard!$C$16*A50)) -> 0.17069771 | E50: =1/(1+EXP(MIN(700,MAX(-700,(C50-Dashboard!$C$18)/Dashboard!$C$19)))) -> 0.93663211 | F50: =D50*E50 -> 0.15988096 | G50: =Dashboard!$C$9*B50*Dashboard!$C$11*(1-F50) -> 284079.14 | H50: =Dashboard!$C$20*A50^2 -> 1843.2 | I50: =G50+H50 -> 285922.34 | J50: =Dashboard!$C$13*A50 -> 9600 | K50: =Dashboard!$C$14*A50 -> 14400 | L50: =Dashboard!$C$21-K50 -> 1485600 | M50: =L50-I50-J50 -> 1190077.7 | N50: =J50+K50 -> 24000 | O50: =Dashboard!$C$15*(Dashboard!$C$16*EXP(-Dashboard!$C$16*A50)*E50-(1-EXP(-Dashboard!$C$16*A50))*Dashboard!$C$17/Dashboard!$C$19*E50*(1-E50)) -> 0.28120394 | P50: =Dashboard!$C$9*B50*Dashboard!$C$11*(-Dashboard!$C$12*(1-F50)-O50)+2*Dashboard!$C$20*A50 -> -186834.43 | Q50: =-P50-Dashboard!$C$13-Dashboard!$C$14 -> 136834.43
A51: =(51-2)/100 -> 0.49 | B51: =Dashboard!$C$10*EXP(-Dashboard!$C$12*A51) -> 0.16848005 | C51: =Dashboard!$C$17*A51 -> 392 | D51: =Dashboard!$C$15*(1-EXP(-Dashboard!$C$16*A51)) -> 0.17383637 | E51: =1/(1+EXP(MIN(700,MAX(-700,(C51-Dashboard!$C$18)/Dashboard!$C$19)))) -> 0.93583612 | F51: =D51*E51 -> 0.16268235 | G51: =Dashboard!$C$9*B51*Dashboard!$C$11*(1-F51) -> 282142.64 | H51: =Dashboard!$C$20*A51^2 -> 1920.8 | I51: =G51+H51 -> 284063.44 | J51: =Dashboard!$C$13*A51 -> 9800 | K51: =Dashboard!$C$14*A51 -> 14700 | L51: =Dashboard!$C$21-K51 -> 1485300 | M51: =L51-I51-J51 -> 1191436.6 | N51: =J51+K51 -> 24500 | O51: =Dashboard!$C$15*(Dashboard!$C$16*EXP(-Dashboard!$C$16*A51)*E51-(1-EXP(-Dashboard!$C$16*A51))*Dashboard!$C$17/Dashboard!$C$19*E51*(1-E51)) -> 0.2790755 | P51: =Dashboard!$C$9*B51*Dashboard!$C$11*(-Dashboard!$C$12*(1-F51)-O51)+2*Dashboard!$C$20*A51 -> -184947.24 | Q51: =-P51-Dashboard!$C$13-Dashboard!$C$14 -> 134947.24
A52: =(52-2)/100 -> 0.5 | B52: =Dashboard!$C$10*EXP(-Dashboard!$C$12*A52) -> 0.1678914 | C52: =Dashboard!$C$17*A52 -> 400 | D52: =Dashboard!$C$15*(1-EXP(-Dashboard!$C$16*A52)) -> 0.17695937 | E52: =1/(1+EXP(MIN(700,MAX(-700,(C52-Dashboard!$C$18)/Dashboard!$C$19)))) -> 0.93503083 | F52: =D52*E52 -> 0.16546247 | G52: =Dashboard!$C$9*B52*Dashboard!$C$11*(1-F52) -> 280223.36 | H52: =Dashboard!$C$20*A52^2 -> 2000 | I52: =G52+H52 -> 282223.36 | J52: =Dashboard!$C$13*A52 -> 10000 | K52: =Dashboard!$C$14*A52 -> 15000 | L52: =Dashboard!$C$21-K52 -> 1485000 | M52: =L52-I52-J52 -> 1192776.6 | N52: =J52+K52 -> 25000 | O52: =Dashboard!$C$15*(Dashboard!$C$16*EXP(-Dashboard!$C$16*A52)*E52-(1-EXP(-Dashboard!$C$16*A52))*Dashboard!$C$17/Dashboard!$C$19*E52*(1-E52)) -> 0.27694782 | P52: =Dashboard!$C$9*B52*Dashboard!$C$11*(-Dashboard!$C$12*(1-F52)-O52)+2*Dashboard!$C$20*A52 -> -183072.49 | Q52: =-P52-Dashboard!$C$13-Dashboard!$C$14 -> 133072.49
A53: =(53-2)/100 -> 0.51 | B53: =Dashboard!$C$10*EXP(-Dashboard!$C$12*A53) -> 0.16730481 | C53: =Dashboard!$C$17*A53 -> 408 | D53: =Dashboard!$C$15*(1-EXP(-Dashboard!$C$16*A53)) -> 0.1800668 | E53: =1/(1+EXP(MIN(700,MAX(-700,(C53-Dashboard!$C$18)/Dashboard!$C$19)))) -> 0.93421614 | F53: =D53*E53 -> 0.16822131 | G53: =Dashboard!$C$9*B53*Dashboard!$C$11*(1-F53) -> 278321.15 | H53: =Dashboard!$C$20*A53^2 -> 2080.8 | I53: =G53+H53 -> 280401.95 | J53: =Dashboard!$C$13*A53 -> 10200 | K53: =Dashboard!$C$14*A53 -> 15300 | L53: =Dashboard!$C$21-K53 -> 1484700 | M53: =L53-I53-J53 -> 1194098 | N53: =J53+K53 -> 25500 | O53: =Dashboard!$C$15*(Dashboard!$C$16*EXP(-Dashboard!$C$16*A53)*E53-(1-EXP(-Dashboard!$C$16*A53))*Dashboard!$C$17/Dashboard!$C$19*E53*(1-E53)) -> 0.2748208 | P53: =Dashboard!$C$9*B53*Dashboard!$C$11*(-Dashboard!$C$12*(1-F53)-O53)+2*Dashboard!$C$20*A53 -> -181210.09 | Q53: =-P53-Dashboard!$C$13-Dashboard!$C$14 -> 131210.09
A54: =(54-2)/100 -> 0.52 | B54: =Dashboard!$C$10*EXP(-Dashboard!$C$12*A54) -> 0.16672027 | C54: =Dashboard!$C$17*A54 -> 416 | D54: =Dashboard!$C$15*(1-EXP(-Dashboard!$C$16*A54)) -> 0.18315873 | E54: =1/(1+EXP(MIN(700,MAX(-700,(C54-Dashboard!$C$18)/Dashboard!$C$19)))) -> 0.93339196 | F54: =D54*E54 -> 0.17095889 | G54: =Dashboard!$C$9*B54*Dashboard!$C$11*(1-F54) -> 276435.91 | H54: =Dashboard!$C$20*A54^2 -> 2163.2 | I54: =G54+H54 -> 278599.11 | J54: =Dashboard!$C$13*A54 -> 10400 | K54: =Dashboard!$C$14*A54 -> 15600 | L54: =Dashboard!$C$21-K54 -> 1484400 | M54: =L54-I54-J54 -> 1195400.9 | N54: =J54+K54 -> 26000 | O54: =Dashboard!$C$15*(Dashboard!$C$16*EXP(-Dashboard!$C$16*A54)*E54-(1-EXP(-Dashboard!$C$16*A54))*Dashboard!$C$17/Dashboard!$C$19*E54*(1-E54)) -> 0.27269436 | P54: =Dashboard!$C$9*B54*Dashboard!$C$11*(-Dashboard!$C$12*(1-F54)-O54)+2*Dashboard!$C$20*A54 -> -179359.92 | Q54: =-P54-Dashboard!$C$13-Dashboard!$C$14 -> 129359.92
A55: =(55-2)/100 -> 0.53 | B55: =Dashboard!$C$10*EXP(-Dashboard!$C$12*A55) -> 0.16613777 | C55: =Dashboard!$C$17*A55 -> 424 | D55: =Dashboard!$C$15*(1-EXP(-Dashboard!$C$16*A55)) -> 0.18623524 | E55: =1/(1+EXP(MIN(700,MAX(-700,(C55-Dashboard!$C$18)/Dashboard!$C$19)))) -> 0.93255821 | F55: =D55*E55 -> 0.1736752 | G55: =Dashboard!$C$9*B55*Dashboard!$C$11*(1-F55) -> 274567.51 | H55: =Dashboard!$C$20*A55^2 -> 2247.2 | I55: =G55+H55 -> 276814.71 | J55: =Dashboard!$C$13*A55 -> 10600 | K55: =Dashboard!$C$14*A55 -> 15900 | L55: =Dashboard!$C$21-K55 -> 1484100 | M55: =L55-I55-J55 -> 1196685.3 | N55: =J55+K55 -> 26500 | O55: =Dashboard!$C$15*(Dashboard!$C$16*EXP(-Dashboard!$C$16*A55)*E55-(1-EXP(-Dashboard!$C$16*A55))*Dashboard!$C$17/Dashboard!$C$19*E55*(1-E55)) -> 0.27056839 | P55: =Dashboard!$C$9*B55*Dashboard!$C$11*(-Dashboard!$C$12*(1-F55)-O55)+2*Dashboard!$C$20*A55 -> -177521.89 | Q55: =-P55-Dashboard!$C$13-Dashboard!$C$14 -> 127521.89
A56: =(56-2)/100 -> 0.54 | B56: =Dashboard!$C$10*EXP(-Dashboard!$C$12*A56) -> 0.1655573 | C56: =Dashboard!$C$17*A56 -> 432 | D56: =Dashboard!$C$15*(1-EXP(-Dashboard!$C$16*A56)) -> 0.1892964 | E56: =1/(1+EXP(MIN(700,MAX(-700,(C56-Dashboard!$C$18)/Dashboard!$C$19)))) -> 0.93171478 | F56: =D56*E56 -> 0.17637026 | G56: =Dashboard!$C$9*B56*Dashboard!$C$11*(1-F56) -> 272715.84 | H56: =Dashboard!$C$20*A56^2 -> 2332.8 | I56: =G56+H56 -> 275048.64 | J56: =Dashboard!$C$13*A56 -> 10800 | K56: =Dashboard!$C$14*A56 -> 16200 | L56: =Dashboard!$C$21-K56 -> 1483800 | M56: =L56-I56-J56 -> 1197951.4 | N56: =J56+K56 -> 27000 | O56: =Dashboard!$C$15*(Dashboard!$C$16*EXP(-Dashboard!$C$16*A56)*E56-(1-EXP(-Dashboard!$C$16*A56))*Dashboard!$C$17/Dashboard!$C$19*E56*(1-E56)) -> 0.26844281 | P56: =Dashboard!$C$9*B56*Dashboard!$C$11*(-Dashboard!$C$12*(1-F56)-O56)+2*Dashboard!$C$20*A56 -> -175695.88 | Q56: =-P56-Dashboard!$C$13-Dashboard!$C$14 -> 125695.88
A57: =(57-2)/100 -> 0.55 | B57: =Dashboard!$C$10*EXP(-Dashboard!$C$12*A57) -> 0.16497886 | C57: =Dashboard!$C$17*A57 -> 440 | D57: =Dashboard!$C$15*(1-EXP(-Dashboard!$C$16*A57)) -> 0.1923423 | E57: =1/(1+EXP(MIN(700,MAX(-700,(C57-Dashboard!$C$18)/Dashboard!$C$19)))) -> 0.93086158 | F57: =D57*E57 -> 0.17904406 | G57: =Dashboard!$C$9*B57*Dashboard!$C$11*(1-F57) -> 270880.76 | H57: =Dashboard!$C$20*A57^2 -> 2420 | I57: =G57+H57 -> 273300.76 | J57: =Dashboard!$C$13*A57 -> 11000 | K57: =Dashboard!$C$14*A57 -> 16500 | L57: =Dashboard!$C$21-K57 -> 1483500 | M57: =L57-I57-J57 -> 1199199.2 | N57: =J57+K57 -> 27500 | O57: =Dashboard!$C$15*(Dashboard!$C$16*EXP(-Dashboard!$C$16*A57)*E57-(1-EXP(-Dashboard!$C$16*A57))*Dashboard!$C$17/Dashboard!$C$19*E57*(1-E57)) -> 0.2663175 | P57: =Dashboard!$C$9*B57*Dashboard!$C$11*(-Dashboard!$C$12*(1-F57)-O57)+2*Dashboard!$C$20*A57 -> -173881.78 | Q57: =-P57-Dashboard!$C$13-Dashboard!$C$14 -> 123881.78
A58: =(58-2)/100 -> 0.56 | B58: =Dashboard!$C$10*EXP(-Dashboard!$C$12*A58) -> 0.16440245 | C58: =Dashboard!$C$17*A58 -> 448 | D58: =Dashboard!$C$15*(1-EXP(-Dashboard!$C$16*A58)) -> 0.19537301 | E58: =1/(1+EXP(MIN(700,MAX(-700,(C58-Dashboard!$C$18)/Dashboard!$C$19)))) -> 0.92999852 | F58: =D58*E58 -> 0.18169661 | G58: =Dashboard!$C$9*B58*Dashboard!$C$11*(1-F58) -> 269062.16 | H58: =Dashboard!$C$20*A58^2 -> 2508.8 | I58: =G58+H58 -> 271570.96 | J58: =Dashboard!$C$13*A58 -> 11200 | K58: =Dashboard!$C$14*A58 -> 16800 | L58: =Dashboard!$C$21-K58 -> 1483200 | M58: =L58-I58-J58 -> 1200429 | N58: =J58+K58 -> 28000 | O58: =Dashboard!$C$15*(Dashboard!$C$16*EXP(-Dashboard!$C$16*A58)*E58-(1-EXP(-Dashboard!$C$16*A58))*Dashboard!$C$17/Dashboard!$C$19*E58*(1-E58)) -> 0.2641924 | P58: =Dashboard!$C$9*B58*Dashboard!$C$11*(-Dashboard!$C$12*(1-F58)-O58)+2*Dashboard!$C$20*A58 -> -172079.51 | Q58: =-P58-Dashboard!$C$13-Dashboard!$C$14 -> 122079.51
A59: =(59-2)/100 -> 0.57 | B59: =Dashboard!$C$10*EXP(-Dashboard!$C$12*A59) -> 0.16382804 | C59: =Dashboard!$C$17*A59 -> 456 | D59: =Dashboard!$C$15*(1-EXP(-Dashboard!$C$16*A59)) -> 0.1983886 | E59: =1/(1+EXP(MIN(700,MAX(-700,(C59-Dashboard!$C$18)/Dashboard!$C$19)))) -> 0.92912551 | F59: =D59*E59 -> 0.18432791 | G59: =Dashboard!$C$9*B59*Dashboard!$C$11*(1-F59) -> 267259.93 | H59: =Dashboard!$C$20*A59^2 -> 2599.2 | I59: =G59+H59 -> 269859.13 | J59: =Dashboard!$C$13*A59 -> 11400 | K59: =Dashboard!$C$14*A59 -> 17100 | L59: =Dashboard!$C$21-K59 -> 1482900 | M59: =L59-I59-J59 -> 1201640.9 | N59: =J59+K59 -> 28500 | O59: =Dashboard!$C$15*(Dashboard!$C$16*EXP(-Dashboard!$C$16*A59)*E59-(1-EXP(-Dashboard!$C$16*A59))*Dashboard!$C$17/Dashboard!$C$19*E59*(1-E59)) -> 0.26206739 | P59: =Dashboard!$C$9*B59*Dashboard!$C$11*(-Dashboard!$C$12*(1-F59)-O59)+2*Dashboard!$C$20*A59 -> -170288.95 | Q59: =-P59-Dashboard!$C$13-Dashboard!$C$14 -> 120288.95
A60: =(60-2)/100 -> 0.58 | B60: =Dashboard!$C$10*EXP(-Dashboard!$C$12*A60) -> 0.16325565 | C60: =Dashboard!$C$17*A60 -> 464 | D60: =Dashboard!$C$15*(1-EXP(-Dashboard!$C$16*A60)) -> 0.20138915 | E60: =1/(1+EXP(MIN(700,MAX(-700,(C60-Dashboard!$C$18)/Dashboard!$C$19)))) -> 0.92824246 | F60: =D60*E60 -> 0.18693796 | G60: =Dashboard!$C$9*B60*Dashboard!$C$11*(1-F60) -> 265473.94 | H60: =Dashboard!$C$20*A60^2 -> 2691.2 | I60: =G60+H60 -> 268165.14 | J60: =Dashboard!$C$13*A60 -> 11600 | K60: =Dashboard!$C$14*A60 -> 17400 | L60: =Dashboard!$C$21-K60 -> 1482600 | M60: =L60-I60-J60 -> 1202834.9 | N60: =J60+K60 -> 29000 | O60: =Dashboard!$C$15*(Dashboard!$C$16*EXP(-Dashboard!$C$16*A60)*E60-(1-EXP(-Dashboard!$C$16*A60))*Dashboard!$C$17/Dashboard!$C$19*E60*(1-E60)) -> 0.25994239 | P60: =Dashboard!$C$9*B60*Dashboard!$C$11*(-Dashboard!$C$12*(1-F60)-O60)+2*Dashboard!$C$20*A60 -> -168510.01 | Q60: =-P60-Dashboard!$C$13-Dashboard!$C$14 -> 118510.01
A61: =(61-2)/100 -> 0.59 | B61: =Dashboard!$C$10*EXP(-Dashboard!$C$12*A61) -> 0.16268525 | C61: =Dashboard!$C$17*A61 -> 472 | D61: =Dashboard!$C$15*(1-EXP(-Dashboard!$C$16*A61)) -> 0.20437473 | E61: =1/(1+EXP(MIN(700,MAX(-700,(C61-Dashboard!$C$18)/Dashboard!$C$19)))) -> 0.92734926 | F61: =D61*E61 -> 0.18952675 | G61: =Dashboard!$C$9*B61*Dashboard!$C$11*(1-F61) -> 263704.09 | H61: =Dashboard!$C$20*A61^2 -> 2784.8 | I61: =G61+H61 -> 266488.89 | J61: =Dashboard!$C$13*A61 -> 11800 | K61: =Dashboard!$C$14*A61 -> 17700 | L61: =Dashboard!$C$21-K61 -> 1482300 | M61: =L61-I61-J61 -> 1204011.1 | N61: =J61+K61 -> 29500 | O61: =Dashboard!$C$15*(Dashboard!$C$16*EXP(-Dashboard!$C$16*A61)*E61-(1-EXP(-Dashboard!$C$16*A61))*Dashboard!$C$17/Dashboard!$C$19*E61*(1-E61)) -> 0.25781731 | P61: =Dashboard!$C$9*B61*Dashboard!$C$11*(-Dashboard!$C$12*(1-F61)-O61)+2*Dashboard!$C$20*A61 -> -166742.58 | Q61: =-P61-Dashboard!$C$13-Dashboard!$C$14 -> 116742.58
A62: =(62-2)/100 -> 0.6 | B62: =Dashboard!$C$10*EXP(-Dashboard!$C$12*A62) -> 0.16211685 | C62: =Dashboard!$C$17*A62 -> 480 | D62: =Dashboard!$C$15*(1-EXP(-Dashboard!$C$16*A62)) -> 0.20734542 | E62: =1/(1+EXP(MIN(700,MAX(-700,(C62-Dashboard!$C$18)/Dashboard!$C$19)))) -> 0.92644582 | F62: =D62*E62 -> 0.1920943 | G62: =Dashboard!$C$9*B62*Dashboard!$C$11*(1-F62) -> 261950.25 | H62: =Dashboard!$C$20*A62^2 -> 2880 | I62: =G62+H62 -> 264830.25 | J62: =Dashboard!$C$13*A62 -> 12000 | K62: =Dashboard!$C$14*A62 -> 18000 | L62: =Dashboard!$C$21-K62 -> 1482000 | M62: =L62-I62-J62 -> 1205169.7 | N62: =J62+K62 -> 30000 | O62: =Dashboard!$C$15*(Dashboard!$C$16*EXP(-Dashboard!$C$16*A62)*E62-(1-EXP(-Dashboard!$C$16*A62))*Dashboard!$C$17/Dashboard!$C$19*E62*(1-E62)) -> 0.25569206 | P62: =Dashboard!$C$9*B62*Dashboard!$C$11*(-Dashboard!$C$12*(1-F62)-O62)+2*Dashboard!$C$20*A62 -> -164986.57 | Q62: =-P62-Dashboard!$C$13-Dashboard!$C$14 -> 114986.57
A63: =(63-2)/100 -> 0.61 | B63: =Dashboard!$C$10*EXP(-Dashboard!$C$12*A63) -> 0.16155043 | C63: =Dashboard!$C$17*A63 -> 488 | D63: =Dashboard!$C$15*(1-EXP(-Dashboard!$C$16*A63)) -> 0.2103013 | E63: =1/(1+EXP(MIN(700,MAX(-700,(C63-Dashboard!$C$18)/Dashboard!$C$19)))) -> 0.92553205 | F63: =D63*E63 -> 0.19464059 | G63: =Dashboard!$C$9*B63*Dashboard!$C$11*(1-F63) -> 260212.32 | H63: =Dashboard!$C$20*A63^2 -> 2976.8 | I63: =G63+H63 -> 263189.12 | J63: =Dashboard!$C$13*A63 -> 12200 | K63: =Dashboard!$C$14*A63 -> 18300 | L63: =Dashboard!$C$21-K63 -> 1481700 | M63: =L63-I63-J63 -> 1206310.9 | N63: =J63+K63 -> 30500 | O63: =Dashboard!$C$15*(Dashboard!$C$16*EXP(-Dashboard!$C$16*A63)*E63-(1-EXP(-Dashboard!$C$16*A63))*Dashboard!$C$17/Dashboard!$C$19*E63*(1-E63)) -> 0.25356654 | P63: =Dashboard!$C$9*B63*Dashboard!$C$11*(-Dashboard!$C$12*(1-F63)-O63)+2*Dashboard!$C$20*A63 -> -163241.88 | Q63: =-P63-Dashboard!$C$13-Dashboard!$C$14 -> 113241.88
A64: =(64-2)/100 -> 0.62 | B64: =Dashboard!$C$10*EXP(-Dashboard!$C$12*A64) -> 0.16098599 | C64: =Dashboard!$C$17*A64 -> 496 | D64: =Dashboard!$C$15*(1-EXP(-Dashboard!$C$16*A64)) -> 0.21324244 | E64: =1/(1+EXP(MIN(700,MAX(-700,(C64-Dashboard!$C$18)/Dashboard!$C$19)))) -> 0.92460786 | F64: =D64*E64 -> 0.19716563 | G64: =Dashboard!$C$9*B64*Dashboard!$C$11*(1-F64) -> 258490.18 | H64: =Dashboard!$C$20*A64^2 -> 3075.2 | I64: =G64+H64 -> 261565.38 | J64: =Dashboard!$C$13*A64 -> 12400 | K64: =Dashboard!$C$14*A64 -> 18600 | L64: =Dashboard!$C$21-K64 -> 1481400 | M64: =L64-I64-J64 -> 1207434.6 | N64: =J64+K64 -> 31000 | O64: =Dashboard!$C$15*(Dashboard!$C$16*EXP(-Dashboard!$C$16*A64)*E64-(1-EXP(-Dashboard!$C$16*A64))*Dashboard!$C$17/Dashboard!$C$19*E64*(1-E64)) -> 0.25144068 | P64: =Dashboard!$C$9*B64*Dashboard!$C$11*(-Dashboard!$C$12*(1-F64)-O64)+2*Dashboard!$C$20*A64 -> -161508.42 | Q64: =-P64-Dashboard!$C$13-Dashboard!$C$14 -> 111508.42
A65: =(65-2)/100 -> 0.63 | B65: =Dashboard!$C$10*EXP(-Dashboard!$C$12*A65) -> 0.16042353 | C65: =Dashboard!$C$17*A65 -> 504 | D65: =Dashboard!$C$15*(1-EXP(-Dashboard!$C$16*A65)) -> 0.2161689 | E65: =1/(1+EXP(MIN(700,MAX(-700,(C65-Dashboard!$C$18)/Dashboard!$C$19)))) -> 0.92367314 | F65: =D65*E65 -> 0.19966941 | G65: =Dashboard!$C$9*B65*Dashboard!$C$11*(1-F65) -> 256783.71 | H65: =Dashboard!$C$20*A65^2 -> 3175.2 | I65: =G65+H65 -> 259958.91 | J65: =Dashboard!$C$13*A65 -> 12600 | K65: =Dashboard!$C$14*A65 -> 18900 | L65: =Dashboard!$C$21-K65 -> 1481100 | M65: =L65-I65-J65 -> 1208541.1 | N65: =J65+K65 -> 31500 | O65: =Dashboard!$C$15*(Dashboard!$C$16*EXP(-Dashboard!$C$16*A65)*E65-(1-EXP(-Dashboard!$C$16*A65))*Dashboard!$C$17/Dashboard!$C$19*E65*(1-E65)) -> 0.24931437 | P65: =Dashboard!$C$9*B65*Dashboard!$C$11*(-Dashboard!$C$12*(1-F65)-O65)+2*Dashboard!$C$20*A65 -> -159786.08 | Q65: =-P65-Dashboard!$C$13-Dashboard!$C$14 -> 109786.08
A66: =(66-2)/100 -> 0.64 | B66: =Dashboard!$C$10*EXP(-Dashboard!$C$12*A66) -> 0.15986303 | C66: =Dashboard!$C$17*A66 -> 512 | D66: =Dashboard!$C$15*(1-EXP(-Dashboard!$C$16*A66)) -> 0.21908077 | E66: =1/(1+EXP(MIN(700,MAX(-700,(C66-Dashboard!$C$18)/Dashboard!$C$19)))) -> 0.9227278 | F66: =D66*E66 -> 0.20215192 | G66: =Dashboard!$C$9*B66*Dashboard!$C$11*(1-F66) -> 255092.82 | H66: =Dashboard!$C$20*A66^2 -> 3276.8 | I66: =G66+H66 -> 258369.62 | J66: =Dashboard!$C$13*A66 -> 12800 | K66: =Dashboard!$C$14*A66 -> 19200 | L66: =Dashboard!$C$21-K66 -> 1480800 | M66: =L66-I66-J66 -> 1209630.4 | N66: =J66+K66 -> 32000 | O66: =Dashboard!$C$15*(Dashboard!$C$16*EXP(-Dashboard!$C$16*A66)*E66-(1-EXP(-Dashboard!$C$16*A66))*Dashboard!$C$17/Dashboard!$C$19*E66*(1-E66)) -> 0.24718753 | P66: =Dashboard!$C$9*B66*Dashboard!$C$11*(-Dashboard!$C$12*(1-F66)-O66)+2*Dashboard!$C$20*A66 -> -158074.78 | Q66: =-P66-Dashboard!$C$13-Dashboard!$C$14 -> 108074.78
A67: =(67-2)/100 -> 0.65 | B67: =Dashboard!$C$10*EXP(-Dashboard!$C$12*A67) -> 0.15930448 | C67: =Dashboard!$C$17*A67 -> 520 | D67: =Dashboard!$C$15*(1-EXP(-Dashboard!$C$16*A67)) -> 0.22197812 | E67: =1/(1+EXP(MIN(700,MAX(-700,(C67-Dashboard!$C$18)/Dashboard!$C$19)))) -> 0.92177174 | F67: =D67*E67 -> 0.20461316 | G67: =Dashboard!$C$9*B67*Dashboard!$C$11*(1-F67) -> 253417.38 | H67: =Dashboard!$C$20*A67^2 -> 3380 | I67: =G67+H67 -> 256797.38 | J67: =Dashboard!$C$13*A67 -> 13000 | K67: =Dashboard!$C$14*A67 -> 19500 | L67: =Dashboard!$C$21-K67 -> 1480500 | M67: =L67-I67-J67 -> 1210702.6 | N67: =J67+K67 -> 32500 | O67: =Dashboard!$C$15*(Dashboard!$C$16*EXP(-Dashboard!$C$16*A67)*E67-(1-EXP(-Dashboard!$C$16*A67))*Dashboard!$C$17/Dashboard!$C$19*E67*(1-E67)) -> 0.24506008 | P67: =Dashboard!$C$9*B67*Dashboard!$C$11*(-Dashboard!$C$12*(1-F67)-O67)+2*Dashboard!$C$20*A67 -> -156374.42 | Q67: =-P67-Dashboard!$C$13-Dashboard!$C$14 -> 106374.42
A68: =(68-2)/100 -> 0.66 | B68: =Dashboard!$C$10*EXP(-Dashboard!$C$12*A68) -> 0.15874789 | C68: =Dashboard!$C$17*A68 -> 528 | D68: =Dashboard!$C$15*(1-EXP(-Dashboard!$C$16*A68)) -> 0.22486101 | E68: =1/(1+EXP(MIN(700,MAX(-700,(C68-Dashboard!$C$18)/Dashboard!$C$19)))) -> 0.92080487 | F68: =D68*E68 -> 0.20705312 | G68: =Dashboard!$C$9*B68*Dashboard!$C$11*(1-F68) -> 251757.29 | H68: =Dashboard!$C$20*A68^2 -> 3484.8 | I68: =G68+H68 -> 255242.09 | J68: =Dashboard!$C$13*A68 -> 13200 | K68: =Dashboard!$C$14*A68 -> 19800 | L68: =Dashboard!$C$21-K68 -> 1480200 | M68: =L68-I68-J68 -> 1211757.9 | N68: =J68+K68 -> 33000 | O68: =Dashboard!$C$15*(Dashboard!$C$16*EXP(-Dashboard!$C$16*A68)*E68-(1-EXP(-Dashboard!$C$16*A68))*Dashboard!$C$17/Dashboard!$C$19*E68*(1-E68)) -> 0.24293193 | P68: =Dashboard!$C$9*B68*Dashboard!$C$11*(-Dashboard!$C$12*(1-F68)-O68)+2*Dashboard!$C$20*A68 -> -154684.92 | Q68: =-P68-Dashboard!$C$13-Dashboard!$C$14 -> 104684.92
A69: =(69-2)/100 -> 0.67 | B69: =Dashboard!$C$10*EXP(-Dashboard!$C$12*A69) -> 0.15819325 | C69: =Dashboard!$C$17*A69 -> 536 | D69: =Dashboard!$C$15*(1-EXP(-Dashboard!$C$16*A69)) -> 0.22772953 | E69: =1/(1+EXP(MIN(700,MAX(-700,(C69-Dashboard!$C$18)/Dashboard!$C$19)))) -> 0.91982709 | F69: =D69*E69 -> 0.20947179 | G69: =Dashboard!$C$9*B69*Dashboard!$C$11*(1-F69) -> 250112.45 | H69: =Dashboard!$C$20*A69^2 -> 3591.2 | I69: =G69+H69 -> 253703.65 | J69: =Dashboard!$C$13*A69 -> 13400 | K69: =Dashboard!$C$14*A69 -> 20100 | L69: =Dashboard!$C$21-K69 -> 1479900 | M69: =L69-I69-J69 -> 1212796.4 | N69: =J69+K69 -> 33500 | O69: =Dashboard!$C$15*(Dashboard!$C$16*EXP(-Dashboard!$C$16*A69)*E69-(1-EXP(-Dashboard!$C$16*A69))*Dashboard!$C$17/Dashboard!$C$19*E69*(1-E69)) -> 0.24080299 | P69: =Dashboard!$C$9*B69*Dashboard!$C$11*(-Dashboard!$C$12*(1-F69)-O69)+2*Dashboard!$C$20*A69 -> -153006.17 | Q69: =-P69-Dashboard!$C$13-Dashboard!$C$14 -> 103006.17
A70: =(70-2)/100 -> 0.68 | B70: =Dashboard!$C$10*EXP(-Dashboard!$C$12*A70) -> 0.15764054 | C70: =Dashboard!$C$17*A70 -> 544 | D70: =Dashboard!$C$15*(1-EXP(-Dashboard!$C$16*A70)) -> 0.23058374 | E70: =1/(1+EXP(MIN(700,MAX(-700,(C70-Dashboard!$C$18)/Dashboard!$C$19)))) -> 0.9188383 | F70: =D70*E70 -> 0.21186917 | G70: =Dashboard!$C$9*B70*Dashboard!$C$11*(1-F70) -> 248482.74 | H70: =Dashboard!$C$20*A70^2 -> 3699.2 | I70: =G70+H70 -> 252181.94 | J70: =Dashboard!$C$13*A70 -> 13600 | K70: =Dashboard!$C$14*A70 -> 20400 | L70: =Dashboard!$C$21-K70 -> 1479600 | M70: =L70-I70-J70 -> 1213818.1 | N70: =J70+K70 -> 34000 | O70: =Dashboard!$C$15*(Dashboard!$C$16*EXP(-Dashboard!$C$16*A70)*E70-(1-EXP(-Dashboard!$C$16*A70))*Dashboard!$C$17/Dashboard!$C$19*E70*(1-E70)) -> 0.23867318 | P70: =Dashboard!$C$9*B70*Dashboard!$C$11*(-Dashboard!$C$12*(1-F70)-O70)+2*Dashboard!$C$20*A70 -> -151338.1 | Q70: =-P70-Dashboard!$C$13-Dashboard!$C$14 -> 101338.1
A71: =(71-2)/100 -> 0.69 | B71: =Dashboard!$C$10*EXP(-Dashboard!$C$12*A71) -> 0.15708976 | C71: =Dashboard!$C$17*A71 -> 552 | D71: =Dashboard!$C$15*(1-EXP(-Dashboard!$C$16*A71)) -> 0.23342372 | E71: =1/(1+EXP(MIN(700,MAX(-700,(C71-Dashboard!$C$18)/Dashboard!$C$19)))) -> 0.9178384 | F71: =D71*E71 -> 0.21424525 | G71: =Dashboard!$C$9*B71*Dashboard!$C$11*(1-F71) -> 246868.05 | H71: =Dashboard!$C$20*A71^2 -> 3808.8 | I71: =G71+H71 -> 250676.85 | J71: =Dashboard!$C$13*A71 -> 13800 | K71: =Dashboard!$C$14*A71 -> 20700 | L71: =Dashboard!$C$21-K71 -> 1479300 | M71: =L71-I71-J71 -> 1214823.1 | N71: =J71+K71 -> 34500 | O71: =Dashboard!$C$15*(Dashboard!$C$16*EXP(-Dashboard!$C$16*A71)*E71-(1-EXP(-Dashboard!$C$16*A71))*Dashboard!$C$17/Dashboard!$C$19*E71*(1-E71)) -> 0.23654243 | P71: =Dashboard!$C$9*B71*Dashboard!$C$11*(-Dashboard!$C$12*(1-F71)-O71)+2*Dashboard!$C$20*A71 -> -149680.6 | Q71: =-P71-Dashboard!$C$13-Dashboard!$C$14 -> 99680.604
A72: =(72-2)/100 -> 0.7 | B72: =Dashboard!$C$10*EXP(-Dashboard!$C$12*A72) -> 0.15654091 | C72: =Dashboard!$C$17*A72 -> 560 | D72: =Dashboard!$C$15*(1-EXP(-Dashboard!$C$16*A72)) -> 0.23624953 | E72: =1/(1+EXP(MIN(700,MAX(-700,(C72-Dashboard!$C$18)/Dashboard!$C$19)))) -> 0.9168273 | F72: =D72*E72 -> 0.21660002 | G72: =Dashboard!$C$9*B72*Dashboard!$C$11*(1-F72) -> 245268.29 | H72: =Dashboard!$C$20*A72^2 -> 3920 | I72: =G72+H72 -> 249188.29 | J72: =Dashboard!$C$13*A72 -> 14000 | K72: =Dashboard!$C$14*A72 -> 21000 | L72: =Dashboard!$C$21-K72 -> 1479000 | M72: =L72-I72-J72 -> 1215811.7 | N72: =J72+K72 -> 35000 | O72: =Dashboard!$C$15*(Dashboard!$C$16*EXP(-Dashboard!$C$16*A72)*E72-(1-EXP(-Dashboard!$C$16*A72))*Dashboard!$C$17/Dashboard!$C$19*E72*(1-E72)) -> 0.23441064 | P72: =Dashboard!$C$9*B72*Dashboard!$C$11*(-Dashboard!$C$12*(1-F72)-O72)+2*Dashboard!$C$20*A72 -> -148033.61 | Q72: =-P72-Dashboard!$C$13-Dashboard!$C$14 -> 98033.608
A73: =(73-2)/100 -> 0.71 | B73: =Dashboard!$C$10*EXP(-Dashboard!$C$12*A73) -> 0.15599397 | C73: =Dashboard!$C$17*A73 -> 568 | D73: =Dashboard!$C$15*(1-EXP(-Dashboard!$C$16*A73)) -> 0.23906125 | E73: =1/(1+EXP(MIN(700,MAX(-700,(C73-Dashboard!$C$18)/Dashboard!$C$19)))) -> 0.9158049 | F73: =D73*E73 -> 0.21893346 | G73: =Dashboard!$C$9*B73*Dashboard!$C$11*(1-F73) -> 243683.34 | H73: =Dashboard!$C$20*A73^2 -> 4032.8 | I73: =G73+H73 -> 247716.14 | J73: =Dashboard!$C$13*A73 -> 14200 | K73: =Dashboard!$C$14*A73 -> 21300 | L73: =Dashboard!$C$21-K73 -> 1478700 | M73: =L73-I73-J73 -> 1216783.9 | N73: =J73+K73 -> 35500 | O73: =Dashboard!$C$15*(Dashboard!$C$16*EXP(-Dashboard!$C$16*A73)*E73-(1-EXP(-Dashboard!$C$16*A73))*Dashboard!$C$17/Dashboard!$C$19*E73*(1-E73)) -> 0.23227773 | P73: =Dashboard!$C$9*B73*Dashboard!$C$11*(-Dashboard!$C$12*(1-F73)-O73)+2*Dashboard!$C$20*A73 -> -146397.02 | Q73: =-P73-Dashboard!$C$13-Dashboard!$C$14 -> 96397.023
A74: =(74-2)/100 -> 0.72 | B74: =Dashboard!$C$10*EXP(-Dashboard!$C$12*A74) -> 0.15544895 | C74: =Dashboard!$C$17*A74 -> 576 | D74: =Dashboard!$C$15*(1-EXP(-Dashboard!$C$16*A74)) -> 0.24185894 | E74: =1/(1+EXP(MIN(700,MAX(-700,(C74-Dashboard!$C$18)/Dashboard!$C$19)))) -> 0.9147711 | F74: =D74*E74 -> 0.22124557 | G74: =Dashboard!$C$9*B74*Dashboard!$C$11*(1-F74) -> 242113.11 | H74: =Dashboard!$C$20*A74^2 -> 4147.2 | I74: =G74+H74 -> 246260.31 | J74: =Dashboard!$C$13*A74 -> 14400 | K74: =Dashboard!$C$14*A74 -> 21600 | L74: =Dashboard!$C$21-K74 -> 1478400 | M74: =L74-I74-J74 -> 1217739.7 | N74: =J74+K74 -> 36000 | O74: =Dashboard!$C$15*(Dashboard!$C$16*EXP(-Dashboard!$C$16*A74)*E74-(1-EXP(-Dashboard!$C$16*A74))*Dashboard!$C$17/Dashboard!$C$19*E74*(1-E74)) -> 0.23014364 | P74: =Dashboard!$C$9*B74*Dashboard!$C$11*(-Dashboard!$C$12*(1-F74)-O74)+2*Dashboard!$C$20*A74 -> -144770.76 | Q74: =-P74-Dashboard!$C$13-Dashboard!$C$14 -> 94770.762
A75: =(75-2)/100 -> 0.73 | B75: =Dashboard!$C$10*EXP(-Dashboard!$C$12*A75) -> 0.15490583 | C75: =Dashboard!$C$17*A75 -> 584 | D75: =Dashboard!$C$15*(1-EXP(-Dashboard!$C$16*A75)) -> 0.24464268 | E75: =1/(1+EXP(MIN(700,MAX(-700,(C75-Dashboard!$C$18)/Dashboard!$C$19)))) -> 0.91372581 | F75: =D75*E75 -> 0.22353633 | G75: =Dashboard!$C$9*B75*Dashboard!$C$11*(1-F75) -> 240557.49 | H75: =Dashboard!$C$20*A75^2 -> 4263.2 | I75: =G75+H75 -> 244820.69 | J75: =Dashboard!$C$13*A75 -> 14600 | K75: =Dashboard!$C$14*A75 -> 21900 | L75: =Dashboard!$C$21-K75 -> 1478100 | M75: =L75-I75-J75 -> 1218679.3 | N75: =J75+K75 -> 36500 | O75: =Dashboard!$C$15*(Dashboard!$C$16*EXP(-Dashboard!$C$16*A75)*E75-(1-EXP(-Dashboard!$C$16*A75))*Dashboard!$C$17/Dashboard!$C$19*E75*(1-E75)) -> 0.22800827 | P75: =Dashboard!$C$9*B75*Dashboard!$C$11*(-Dashboard!$C$12*(1-F75)-O75)+2*Dashboard!$C$20*A75 -> -143154.74 | Q75: =-P75-Dashboard!$C$13-Dashboard!$C$14 -> 93154.742
A76: =(76-2)/100 -> 0.74 | B76: =Dashboard!$C$10*EXP(-Dashboard!$C$12*A76) -> 0.1543646 | C76: =Dashboard!$C$17*A76 -> 592 | D76: =Dashboard!$C$15*(1-EXP(-Dashboard!$C$16*A76)) -> 0.24741254 | E76: =1/(1+EXP(MIN(700,MAX(-700,(C76-Dashboard!$C$18)/Dashboard!$C$19)))) -> 0.91266891 | F76: =D76*E76 -> 0.22580573 | G76: =Dashboard!$C$9*B76*Dashboard!$C$11*(1-F76) -> 239016.38 | H76: =Dashboard!$C$20*A76^2 -> 4380.8 | I76: =G76+H76 -> 243397.18 | J76: =Dashboard!$C$13*A76 -> 14800 | K76: =Dashboard!$C$14*A76 -> 22200 | L76: =Dashboard!$C$21-K76 -> 1477800 | M76: =L76-I76-J76 -> 1219602.8 | N76: =J76+K76 -> 37000 | O76: =Dashboard!$C$15*(Dashboard!$C$16*EXP(-Dashboard!$C$16*A76)*E76-(1-EXP(-Dashboard!$C$16*A76))*Dashboard!$C$17/Dashboard!$C$19*E76*(1-E76)) -> 0.22587155 | P76: =Dashboard!$C$9*B76*Dashboard!$C$11*(-Dashboard!$C$12*(1-F76)-O76)+2*Dashboard!$C$20*A76 -> -141548.88 | Q76: =-P76-Dashboard!$C$13-Dashboard!$C$14 -> 91548.881
A77: =(77-2)/100 -> 0.75 | B77: =Dashboard!$C$10*EXP(-Dashboard!$C$12*A77) -> 0.15382527 | C77: =Dashboard!$C$17*A77 -> 600 | D77: =Dashboard!$C$15*(1-EXP(-Dashboard!$C$16*A77)) -> 0.25016858 | E77: =1/(1+EXP(MIN(700,MAX(-700,(C77-Dashboard!$C$18)/Dashboard!$C$19)))) -> 0.91160032 | F77: =D77*E77 -> 0.22805376 | G77: =Dashboard!$C$9*B77*Dashboard!$C$11*(1-F77) -> 237489.68 | H77: =Dashboard!$C$20*A77^2 -> 4500 | I77: =G77+H77 -> 241989.68 | J77: =Dashboard!$C$13*A77 -> 15000 | K77: =Dashboard!$C$14*A77 -> 22500 | L77: =Dashboard!$C$21-K77 -> 1477500 | M77: =L77-I77-J77 -> 1220510.3 | N77: =J77+K77 -> 37500 | O77: =Dashboard!$C$15*(Dashboard!$C$16*EXP(-Dashboard!$C$16*A77)*E77-(1-EXP(-Dashboard!$C$16*A77))*Dashboard!$C$17/Dashboard!$C$19*E77*(1-E77)) -> 0.22373341 | P77: =Dashboard!$C$9*B77*Dashboard!$C$11*(-Dashboard!$C$12*(1-F77)-O77)+2*Dashboard!$C$20*A77 -> -139953.1 | Q77: =-P77-Dashboard!$C$13-Dashboard!$C$14 -> 89953.096
A78: =(78-2)/100 -> 0.76 | B78: =Dashboard!$C$10*EXP(-Dashboard!$C$12*A78) -> 0.15328783 | C78: =Dashboard!$C$17*A78 -> 608 | D78: =Dashboard!$C$15*(1-EXP(-Dashboard!$C$16*A78)) -> 0.25291087 | E78: =1/(1+EXP(MIN(700,MAX(-700,(C78-Dashboard!$C$18)/Dashboard!$C$19)))) -> 0.91051994 | F78: =D78*E78 -> 0.23028039 | G78: =Dashboard!$C$9*B78*Dashboard!$C$11*(1-F78) -> 235977.29 | H78: =Dashboard!$C$20*A78^2 -> 4620.8 | I78: =G78+H78 -> 240598.09 | J78: =Dashboard!$C$13*A78 -> 15200 | K78: =Dashboard!$C$14*A78 -> 22800 | L78: =Dashboard!$C$21-K78 -> 1477200 | M78: =L78-I78-J78 -> 1221401.9 | N78: =J78+K78 -> 38000 | O78: =Dashboard!$C$15*(Dashboard!$C$16*EXP(-Dashboard!$C$16*A78)*E78-(1-EXP(-Dashboard!$C$16*A78))*Dashboard!$C$17/Dashboard!$C$19*E78*(1-E78)) -> 0.22159378 | P78: =Dashboard!$C$9*B78*Dashboard!$C$11*(-Dashboard!$C$12*(1-F78)-O78)+2*Dashboard!$C$20*A78 -> -138367.31 | Q78: =-P78-Dashboard!$C$13-Dashboard!$C$14 -> 88367.307
A79: =(79-2)/100 -> 0.77 | B79: =Dashboard!$C$10*EXP(-Dashboard!$C$12*A79) -> 0.15275226 | C79: =Dashboard!$C$17*A79 -> 616 | D79: =Dashboard!$C$15*(1-EXP(-Dashboard!$C$16*A79)) -> 0.25563949 | E79: =1/(1+EXP(MIN(700,MAX(-700,(C79-Dashboard!$C$18)/Dashboard!$C$19)))) -> 0.90942767 | F79: =D79*E79 -> 0.23248563 | G79: =Dashboard!$C$9*B79*Dashboard!$C$11*(1-F79) -> 234479.1 | H79: =Dashboard!$C$20*A79^2 -> 4743.2 | I79: =G79+H79 -> 239222.3 | J79: =Dashboard!$C$13*A79 -> 15400 | K79: =Dashboard!$C$14*A79 -> 23100 | L79: =Dashboard!$C$21-K79 -> 1476900 | M79: =L79-I79-J79 -> 1222277.7 | N79: =J79+K79 -> 38500 | O79: =Dashboard!$C$15*(Dashboard!$C$16*EXP(-Dashboard!$C$16*A79)*E79-(1-EXP(-Dashboard!$C$16*A79))*Dashboard!$C$17/Dashboard!$C$19*E79*(1-E79)) -> 0.21945257 | P79: =Dashboard!$C$9*B79*Dashboard!$C$11*(-Dashboard!$C$12*(1-F79)-O79)+2*Dashboard!$C$20*A79 -> -136791.44 | Q79: =-P79-Dashboard!$C$13-Dashboard!$C$14 -> 86791.436
A80: =(80-2)/100 -> 0.78 | B80: =Dashboard!$C$10*EXP(-Dashboard!$C$12*A80) -> 0.15221856 | C80: =Dashboard!$C$17*A80 -> 624 | D80: =Dashboard!$C$15*(1-EXP(-Dashboard!$C$16*A80)) -> 0.2583545 | E80: =1/(1+EXP(MIN(700,MAX(-700,(C80-Dashboard!$C$18)/Dashboard!$C$19)))) -> 0.9083234 | F80: =D80*E80 -> 0.23466944 | G80: =Dashboard!$C$9*B80*Dashboard!$C$11*(1-F80) -> 232995.03 | H80: =Dashboard!$C$20*A80^2 -> 4867.2 | I80: =G80+H80 -> 237862.23 | J80: =Dashboard!$C$13*A80 -> 15600 | K80: =Dashboard!$C$14*A80 -> 23400 | L80: =Dashboard!$C$21-K80 -> 1476600 | M80: =L80-I80-J80 -> 1223137.8 | N80: =J80+K80 -> 39000 | O80: =Dashboard!$C$15*(Dashboard!$C$16*EXP(-Dashboard!$C$16*A80)*E80-(1-EXP(-Dashboard!$C$16*A80))*Dashboard!$C$17/Dashboard!$C$19*E80*(1-E80)) -> 0.21730971 | P80: =Dashboard!$C$9*B80*Dashboard!$C$11*(-Dashboard!$C$12*(1-F80)-O80)+2*Dashboard!$C$20*A80 -> -135225.4 | Q80: =-P80-Dashboard!$C$13-Dashboard!$C$14 -> 85225.402
A81: =(81-2)/100 -> 0.79 | B81: =Dashboard!$C$10*EXP(-Dashboard!$C$12*A81) -> 0.15168672 | C81: =Dashboard!$C$17*A81 -> 632 | D81: =Dashboard!$C$15*(1-EXP(-Dashboard!$C$16*A81)) -> 0.26105597 | E81: =1/(1+EXP(MIN(700,MAX(-700,(C81-Dashboard!$C$18)/Dashboard!$C$19)))) -> 0.90720705 | F81: =D81*E81 -> 0.23683181 | G81: =Dashboard!$C$9*B81*Dashboard!$C$11*(1-F81) -> 231524.96 | H81: =Dashboard!$C$20*A81^2 -> 4992.8 | I81: =G81+H81 -> 236517.76 | J81: =Dashboard!$C$13*A81 -> 15800 | K81: =Dashboard!$C$14*A81 -> 23700 | L81: =Dashboard!$C$21-K81 -> 1476300 | M81: =L81-I81-J81 -> 1223982.2 | N81: =J81+K81 -> 39500 | O81: =Dashboard!$C$15*(Dashboard!$C$16*EXP(-Dashboard!$C$16*A81)*E81-(1-EXP(-Dashboard!$C$16*A81))*Dashboard!$C$17/Dashboard!$C$19*E81*(1-E81)) -> 0.21516515 | P81: =Dashboard!$C$9*B81*Dashboard!$C$11*(-Dashboard!$C$12*(1-F81)-O81)+2*Dashboard!$C$20*A81 -> -133669.13 | Q81: =-P81-Dashboard!$C$13-Dashboard!$C$14 -> 83669.13
A82: =(82-2)/100 -> 0.8 | B82: =Dashboard!$C$10*EXP(-Dashboard!$C$12*A82) -> 0.15115675 | C82: =Dashboard!$C$17*A82 -> 640 | D82: =Dashboard!$C$15*(1-EXP(-Dashboard!$C$16*A82)) -> 0.26374396 | E82: =1/(1+EXP(MIN(700,MAX(-700,(C82-Dashboard!$C$18)/Dashboard!$C$19)))) -> 0.9060785 | F82: =D82*E82 -> 0.23897274 | G82: =Dashboard!$C$9*B82*Dashboard!$C$11*(1-F82) -> 230068.81 | H82: =Dashboard!$C$20*A82^2 -> 5120 | I82: =G82+H82 -> 235188.81 | J82: =Dashboard!$C$13*A82 -> 16000 | K82: =Dashboard!$C$14*A82 -> 24000 | L82: =Dashboard!$C$21-K82 -> 1476000 | M82: =L82-I82-J82 -> 1224811.2 | N82: =J82+K82 -> 40000 | O82: =Dashboard!$C$15*(Dashboard!$C$16*EXP(-Dashboard!$C$16*A82)*E82-(1-EXP(-Dashboard!$C$16*A82))*Dashboard!$C$17/Dashboard!$C$19*E82*(1-E82)) -> 0.2130188 | P82: =Dashboard!$C$9*B82*Dashboard!$C$11*(-Dashboard!$C$12*(1-F82)-O82)+2*Dashboard!$C$20*A82 -> -132122.54 | Q82: =-P82-Dashboard!$C$13-Dashboard!$C$14 -> 82122.542
A83: =(83-2)/100 -> 0.81 | B83: =Dashboard!$C$10*EXP(-Dashboard!$C$12*A83) -> 0.15062862 | C83: =Dashboard!$C$17*A83 -> 648 | D83: =Dashboard!$C$15*(1-EXP(-Dashboard!$C$16*A83)) -> 0.26641855 | E83: =1/(1+EXP(MIN(700,MAX(-700,(C83-Dashboard!$C$18)/Dashboard!$C$19)))) -> 0.90493767 | F83: =D83*E83 -> 0.24109218 | G83: =Dashboard!$C$9*B83*Dashboard!$C$11*(1-F83) -> 228626.48 | H83: =Dashboard!$C$20*A83^2 -> 5248.8 | I83: =G83+H83 -> 233875.28 | J83: =Dashboard!$C$13*A83 -> 16200 | K83: =Dashboard!$C$14*A83 -> 24300 | L83: =Dashboard!$C$21-K83 -> 1475700 | M83: =L83-I83-J83 -> 1225624.7 | N83: =J83+K83 -> 40500 | O83: =Dashboard!$C$15*(Dashboard!$C$16*EXP(-Dashboard!$C$16*A83)*E83-(1-EXP(-Dashboard!$C$16*A83))*Dashboard!$C$17/Dashboard!$C$19*E83*(1-E83)) -> 0.2108706 | P83: =Dashboard!$C$9*B83*Dashboard!$C$11*(-Dashboard!$C$12*(1-F83)-O83)+2*Dashboard!$C$20*A83 -> -130585.56 | Q83: =-P83-Dashboard!$C$13-Dashboard!$C$14 -> 80585.565
A84: =(84-2)/100 -> 0.82 | B84: =Dashboard!$C$10*EXP(-Dashboard!$C$12*A84) -> 0.15010235 | C84: =Dashboard!$C$17*A84 -> 656 | D84: =Dashboard!$C$15*(1-EXP(-Dashboard!$C$16*A84)) -> 0.2690798 | E84: =1/(1+EXP(MIN(700,MAX(-700,(C84-Dashboard!$C$18)/Dashboard!$C$19)))) -> 0.90378446 | F84: =D84*E84 -> 0.24319014 | G84: =Dashboard!$C$9*B84*Dashboard!$C$11*(1-F84) -> 227197.87 | H84: =Dashboard!$C$20*A84^2 -> 5379.2 | I84: =G84+H84 -> 232577.07 | J84: =Dashboard!$C$13*A84 -> 16400 | K84: =Dashboard!$C$14*A84 -> 24600 | L84: =Dashboard!$C$21-K84 -> 1475400 | M84: =L84-I84-J84 -> 1226422.9 | N84: =J84+K84 -> 41000 | O84: =Dashboard!$C$15*(Dashboard!$C$16*EXP(-Dashboard!$C$16*A84)*E84-(1-EXP(-Dashboard!$C$16*A84))*Dashboard!$C$17/Dashboard!$C$19*E84*(1-E84)) -> 0.20872048 | P84: =Dashboard!$C$9*B84*Dashboard!$C$11*(-Dashboard!$C$12*(1-F84)-O84)+2*Dashboard!$C$20*A84 -> -129058.12 | Q84: =-P84-Dashboard!$C$13-Dashboard!$C$14 -> 79058.123
A85: =(85-2)/100 -> 0.83 | B85: =Dashboard!$C$10*EXP(-Dashboard!$C$12*A85) -> 0.14957791 | C85: =Dashboard!$C$17*A85 -> 664 | D85: =Dashboard!$C$15*(1-EXP(-Dashboard!$C$16*A85)) -> 0.27172778 | E85: =1/(1+EXP(MIN(700,MAX(-700,(C85-Dashboard!$C$18)/Dashboard!$C$19)))) -> 0.90261876 | F85: =D85*E85 -> 0.24526659 | G85: =Dashboard!$C$9*B85*Dashboard!$C$11*(1-F85) -> 225782.89 | H85: =Dashboard!$C$20*A85^2 -> 5511.2 | I85: =G85+H85 -> 231294.09 | J85: =Dashboard!$C$13*A85 -> 16600 | K85: =Dashboard!$C$14*A85 -> 24900 | L85: =Dashboard!$C$21-K85 -> 1475100 | M85: =L85-I85-J85 -> 1227205.9 | N85: =J85+K85 -> 41500 | O85: =Dashboard!$C$15*(Dashboard!$C$16*EXP(-Dashboard!$C$16*A85)*E85-(1-EXP(-Dashboard!$C$16*A85))*Dashboard!$C$17/Dashboard!$C$19*E85*(1-E85)) -> 0.20656839 | P85: =Dashboard!$C$9*B85*Dashboard!$C$11*(-Dashboard!$C$12*(1-F85)-O85)+2*Dashboard!$C$20*A85 -> -127540.14 | Q85: =-P85-Dashboard!$C$13-Dashboard!$C$14 -> 77540.145
A86: =(86-2)/100 -> 0.84 | B86: =Dashboard!$C$10*EXP(-Dashboard!$C$12*A86) -> 0.1490553 | C86: =Dashboard!$C$17*A86 -> 672 | D86: =Dashboard!$C$15*(1-EXP(-Dashboard!$C$16*A86)) -> 0.27436254 | E86: =1/(1+EXP(MIN(700,MAX(-700,(C86-Dashboard!$C$18)/Dashboard!$C$19)))) -> 0.90144048 | F86: =D86*E86 -> 0.2473215 | G86: =Dashboard!$C$9*B86*Dashboard!$C$11*(1-F86) -> 224381.44 | H86: =Dashboard!$C$20*A86^2 -> 5644.8 | I86: =G86+H86 -> 230026.24 | J86: =Dashboard!$C$13*A86 -> 16800 | K86: =Dashboard!$C$14*A86 -> 25200 | L86: =Dashboard!$C$21-K86 -> 1474800 | M86: =L86-I86-J86 -> 1227973.8 | N86: =J86+K86 -> 42000 | O86: =Dashboard!$C$15*(Dashboard!$C$16*EXP(-Dashboard!$C$16*A86)*E86-(1-EXP(-Dashboard!$C$16*A86))*Dashboard!$C$17/Dashboard!$C$19*E86*(1-E86)) -> 0.20441425 | P86: =Dashboard!$C$9*B86*Dashboard!$C$11*(-Dashboard!$C$12*(1-F86)-O86)+2*Dashboard!$C$20*A86 -> -126031.56 | Q86: =-P86-Dashboard!$C$13-Dashboard!$C$14 -> 76031.557
A87: =(87-2)/100 -> 0.85 | B87: =Dashboard!$C$10*EXP(-Dashboard!$C$12*A87) -> 0.14853452 | C87: =Dashboard!$C$17*A87 -> 680 | D87: =Dashboard!$C$15*(1-EXP(-Dashboard!$C$16*A87)) -> 0.27698417 | E87: =1/(1+EXP(MIN(700,MAX(-700,(C87-Dashboard!$C$18)/Dashboard!$C$19)))) -> 0.90024951 | F87: =D87*E87 -> 0.24935487 | G87: =Dashboard!$C$9*B87*Dashboard!$C$11*(1-F87) -> 222993.42 | H87: =Dashboard!$C$20*A87^2 -> 5780 | I87: =G87+H87 -> 228773.42 | J87: =Dashboard!$C$13*A87 -> 17000 | K87: =Dashboard!$C$14*A87 -> 25500 | L87: =Dashboard!$C$21-K87 -> 1474500 | M87: =L87-I87-J87 -> 1228726.6 | N87: =J87+K87 -> 42500 | O87: =Dashboard!$C$15*(Dashboard!$C$16*EXP(-Dashboard!$C$16*A87)*E87-(1-EXP(-Dashboard!$C$16*A87))*Dashboard!$C$17/Dashboard!$C$19*E87*(1-E87)) -> 0.20225801 | P87: =Dashboard!$C$9*B87*Dashboard!$C$11*(-Dashboard!$C$12*(1-F87)-O87)+2*Dashboard!$C$20*A87 -> -124532.29 | Q87: =-P87-Dashboard!$C$13-Dashboard!$C$14 -> 74532.291
A88: =(88-2)/100 -> 0.86 | B88: =Dashboard!$C$10*EXP(-Dashboard!$C$12*A88) -> 0.14801555 | C88: =Dashboard!$C$17*A88 -> 688 | D88: =Dashboard!$C$15*(1-EXP(-Dashboard!$C$16*A88)) -> 0.27959272 | E88: =1/(1+EXP(MIN(700,MAX(-700,(C88-Dashboard!$C$18)/Dashboard!$C$19)))) -> 0.89904577 | F88: =D88*E88 -> 0.25136666 | G88: =Dashboard!$C$9*B88*Dashboard!$C$11*(1-F88) -> 221618.76 | H88: =Dashboard!$C$20*A88^2 -> 5916.8 | I88: =G88+H88 -> 227535.56 | J88: =Dashboard!$C$13*A88 -> 17200 | K88: =Dashboard!$C$14*A88 -> 25800 | L88: =Dashboard!$C$21-K88 -> 1474200 | M88: =L88-I88-J88 -> 1229464.4 | N88: =J88+K88 -> 43000 | O88: =Dashboard!$C$15*(Dashboard!$C$16*EXP(-Dashboard!$C$16*A88)*E88-(1-EXP(-Dashboard!$C$16*A88))*Dashboard!$C$17/Dashboard!$C$19*E88*(1-E88)) -> 0.20009961 | P88: =Dashboard!$C$9*B88*Dashboard!$C$11*(-Dashboard!$C$12*(1-F88)-O88)+2*Dashboard!$C$20*A88 -> -123042.27 | Q88: =-P88-Dashboard!$C$13-Dashboard!$C$14 -> 73042.275
A89: =(89-2)/100 -> 0.87 | B89: =Dashboard!$C$10*EXP(-Dashboard!$C$12*A89) -> 0.14749841 | C89: =Dashboard!$C$17*A89 -> 696 | D89: =Dashboard!$C$15*(1-EXP(-Dashboard!$C$16*A89)) -> 0.28218827 | E89: =1/(1+EXP(MIN(700,MAX(-700,(C89-Dashboard!$C$18)/Dashboard!$C$19)))) -> 0.89782915 | F89: =D89*E89 -> 0.25335685 | G89: =Dashboard!$C$9*B89*Dashboard!$C$11*(1-F89) -> 220257.35 | H89: =Dashboard!$C$20*A89^2 -> 6055.2 | I89: =G89+H89 -> 226312.55 | J89: =Dashboard!$C$13*A89 -> 17400 | K89: =Dashboard!$C$14*A89 -> 26100 | L89: =Dashboard!$C$21-K89 -> 1473900 | M89: =L89-I89-J89 -> 1230187.5 | N89: =J89+K89 -> 43500 | O89: =Dashboard!$C$15*(Dashboard!$C$16*EXP(-Dashboard!$C$16*A89)*E89-(1-EXP(-Dashboard!$C$16*A89))*Dashboard!$C$17/Dashboard!$C$19*E89*(1-E89)) -> 0.19793899 | P89: =Dashboard!$C$9*B89*Dashboard!$C$11*(-Dashboard!$C$12*(1-F89)-O89)+2*Dashboard!$C$20*A89 -> -121561.44 | Q89: =-P89-Dashboard!$C$13-Dashboard!$C$14 -> 71561.441
A90: =(90-2)/100 -> 0.88 | B90: =Dashboard!$C$10*EXP(-Dashboard!$C$12*A90) -> 0.14698306 | C90: =Dashboard!$C$17*A90 -> 704 | D90: =Dashboard!$C$15*(1-EXP(-Dashboard!$C$16*A90)) -> 0.28477086 | E90: =1/(1+EXP(MIN(700,MAX(-700,(C90-Dashboard!$C$18)/Dashboard!$C$19)))) -> 0.89659955 | F90: =D90*E90 -> 0.25532543 | G90: =Dashboard!$C$9*B90*Dashboard!$C$11*(1-F90) -> 218909.1 | H90: =Dashboard!$C$20*A90^2 -> 6195.2 | I90: =G90+H90 -> 225104.3 | J90: =Dashboard!$C$13*A90 -> 17600 | K90: =Dashboard!$C$14*A90 -> 26400 | L90: =Dashboard!$C$21-K90 -> 1473600 | M90: =L90-I90-J90 -> 1230895.7 | N90: =J90+K90 -> 44000 | O90: =Dashboard!$C$15*(Dashboard!$C$16*EXP(-Dashboard!$C$16*A90)*E90-(1-EXP(-Dashboard!$C$16*A90))*Dashboard!$C$17/Dashboard!$C$19*E90*(1-E90)) -> 0.19577609 | P90: =Dashboard!$C$9*B90*Dashboard!$C$11*(-Dashboard!$C$12*(1-F90)-O90)+2*Dashboard!$C$20*A90 -> -120089.72 | Q90: =-P90-Dashboard!$C$13-Dashboard!$C$14 -> 70089.723
A91: =(91-2)/100 -> 0.89 | B91: =Dashboard!$C$10*EXP(-Dashboard!$C$12*A91) -> 0.14646952 | C91: =Dashboard!$C$17*A91 -> 712 | D91: =Dashboard!$C$15*(1-EXP(-Dashboard!$C$16*A91)) -> 0.28734058 | E91: =1/(1+EXP(MIN(700,MAX(-700,(C91-Dashboard!$C$18)/Dashboard!$C$19)))) -> 0.89535688 | F91: =D91*E91 -> 0.25727236 | G91: =Dashboard!$C$9*B91*Dashboard!$C$11*(1-F91) -> 217573.92 | H91: =Dashboard!$C$20*A91^2 -> 6336.8 | I91: =G91+H91 -> 223910.72 | J91: =Dashboard!$C$13*A91 -> 17800 | K91: =Dashboard!$C$14*A91 -> 26700 | L91: =Dashboard!$C$21-K91 -> 1473300 | M91: =L91-I91-J91 -> 1231589.3 | N91: =J91+K91 -> 44500 | O91: =Dashboard!$C$15*(Dashboard!$C$16*EXP(-Dashboard!$C$16*A91)*E91-(1-EXP(-Dashboard!$C$16*A91))*Dashboard!$C$17/Dashboard!$C$19*E91*(1-E91)) -> 0.19361086 | P91: =Dashboard!$C$9*B91*Dashboard!$C$11*(-Dashboard!$C$12*(1-F91)-O91)+2*Dashboard!$C$20*A91 -> -118627.05 | Q91: =-P91-Dashboard!$C$13-Dashboard!$C$14 -> 68627.053
A92: =(92-2)/100 -> 0.9 | B92: =Dashboard!$C$10*EXP(-Dashboard!$C$12*A92) -> 0.14595777 | C92: =Dashboard!$C$17*A92 -> 720 | D92: =Dashboard!$C$15*(1-EXP(-Dashboard!$C$16*A92)) -> 0.28989748 | E92: =1/(1+EXP(MIN(700,MAX(-700,(C92-Dashboard!$C$18)/Dashboard!$C$19)))) -> 0.89410104 | F92: =D92*E92 -> 0.25919764 | G92: =Dashboard!$C$9*B92*Dashboard!$C$11*(1-F92) -> 216251.73 | H92: =Dashboard!$C$20*A92^2 -> 6480 | I92: =G92+H92 -> 222731.73 | J92: =Dashboard!$C$13*A92 -> 18000 | K92: =Dashboard!$C$14*A92 -> 27000 | L92: =Dashboard!$C$21-K92 -> 1473000 | M92: =L92-I92-J92 -> 1232268.3 | N92: =J92+K92 -> 45000 | O92: =Dashboard!$C$15*(Dashboard!$C$16*EXP(-Dashboard!$C$16*A92)*E92-(1-EXP(-Dashboard!$C$16*A92))*Dashboard!$C$17/Dashboard!$C$19*E92*(1-E92)) -> 0.19144325 | P92: =Dashboard!$C$9*B92*Dashboard!$C$11*(-Dashboard!$C$12*(1-F92)-O92)+2*Dashboard!$C$20*A92 -> -117173.37 | Q92: =-P92-Dashboard!$C$13-Dashboard!$C$14 -> 67173.367
A93: =(93-2)/100 -> 0.91 | B93: =Dashboard!$C$10*EXP(-Dashboard!$C$12*A93) -> 0.14544782 | C93: =Dashboard!$C$17*A93 -> 728 | D93: =Dashboard!$C$15*(1-EXP(-Dashboard!$C$16*A93)) -> 0.29244163 | E93: =1/(1+EXP(MIN(700,MAX(-700,(C93-Dashboard!$C$18)/Dashboard!$C$19)))) -> 0.89283193 | F93: =D93*E93 -> 0.26110122 | G93: =Dashboard!$C$9*B93*Dashboard!$C$11*(1-F93) -> 214942.43 | H93: =Dashboard!$C$20*A93^2 -> 6624.8 | I93: =G93+H93 -> 221567.23 | J93: =Dashboard!$C$13*A93 -> 18200 | K93: =Dashboard!$C$14*A93 -> 27300 | L93: =Dashboard!$C$21-K93 -> 1472700 | M93: =L93-I93-J93 -> 1232932.8 | N93: =J93+K93 -> 45500 | O93: =Dashboard!$C$15*(Dashboard!$C$16*EXP(-Dashboard!$C$16*A93)*E93-(1-EXP(-Dashboard!$C$16*A93))*Dashboard!$C$17/Dashboard!$C$19*E93*(1-E93)) -> 0.18927321 | P93: =Dashboard!$C$9*B93*Dashboard!$C$11*(-Dashboard!$C$12*(1-F93)-O93)+2*Dashboard!$C$20*A93 -> -115728.6 | Q93: =-P93-Dashboard!$C$13-Dashboard!$C$14 -> 65728.599
A94: =(94-2)/100 -> 0.92 | B94: =Dashboard!$C$10*EXP(-Dashboard!$C$12*A94) -> 0.14493964 | C94: =Dashboard!$C$17*A94 -> 736 | D94: =Dashboard!$C$15*(1-EXP(-Dashboard!$C$16*A94)) -> 0.29497308 | E94: =1/(1+EXP(MIN(700,MAX(-700,(C94-Dashboard!$C$18)/Dashboard!$C$19)))) -> 0.89154946 | F94: =D94*E94 -> 0.26298309 | G94: =Dashboard!$C$9*B94*Dashboard!$C$11*(1-F94) -> 213645.93 | H94: =Dashboard!$C$20*A94^2 -> 6771.2 | I94: =G94+H94 -> 220417.13 | J94: =Dashboard!$C$13*A94 -> 18400 | K94: =Dashboard!$C$14*A94 -> 27600 | L94: =Dashboard!$C$21-K94 -> 1472400 | M94: =L94-I94-J94 -> 1233582.9 | N94: =J94+K94 -> 46000 | O94: =Dashboard!$C$15*(Dashboard!$C$16*EXP(-Dashboard!$C$16*A94)*E94-(1-EXP(-Dashboard!$C$16*A94))*Dashboard!$C$17/Dashboard!$C$19*E94*(1-E94)) -> 0.18710069 | P94: =Dashboard!$C$9*B94*Dashboard!$C$11*(-Dashboard!$C$12*(1-F94)-O94)+2*Dashboard!$C$20*A94 -> -114292.69 | Q94: =-P94-Dashboard!$C$13-Dashboard!$C$14 -> 64292.688
A95: =(95-2)/100 -> 0.93 | B95: =Dashboard!$C$10*EXP(-Dashboard!$C$12*A95) -> 0.14443324 | C95: =Dashboard!$C$17*A95 -> 744 | D95: =Dashboard!$C$15*(1-EXP(-Dashboard!$C$16*A95)) -> 0.29749192 | E95: =1/(1+EXP(MIN(700,MAX(-700,(C95-Dashboard!$C$18)/Dashboard!$C$19)))) -> 0.89025352 | F95: =D95*E95 -> 0.26484323 | G95: =Dashboard!$C$9*B95*Dashboard!$C$11*(1-F95) -> 212362.14 | H95: =Dashboard!$C$20*A95^2 -> 6919.2 | I95: =G95+H95 -> 219281.34 | J95: =Dashboard!$C$13*A95 -> 18600 | K95: =Dashboard!$C$14*A95 -> 27900 | L95: =Dashboard!$C$21-K95 -> 1472100 | M95: =L95-I95-J95 -> 1234218.7 | N95: =J95+K95 -> 46500 | O95: =Dashboard!$C$15*(Dashboard!$C$16*EXP(-Dashboard!$C$16*A95)*E95-(1-EXP(-Dashboard!$C$16*A95))*Dashboard!$C$17/Dashboard!$C$19*E95*(1-E95)) -> 0.18492565 | P95: =Dashboard!$C$9*B95*Dashboard!$C$11*(-Dashboard!$C$12*(1-F95)-O95)+2*Dashboard!$C$20*A95 -> -112865.57 | Q95: =-P95-Dashboard!$C$13-Dashboard!$C$14 -> 62865.57
A96: =(96-2)/100 -> 0.94 | B96: =Dashboard!$C$10*EXP(-Dashboard!$C$12*A96) -> 0.1439286 | C96: =Dashboard!$C$17*A96 -> 752 | D96: =Dashboard!$C$15*(1-EXP(-Dashboard!$C$16*A96)) -> 0.29999819 | E96: =1/(1+EXP(MIN(700,MAX(-700,(C96-Dashboard!$C$18)/Dashboard!$C$19)))) -> 0.88894403 | F96: =D96*E96 -> 0.2666816 | G96: =Dashboard!$C$9*B96*Dashboard!$C$11*(1-F96) -> 211090.99 | H96: =Dashboard!$C$20*A96^2 -> 7068.8 | I96: =G96+H96 -> 218159.79 | J96: =Dashboard!$C$13*A96 -> 18800 | K96: =Dashboard!$C$14*A96 -> 28200 | L96: =Dashboard!$C$21-K96 -> 1471800 | M96: =L96-I96-J96 -> 1234840.2 | N96: =J96+K96 -> 47000 | O96: =Dashboard!$C$15*(Dashboard!$C$16*EXP(-Dashboard!$C$16*A96)*E96-(1-EXP(-Dashboard!$C$16*A96))*Dashboard!$C$17/Dashboard!$C$19*E96*(1-E96)) -> 0.18274804 | P96: =Dashboard!$C$9*B96*Dashboard!$C$11*(-Dashboard!$C$12*(1-F96)-O96)+2*Dashboard!$C$20*A96 -> -111447.19 | Q96: =-P96-Dashboard!$C$13-Dashboard!$C$14 -> 61447.185
A97: =(97-2)/100 -> 0.95 | B97: =Dashboard!$C$10*EXP(-Dashboard!$C$12*A97) -> 0.14342573 | C97: =Dashboard!$C$17*A97 -> 760 | D97: =Dashboard!$C$15*(1-EXP(-Dashboard!$C$16*A97)) -> 0.30249195 | E97: =1/(1+EXP(MIN(700,MAX(-700,(C97-Dashboard!$C$18)/Dashboard!$C$19)))) -> 0.88762089 | F97: =D97*E97 -> 0.26849818 | G97: =Dashboard!$C$9*B97*Dashboard!$C$11*(1-F97) -> 209832.37 | H97: =Dashboard!$C$20*A97^2 -> 7220 | I97: =G97+H97 -> 217052.37 | J97: =Dashboard!$C$13*A97 -> 19000 | K97: =Dashboard!$C$14*A97 -> 28500 | L97: =Dashboard!$C$21-K97 -> 1471500 | M97: =L97-I97-J97 -> 1235447.6 | N97: =J97+K97 -> 47500 | O97: =Dashboard!$C$15*(Dashboard!$C$16*EXP(-Dashboard!$C$16*A97)*E97-(1-EXP(-Dashboard!$C$16*A97))*Dashboard!$C$17/Dashboard!$C$19*E97*(1-E97)) -> 0.18056782 | P97: =Dashboard!$C$9*B97*Dashboard!$C$11*(-Dashboard!$C$12*(1-F97)-O97)+2*Dashboard!$C$20*A97 -> -110037.47 | Q97: =-P97-Dashboard!$C$13-Dashboard!$C$14 -> 60037.474
A98: =(98-2)/100 -> 0.96 | B98: =Dashboard!$C$10*EXP(-Dashboard!$C$12*A98) -> 0.14292462 | C98: =Dashboard!$C$17*A98 -> 768 | D98: =Dashboard!$C$15*(1-EXP(-Dashboard!$C$16*A98)) -> 0.30497329 | E98: =1/(1+EXP(MIN(700,MAX(-700,(C98-Dashboard!$C$18)/Dashboard!$C$19)))) -> 0.886284 | F98: =D98*E98 -> 0.27029294 | G98: =Dashboard!$C$9*B98*Dashboard!$C$11*(1-F98) -> 208586.21 | H98: =Dashboard!$C$20*A98^2 -> 7372.8 | I98: =G98+H98 -> 215959.01 | J98: =Dashboard!$C$13*A98 -> 19200 | K98: =Dashboard!$C$14*A98 -> 28800 | L98: =Dashboard!$C$21-K98 -> 1471200 | M98: =L98-I98-J98 -> 1236041 | N98: =J98+K98 -> 48000 | O98: =Dashboard!$C$15*(Dashboard!$C$16*EXP(-Dashboard!$C$16*A98)*E98-(1-EXP(-Dashboard!$C$16*A98))*Dashboard!$C$17/Dashboard!$C$19*E98*(1-E98)) -> 0.17838495 | P98: =Dashboard!$C$9*B98*Dashboard!$C$11*(-Dashboard!$C$12*(1-F98)-O98)+2*Dashboard!$C$20*A98 -> -108636.38 | Q98: =-P98-Dashboard!$C$13-Dashboard!$C$14 -> 58636.376
A99: =(99-2)/100 -> 0.97 | B99: =Dashboard!$C$10*EXP(-Dashboard!$C$12*A99) -> 0.14242526 | C99: =Dashboard!$C$17*A99 -> 776 | D99: =Dashboard!$C$15*(1-EXP(-Dashboard!$C$16*A99)) -> 0.30744224 | E99: =1/(1+EXP(MIN(700,MAX(-700,(C99-Dashboard!$C$18)/Dashboard!$C$19)))) -> 0.88493327 | F99: =D99*E99 -> 0.27206587 | G99: =Dashboard!$C$9*B99*Dashboard!$C$11*(1-F99) -> 207352.42 | H99: =Dashboard!$C$20*A99^2 -> 7527.2 | I99: =G99+H99 -> 214879.62 | J99: =Dashboard!$C$13*A99 -> 19400 | K99: =Dashboard!$C$14*A99 -> 29100 | L99: =Dashboard!$C$21-K99 -> 1470900 | M99: =L99-I99-J99 -> 1236620.4 | N99: =J99+K99 -> 48500 | O99: =Dashboard!$C$15*(Dashboard!$C$16*EXP(-Dashboard!$C$16*A99)*E99-(1-EXP(-Dashboard!$C$16*A99))*Dashboard!$C$17/Dashboard!$C$19*E99*(1-E99)) -> 0.1761994 | P99: =Dashboard!$C$9*B99*Dashboard!$C$11*(-Dashboard!$C$12*(1-F99)-O99)+2*Dashboard!$C$20*A99 -> -107243.84 | Q99: =-P99-Dashboard!$C$13-Dashboard!$C$14 -> 57243.835
A100: =(100-2)/100 -> 0.98 | B100: =Dashboard!$C$10*EXP(-Dashboard!$C$12*A100) -> 0.14192764 | C100: =Dashboard!$C$17*A100 -> 784 | D100: =Dashboard!$C$15*(1-EXP(-Dashboard!$C$16*A100)) -> 0.30989888 | E100: =1/(1+EXP(MIN(700,MAX(-700,(C100-Dashboard!$C$18)/Dashboard!$C$19)))) -> 0.8835686 | F100: =D100*E100 -> 0.27381692 | G100: =Dashboard!$C$9*B100*Dashboard!$C$11*(1-F100) -> 206130.9 | H100: =Dashboard!$C$20*A100^2 -> 7683.2 | I100: =G100+H100 -> 213814.1 | J100: =Dashboard!$C$13*A100 -> 19600 | K100: =Dashboard!$C$14*A100 -> 29400 | L100: =Dashboard!$C$21-K100 -> 1470600 | M100: =L100-I100-J100 -> 1237185.9 | N100: =J100+K100 -> 49000 | O100: =Dashboard!$C$15*(Dashboard!$C$16*EXP(-Dashboard!$C$16*A100)*E100-(1-EXP(-Dashboard!$C$16*A100))*Dashboard!$C$17/Dashboard!$C$19*E100*(1-E100)) -> 0.17401113 | P100: =Dashboard!$C$9*B100*Dashboard!$C$11*(-Dashboard!$C$12*(1-F100)-O100)+2*Dashboard!$C$20*A100 -> -105859.79 | Q100: =-P100-Dashboard!$C$13-Dashboard!$C$14 -> 55859.794
...

Sheet Examples
B2: Synthetic scenario presets — not estimates of the named sectors
B3: Blue columns are inputs; rows 20-26 are live per scenario. Transcribe a column into the Dashboard to explore it.
B5: parameter | C5: Summarization | D5: MCP DevOps | E5: Finance | F5: Drafting | G5: High-loss / smooth | H5: High-loss / steep
B6: lambda | C6: 25 | D6: 60 | E6: 15 | F6: 10 | G6: 40 | H6: 40
B7: q0 | C7: 0.3 | D7: 0.25 | E7: 0.15 | F7: 0.35 | G7: 0.2 | H7: 0.2
B8: L0 | C8: 80000 | D8: 400000 | E8: 1200000 | F8: 5000 | G8: 250000 | H8: 250000
B9: gamma | C9: 0.3 | D9: 0.45 | E9: 0.5 | F9: 0.3 | G9: 0.35 | H9: 0.35
B10: c | C10: 10000 | D10: 25000 | E10: 40000 | F10: 8000 | G10: 20000 | H10: 20000
B11: tau | C11: 25000 | D11: 20000 | E11: 45000 | F11: 12000 | G11: 30000 | H11: 30000
B12: h_max | C12: 0.6 | D12: 0.75 | E12: 0.85 | F12: 0.4 | G12: 0.8 | H12: 0.8
B13: kappa_d | C13: 0.4 | D13: 0.6 | E13: 0.7 | F13: 0.3 | G13: 0.5 | H13: 0.5
B14: v0 | C14: 1500 | D14: 400 | E14: 200 | F14: 600 | G14: 800 | H14: 800
B15: Ac | C15: 2500 | D15: 1500 | E15: 1000 | F15: 800 | G15: 2000 | H15: 2000
B16: s | C16: 450 | D16: 300 | E16: 250 | F16: 150 | G16: 600 | H16: 250
B17: D1 | C17: 15000 | D17: 5000 | E17: 3000 | F17: 20000 | G17: 8000 | H17: 8000
B18: B0 | C18: 600000 | D18: 2500000 | E18: 3000000 | F18: 150000 | G18: 1500000 | H18: 1500000
B20: R0 (baseline expected loss) | C20: =C6*C7*C8 -> 600000 | D20: =D6*D7*D8 -> 6000000 | E20: =E6*E7*E8 -> 2700000 | F20: =F6*F7*F8 -> 17500 | G20: =G6*G7*G8 -> 2000000 | H20: =H6*H7*H8 -> 2000000
B21: k = c + tau | C21: =C10+C11 -> 35000 | D21: =D10+D11 -> 45000 | E21: =E10+E11 -> 85000 | F21: =F10+F11 -> 20000 | G21: =G10+G11 -> 50000 | H21: =H10+H11 -> 50000
B22: q-only closed-form interior? | C22: =IF(C9*C20>C21,"Interior","Corner") -> Interior | D22: =IF(D9*D20>D21,"Interior","Corner") -> Interior | E22: =IF(E9*E20>E21,"Interior","Corner") -> Interior | F22: =IF(F9*F20>F21,"Interior","Corner") -> Corner | G22: =IF(G9*G20>G21,"Interior","Corner") -> Interior | H22: =IF(H9*H20>H21,"Interior","Corner") -> Interior
B23: z* closed form (q-only) | C23: =IF(AND(C9>0,C21>0,C9*C20>C21),LN(C9*C20/C21)/C9,0) -> 5.458696 | D23: =IF(AND(D9>0,D21>0,D9*D20>D21),LN(D9*D20/D21)/D9,0) -> 9.0985435 | E23: =IF(AND(E9>0,E21>0,E9*E20>E21),LN(E9*E20/E21)/E9,0) -> 5.5304172 | F23: =IF(AND(F9>0,F21>0,F9*F20>F21),LN(F9*F20/F21)/F9,0) -> 0 | G23: =IF(AND(G9>0,G21>0,G9*G20>G21),LN(G9*G20/G21)/G9,0) -> 7.5401638 | H23: =IF(AND(H9>0,H21>0,H9*H20>H21),LN(H9*H20/H21)/H9,0) -> 7.5401638
B24: all-in share at closed-form z* | C24: =IF(C20>0,C21*C23/C20,0) -> 0.31842393 | D24: =IF(D20>0,D21*D23/D20,0) -> 0.068239076 | E24: =IF(E20>0,E21*E23/E20,0) -> 0.17410573 | F24: =IF(F20>0,F21*F23/F20,0) -> 0 | G24: =IF(G20>0,G21*G23/G20,0) -> 0.18850409 | H24: =IF(H20>0,H21*H23/H20,0) -> 0.18850409
B25: welfare-optimal z (full model) | C25: =INDEX(ScenarioCurves!$A$2:$A$1002,MATCH(MAX(ScenarioCurves!B2:B1002),ScenarioCurves!B2:B1002,0)) -> 1.35 | D25: =INDEX(ScenarioCurves!$A$2:$A$1002,MATCH(MAX(ScenarioCurves!D2:D1002),ScenarioCurves!D2:D1002,0)) -> 6.93 | E25: =INDEX(ScenarioCurves!$A$2:$A$1002,MATCH(MAX(ScenarioCurves!F2:F1002),ScenarioCurves!F2:F1002,0)) -> 2.98 | F25: =INDEX(ScenarioCurves!$A$2:$A$1002,MATCH(MAX(ScenarioCurves!H2:H1002),ScenarioCurves!H2:H1002,0)) -> 0 | G25: =INDEX(ScenarioCurves!$A$2:$A$1002,MATCH(MAX(ScenarioCurves!J2:J1002),ScenarioCurves!J2:J1002,0)) -> 2.59 | H25: =INDEX(ScenarioCurves!$A$2:$A$1002,MATCH(MAX(ScenarioCurves!L2:L1002),ScenarioCurves!L2:L1002,0)) -> 2.02
B26: realized-risk min z (full model) | C26: =INDEX(ScenarioCurves!$A$2:$A$1002,MATCH(MIN(ScenarioCurves!C2:C1002),ScenarioCurves!C2:C1002,0)) -> 1.51 | D26: =INDEX(ScenarioCurves!$A$2:$A$1002,MATCH(MIN(ScenarioCurves!E2:E1002),ScenarioCurves!E2:E1002,0)) -> 7.84 | E26: =INDEX(ScenarioCurves!$A$2:$A$1002,MATCH(MIN(ScenarioCurves!G2:G1002),ScenarioCurves!G2:G1002,0)) -> 5.09 | F26: =INDEX(ScenarioCurves!$A$2:$A$1002,MATCH(MIN(ScenarioCurves!I2:I1002),ScenarioCurves!I2:I1002,0)) -> 0.17 | G26: =INDEX(ScenarioCurves!$A$2:$A$1002,MATCH(MIN(ScenarioCurves!K2:K1002),ScenarioCurves!K2:K1002,0)) -> 5.69 | H26: =INDEX(ScenarioCurves!$A$2:$A$1002,MATCH(MIN(ScenarioCurves!M2:M1002),ScenarioCurves!M2:M1002,0)) -> 5.78

Sheet ScenarioCurves
A1: Intensity x | B1: Summarization welfare | C1: Summarization risk | D1: MCP DevOps welfare | E1: MCP DevOps risk | F1: Finance welfare | G1: Finance risk | H1: Drafting welfare | I1: Drafting risk | J1: High-loss / smooth welfare | K1: High-loss / smooth risk | L1: High-loss / steep welfare | M1: High-loss / steep risk
A2: =(2-2)/100 -> 0 | B2: =Examples!$C$18-(Examples!$C$10+Examples!$C$11)*$A2-(Examples!$C$6*Examples!$C$7*Examples!$C$8*EXP(-Examples!$C$9*$A2)*(1-(Examples!$C$12*(1-EXP(-Examples!$C$13*$A2))/(1+EXP(MIN(700,MAX(-700,(Examples!$C$14*$A2-Examples!$C$15)/Examples!$C$16))))))+Examples!$C$17*$A2^2) -> 0 | C2: =(Examples!$C$6*Examples!$C$7*Examples!$C$8*EXP(-Examples!$C$9*$A2)*(1-(Examples!$C$12*(1-EXP(-Examples!$C$13*$A2))/(1+EXP(MIN(700,MAX(-700,(Examples!$C$14*$A2-Examples!$C$15)/Examples!$C$16))))))+Examples!$C$17*$A2^2) -> 600000 | D2: =Examples!$D$18-(Examples!$D$10+Examples!$D$11)*$A2-(Examples!$D$6*Examples!$D$7*Examples!$D$8*EXP(-Examples!$D$9*$A2)*(1-(Examples!$D$12*(1-EXP(-Examples!$D$13*$A2))/(1+EXP(MIN(700,MAX(-700,(Examples!$D$14*$A2-Examples!$D$15)/Examples!$D$16))))))+Examples!$D$17*$A2^2) -> -3500000 | E2: =(Examples!$D$6*Examples!$D$7*Examples!$D$8*EXP(-Examples!$D$9*$A2)*(1-(Examples!$D$12*(1-EXP(-Examples!$D$13*$A2))/(1+EXP(MIN(700,MAX(-700,(Examples!$D$14*$A2-Examples!$D$15)/Examples!$D$16))))))+Examples!$D$17*$A2^2) -> 6000000 | F2: =Examples!$E$18-(Examples!$E$10+Examples!$E$11)*$A2-(Examples!$E$6*Examples!$E$7*Examples!$E$8*EXP(-Examples!$E$9*$A2)*(1-(Examples!$E$12*(1-EXP(-Examples!$E$13*$A2))/(1+EXP(MIN(700,MAX(-700,(Examples!$E$14*$A2-Examples!$E$15)/Examples!$E$16))))))+Examples!$E$17*$A2^2) -> 300000 | G2: =(Examples!$E$6*Examples!$E$7*Examples!$E$8*EXP(-Examples!$E$9*$A2)*(1-(Examples!$E$12*(1-EXP(-Examples!$E$13*$A2))/(1+EXP(MIN(700,MAX(-700,(Examples!$E$14*$A2-Examples!$E$15)/Examples!$E$16))))))+Examples!$E$17*$A2^2) -> 2700000 | H2: =Examples!$F$18-(Examples!$F$10+Examples!$F$11)*$A2-(Examples!$F$6*Examples!$F$7*Examples!$F$8*EXP(-Examples!$F$9*$A2)*(1-(Examples!$F$12*(1-EXP(-Examples!$F$13*$A2))/(1+EXP(MIN(700,MAX(-700,(Examples!$F$14*$A2-Examples!$F$15)/Examples!$F$16))))))+Examples!$F$17*$A2^2) -> 132500 | I2: =(Examples!$F$6*Examples!$F$7*Examples!$F$8*EXP(-Examples!$F$9*$A2)*(1-(Examples!$F$12*(1-EXP(-Examples!$F$13*$A2))/(1+EXP(MIN(700,MAX(-700,(Examples!$F$14*$A2-Examples!$F$15)/Examples!$F$16))))))+Examples!$F$17*$A2^2) -> 17500 | J2: =Examples!$G$18-(Examples!$G$10+Examples!$G$11)*$A2-(Examples!$G$6*Examples!$G$7*Examples!$G$8*EXP(-Examples!$G$9*$A2)*(1-(Examples!$G$12*(1-EXP(-Examples!$G$13*$A2))/(1+EXP(MIN(700,MAX(-700,(Examples!$G$14*$A2-Examples!$G$15)/Examples!$G$16))))))+Examples!$G$17*$A2^2) -> -500000 | K2: =(Examples!$G$6*Examples!$G$7*Examples!$G$8*EXP(-Examples!$G$9*$A2)*(1-(Examples!$G$12*(1-EXP(-Examples!$G$13*$A2))/(1+EXP(MIN(700,MAX(-700,(Examples!$G$14*$A2-Examples!$G$15)/Examples!$G$16))))))+Examples!$G$17*$A2^2) -> 2000000 | L2: =Examples!$H$18-(Examples!$H$10+Examples!$H$11)*$A2-(Examples!$H$6*Examples!$H$7*Examples!$H$8*EXP(-Examples!$H$9*$A2)*(1-(Examples!$H$12*(1-EXP(-Examples!$H$13*$A2))/(1+EXP(MIN(700,MAX(-700,(Examples!$H$14*$A2-Examples!$H$15)/Examples!$H$16))))))+Examples!$H$17*$A2^2) -> -500000 | M2: =(Examples!$H$6*Examples!$H$7*Examples!$H$8*EXP(-Examples!$H$9*$A2)*(1-(Examples!$H$12*(1-EXP(-Examples!$H$13*$A2))/(1+EXP(MIN(700,MAX(-700,(Examples!$H$14*$A2-Examples!$H$15)/Examples!$H$16))))))+Examples!$H$17*$A2^2) -> 2000000
A3: =(3-2)/100 -> 0.01 | B3: =Examples!$C$18-(Examples!$C$10+Examples!$C$11)*$A3-(Examples!$C$6*Examples!$C$7*Examples!$C$8*EXP(-Examples!$C$9*$A3)*(1-(Examples!$C$12*(1-EXP(-Examples!$C$13*$A3))/(1+EXP(MIN(700,MAX(-700,(Examples!$C$14*$A3-Examples!$C$15)/Examples!$C$16))))))+Examples!$C$17*$A3^2) -> 2872.9175 | C3: =(Examples!$C$6*Examples!$C$7*Examples!$C$8*EXP(-Examples!$C$9*$A3)*(1-(Examples!$C$12*(1-EXP(-Examples!$C$13*$A3))/(1+EXP(MIN(700,MAX(-700,(Examples!$C$14*$A3-Examples!$C$15)/Examples!$C$16))))))+Examples!$C$17*$A3^2) -> 596777.08 | D3: =Examples!$D$18-(Examples!$D$10+Examples!$D$11)*$A3-(Examples!$D$6*Examples!$D$7*Examples!$D$8*EXP(-Examples!$D$9*$A3)*(1-(Examples!$D$12*(1-EXP(-Examples!$D$13*$A3))/(1+EXP(MIN(700,MAX(-700,(Examples!$D$14*$A3-Examples!$D$15)/Examples!$D$16))))))+Examples!$D$17*$A3^2) -> -3446894.6 | E3: =(Examples!$D$6*Examples!$D$7*Examples!$D$8*EXP(-Examples!$D$9*$A3)*(1-(Examples!$D$12*(1-EXP(-Examples!$D$13*$A3))/(1+EXP(MIN(700,MAX(-700,(Examples!$D$14*$A3-Examples!$D$15)/Examples!$D$16))))))+Examples!$D$17*$A3^2) -> 5946444.6 | F3: =Examples!$E$18-(Examples!$E$10+Examples!$E$11)*$A3-(Examples!$E$6*Examples!$E$7*Examples!$E$8*EXP(-Examples!$E$9*$A3)*(1-(Examples!$E$12*(1-EXP(-Examples!$E$13*$A3))/(1+EXP(MIN(700,MAX(-700,(Examples!$E$14*$A3-Examples!$E$15)/Examples!$E$16))))))+Examples!$E$17*$A3^2) -> 328256.3 | G3: =(Examples!$E$6*Examples!$E$7*Examples!$E$8*EXP(-Examples!$E$9*$A3)*(1-(Examples!$E$12*(1-EXP(-Examples!$E$13*$A3))/(1+EXP(MIN(700,MAX(-700,(Examples!$E$14*$A3-Examples!$E$15)/Examples!$E$16))))))+Examples!$E$17*$A3^2) -> 2670893.7 | H3: =Examples!$F$18-(Examples!$F$10+Examples!$F$11)*$A3-(Examples!$F$6*Examples!$F$7*Examples!$F$8*EXP(-Examples!$F$9*$A3)*(1-(Examples!$F$12*(1-EXP(-Examples!$F$13*$A3))/(1+EXP(MIN(700,MAX(-700,(Examples!$F$14*$A3-Examples!$F$15)/Examples!$F$16))))))+Examples!$F$17*$A3^2) -> 132371.22 | I3: =(Examples!$F$6*Examples!$F$7*Examples!$F$8*EXP(-Examples!$F$9*$A3)*(1-(Examples!$F$12*(1-EXP(-Examples!$F$13*$A3))/(1+EXP(MIN(700,MAX(-700,(Examples!$F$14*$A3-Examples!$F$15)/Examples!$F$16))))))+Examples!$F$17*$A3^2) -> 17428.777 | J3: =Examples!$G$18-(Examples!$G$10+Examples!$G$11)*$A3-(Examples!$G$6*Examples!$G$7*Examples!$G$8*EXP(-Examples!$G$9*$A3)*(1-(Examples!$G$12*(1-EXP(-Examples!$G$13*$A3))/(1+EXP(MIN(700,MAX(-700,(Examples!$G$14*$A3-Examples!$G$15)/Examples!$G$16))))))+Examples!$G$17*$A3^2) -> -485838.35 | K3: =(Examples!$G$6*Examples!$G$7*Examples!$G$8*EXP(-Examples!$G$9*$A3)*(1-(Examples!$G$12*(1-EXP(-Examples!$G$13*$A3))/(1+EXP(MIN(700,MAX(-700,(Examples!$G$14*$A3-Examples!$G$15)/Examples!$G$16))))))+Examples!$G$17*$A3^2) -> 1985338.3 | L3: =Examples!$H$18-(Examples!$H$10+Examples!$H$11)*$A3-(Examples!$H$6*Examples!$H$7*Examples!$H$8*EXP(-Examples!$H$9*$A3)*(1-(Examples!$H$12*(1-EXP(-Examples!$H$13*$A3))/(1+EXP(MIN(700,MAX(-700,(Examples!$H$14*$A3-Examples!$H$15)/Examples!$H$16))))))+Examples!$H$17*$A3^2) -> -485563.64 | M3: =(Examples!$H$6*Examples!$H$7*Examples!$H$8*EXP(-Examples!$H$9*$A3)*(1-(Examples!$H$12*(1-EXP(-Examples!$H$13*$A3))/(1+EXP(MIN(700,MAX(-700,(Examples!$H$14*$A3-Examples!$H$15)/Examples!$H$16))))))+Examples!$H$17*$A3^2) -> 1985063.6
A4: =(4-2)/100 -> 0.02 | B4: =Examples!$C$18-(Examples!$C$10+Examples!$C$11)*$A4-(Examples!$C$6*Examples!$C$7*Examples!$C$8*EXP(-Examples!$C$9*$A4)*(1-(Examples!$C$12*(1-EXP(-Examples!$C$13*$A4))/(1+EXP(MIN(700,MAX(-700,(Examples!$C$14*$A4-Examples!$C$15)/Examples!$C$16))))))+Examples!$C$17*$A4^2) -> 5722.8382 | C4: =(Examples!$C$6*Examples!$C$7*Examples!$C$8*EXP(-Examples!$C$9*$A4)*(1-(Examples!$C$12*(1-EXP(-Examples!$C$13*$A4))/(1+EXP(MIN(700,MAX(-700,(Examples!$C$14*$A4-Examples!$C$15)/Examples!$C$16))))))+Examples!$C$17*$A4^2) -> 593577.16 | D4: =Examples!$D$18-(Examples!$D$10+Examples!$D$11)*$A4-(Examples!$D$6*Examples!$D$7*Examples!$D$8*EXP(-Examples!$D$9*$A4)*(1-(Examples!$D$12*(1-EXP(-Examples!$D$13*$A4))/(1+EXP(MIN(700,MAX(-700,(Examples!$D$14*$A4-Examples!$D$15)/Examples!$D$16))))))+Examples!$D$17*$A4^2) -> -3394313.5 | E4: =(Examples!$D$6*Examples!$D$7*Examples!$D$8*EXP(-Examples!$D$9*$A4)*(1-(Examples!$D$12*(1-EXP(-Examples!$D$13*$A4))/(1+EXP(MIN(700,MAX(-700,(Examples!$D$14*$A4-Examples!$D$15)/Examples!$D$16))))))+Examples!$D$17*$A4^2) -> 5893413.5 | F4: =Examples!$E$18-(Examples!$E$10+Examples!$E$11)*$A4-(Examples!$E$6*Examples!$E$7*Examples!$E$8*EXP(-Examples!$E$9*$A4)*(1-(Examples!$E$12*(1-EXP(-Examples!$E$13*$A4))/(1+EXP(MIN(700,MAX(-700,(Examples!$E$14*$A4-Examples!$E$15)/Examples!$E$16))))))+Examples!$E$17*$A4^2) -> 356175.76 | G4: =(Examples!$E$6*Examples!$E$7*Examples!$E$8*EXP(-Examples!$E$9*$A4)*(1-(Examples!$E$12*(1-EXP(-Examples!$E$13*$A4))/(1+EXP(MIN(700,MAX(-700,(Examples!$E$14*$A4-Examples!$E$15)/Examples!$E$16))))))+Examples!$E$17*$A4^2) -> 2642124.2 | H4: =Examples!$F$18-(Examples!$F$10+Examples!$F$11)*$A4-(Examples!$F$6*Examples!$F$7*Examples!$F$8*EXP(-Examples!$F$9*$A4)*(1-(Examples!$F$12*(1-EXP(-Examples!$F$13*$A4))/(1+EXP(MIN(700,MAX(-700,(Examples!$F$14*$A4-Examples!$F$15)/Examples!$F$16))))))+Examples!$F$17*$A4^2) -> 132238.09 | I4: =(Examples!$F$6*Examples!$F$7*Examples!$F$8*EXP(-Examples!$F$9*$A4)*(1-(Examples!$F$12*(1-EXP(-Examples!$F$13*$A4))/(1+EXP(MIN(700,MAX(-700,(Examples!$F$14*$A4-Examples!$F$15)/Examples!$F$16))))))+Examples!$F$17*$A4^2) -> 17361.907 | J4: =Examples!$G$18-(Examples!$G$10+Examples!$G$11)*$A4-(Examples!$G$6*Examples!$G$7*Examples!$G$8*EXP(-Examples!$G$9*$A4)*(1-(Examples!$G$12*(1-EXP(-Examples!$G$13*$A4))/(1+EXP(MIN(700,MAX(-700,(Examples!$G$14*$A4-Examples!$G$15)/Examples!$G$16))))))+Examples!$G$17*$A4^2) -> -471801.62 | K4: =(Examples!$G$6*Examples!$G$7*Examples!$G$8*EXP(-Examples!$G$9*$A4)*(1-(Examples!$G$12*(1-EXP(-Examples!$G$13*$A4))/(1+EXP(MIN(700,MAX(-700,(Examples!$G$14*$A4-Examples!$G$15)/Examples!$G$16))))))+Examples!$G$17*$A4^2) -> 1970801.6 | L4: =Examples!$H$18-(Examples!$H$10+Examples!$H$11)*$A4-(Examples!$H$6*Examples!$H$7*Examples!$H$8*EXP(-Examples!$H$9*$A4)*(1-(Examples!$H$12*(1-EXP(-Examples!$H$13*$A4))/(1+EXP(MIN(700,MAX(-700,(Examples!$H$14*$A4-Examples!$H$15)/Examples!$H$16))))))+Examples!$H$17*$A4^2) -> -471248.52 | M4: =(Examples!$H$6*Examples!$H$7*Examples!$H$8*EXP(-Examples!$H$9*$A4)*(1-(Examples!$H$12*(1-EXP(-Examples!$H$13*$A4))/(1+EXP(MIN(700,MAX(-700,(Examples!$H$14*$A4-Examples!$H$15)/Examples!$H$16))))))+Examples!$H$17*$A4^2) -> 1970248.5
A5: =(5-2)/100 -> 0.03 | B5: =Examples!$C$18-(Examples!$C$10+Examples!$C$11)*$A5-(Examples!$C$6*Examples!$C$7*Examples!$C$8*EXP(-Examples!$C$9*$A5)*(1-(Examples!$C$12*(1-EXP(-Examples!$C$13*$A5))/(1+EXP(MIN(700,MAX(-700,(Examples!$C$14*$A5-Examples!$C$15)/Examples!$C$16))))))+Examples!$C$17*$A5^2) -> 8549.8767 | C5: =(Examples!$C$6*Examples!$C$7*Examples!$C$8*EXP(-Examples!$C$9*$A5)*(1-(Examples!$C$12*(1-EXP(-Examples!$C$13*$A5))/(1+EXP(MIN(700,MAX(-700,(Examples!$C$14*$A5-Examples!$C$15)/Examples!$C$16))))))+Examples!$C$17*$A5^2) -> 590400.12 | D5: =Examples!$D$18-(Examples!$D$10+Examples!$D$11)*$A5-(Examples!$D$6*Examples!$D$7*Examples!$D$8*EXP(-Examples!$D$9*$A5)*(1-(Examples!$D$12*(1-EXP(-Examples!$D$13*$A5))/(1+EXP(MIN(700,MAX(-700,(Examples!$D$14*$A5-Examples!$D$15)/Examples!$D$16))))))+Examples!$D$17*$A5^2) -> -3342251.4 | E5: =(Examples!$D$6*Examples!$D$7*Examples!$D$8*EXP(-Examples!$D$9*$A5)*(1-(Examples!$D$12*(1-EXP(-Examples!$D$13*$A5))/(1+EXP(MIN(700,MAX(-700,(Examples!$D$14*$A5-Examples!$D$15)/Examples!$D$16))))))+Examples!$D$17*$A5^2) -> 5840901.4 | F5: =Examples!$E$18-(Examples!$E$10+Examples!$E$11)*$A5-(Examples!$E$6*Examples!$E$7*Examples!$E$8*EXP(-Examples!$E$9*$A5)*(1-(Examples!$E$12*(1-EXP(-Examples!$E$13*$A5))/(1+EXP(MIN(700,MAX(-700,(Examples!$E$14*$A5-Examples!$E$15)/Examples!$E$16))))))+Examples!$E$17*$A5^2) -> 383762.31 | G5: =(Examples!$E$6*Examples!$E$7*Examples!$E$8*EXP(-Examples!$E$9*$A5)*(1-(Examples!$E$12*(1-EXP(-Examples!$E$13*$A5))/(1+EXP(MIN(700,MAX(-700,(Examples!$E$14*$A5-Examples!$E$15)/Examples!$E$16))))))+Examples!$E$17*$A5^2) -> 2613687.7 | H5: =Examples!$F$18-(Examples!$F$10+Examples!$F$11)*$A5-(Examples!$F$6*Examples!$F$7*Examples!$F$8*EXP(-Examples!$F$9*$A5)*(1-(Examples!$F$12*(1-EXP(-Examples!$F$13*$A5))/(1+EXP(MIN(700,MAX(-700,(Examples!$F$14*$A5-Examples!$F$15)/Examples!$F$16))))))+Examples!$F$17*$A5^2) -> 132100.61 | I5: =(Examples!$F$6*Examples!$F$7*Examples!$F$8*EXP(-Examples!$F$9*$A5)*(1-(Examples!$F$12*(1-EXP(-Examples!$F$13*$A5))/(1+EXP(MIN(700,MAX(-700,(Examples!$F$14*$A5-Examples!$F$15)/Examples!$F$16))))))+Examples!$F$17*$A5^2) -> 17299.388 | J5: =Examples!$G$18-(Examples!$G$10+Examples!$G$11)*$A5-(Examples!$G$6*Examples!$G$7*Examples!$G$8*EXP(-Examples!$G$9*$A5)*(1-(Examples!$G$12*(1-EXP(-Examples!$G$13*$A5))/(1+EXP(MIN(700,MAX(-700,(Examples!$G$14*$A5-Examples!$G$15)/Examples!$G$16))))))+Examples!$G$17*$A5^2) -> -457888.87 | K5: =(Examples!$G$6*Examples!$G$7*Examples!$G$8*EXP(-Examples!$G$9*$A5)*(1-(Examples!$G$12*(1-EXP(-Examples!$G$13*$A5))/(1+EXP(MIN(700,MAX(-700,(Examples!$G$14*$A5-Examples!$G$15)/Examples!$G$16))))))+Examples!$G$17*$A5^2) -> 1956388.9 | L5: =Examples!$H$18-(Examples!$H$10+Examples!$H$11)*$A5-(Examples!$H$6*Examples!$H$7*Examples!$H$8*EXP(-Examples!$H$9*$A5)*(1-(Examples!$H$12*(1-EXP(-Examples!$H$13*$A5))/(1+EXP(MIN(700,MAX(-700,(Examples!$H$14*$A5-Examples!$H$15)/Examples!$H$16))))))+Examples!$H$17*$A5^2) -> -457053.68 | M5: =(Examples!$H$6*Examples!$H$7*Examples!$H$8*EXP(-Examples!$H$9*$A5)*(1-(Examples!$H$12*(1-EXP(-Examples!$H$13*$A5))/(1+EXP(MIN(700,MAX(-700,(Examples!$H$14*$A5-Examples!$H$15)/Examples!$H$16))))))+Examples!$H$17*$A5^2) -> 1955553.7
A6: =(6-2)/100 -> 0.04 | B6: =Examples!$C$18-(Examples!$C$10+Examples!$C$11)*$A6-(Examples!$C$6*Examples!$C$7*Examples!$C$8*EXP(-Examples!$C$9*$A6)*(1-(Examples!$C$12*(1-EXP(-Examples!$C$13*$A6))/(1+EXP(MIN(700,MAX(-700,(Examples!$C$14*$A6-Examples!$C$15)/Examples!$C$16))))))+Examples!$C$17*$A6^2) -> 11354.146 | C6: =(Examples!$C$6*Examples!$C$7*Examples!$C$8*EXP(-Examples!$C$9*$A6)*(1-(Examples!$C$12*(1-EXP(-Examples!$C$13*$A6))/(1+EXP(MIN(700,MAX(-700,(Examples!$C$14*$A6-Examples!$C$15)/Examples!$C$16))))))+Examples!$C$17*$A6^2) -> 587245.85 | D6: =Examples!$D$18-(Examples!$D$10+Examples!$D$11)*$A6-(Examples!$D$6*Examples!$D$7*Examples!$D$8*EXP(-Examples!$D$9*$A6)*(1-(Examples!$D$12*(1-EXP(-Examples!$D$13*$A6))/(1+EXP(MIN(700,MAX(-700,(Examples!$D$14*$A6-Examples!$D$15)/Examples!$D$16))))))+Examples!$D$17*$A6^2) -> -3290703.2 | E6: =(Examples!$D$6*Examples!$D$7*Examples!$D$8*EXP(-Examples!$D$9*$A6)*(1-(Examples!$D$12*(1-EXP(-Examples!$D$13*$A6))/(1+EXP(MIN(700,MAX(-700,(Examples!$D$14*$A6-Examples!$D$15)/Examples!$D$16))))))+Examples!$D$17*$A6^2) -> 5788903.2 | F6: =Examples!$E$18-(Examples!$E$10+Examples!$E$11)*$A6-(Examples!$E$6*Examples!$E$7*Examples!$E$8*EXP(-Examples!$E$9*$A6)*(1-(Examples!$E$12*(1-EXP(-Examples!$E$13*$A6))/(1+EXP(MIN(700,MAX(-700,(Examples!$E$14*$A6-Examples!$E$15)/Examples!$E$16))))))+Examples!$E$17*$A6^2) -> 411019.85 | G6: =(Examples!$E$6*Examples!$E$7*Examples!$E$8*EXP(-Examples!$E$9*$A6)*(1-(Examples!$E$12*(1-EXP(-Examples!$E$13*$A6))/(1+EXP(MIN(700,MAX(-700,(Examples!$E$14*$A6-Examples!$E$15)/Examples!$E$16))))))+Examples!$E$17*$A6^2) -> 2585580.2 | H6: =Examples!$F$18-(Examples!$F$10+Examples!$F$11)*$A6-(Examples!$F$6*Examples!$F$7*Examples!$F$8*EXP(-Examples!$F$9*$A6)*(1-(Examples!$F$12*(1-EXP(-Examples!$F$13*$A6))/(1+EXP(MIN(700,MAX(-700,(Examples!$F$14*$A6-Examples!$F$15)/Examples!$F$16))))))+Examples!$F$17*$A6^2) -> 131958.78 | I6: =(Examples!$F$6*Examples!$F$7*Examples!$F$8*EXP(-Examples!$F$9*$A6)*(1-(Examples!$F$12*(1-EXP(-Examples!$F$13*$A6))/(1+EXP(MIN(700,MAX(-700,(Examples!$F$14*$A6-Examples!$F$15)/Examples!$F$16))))))+Examples!$F$17*$A6^2) -> 17241.218 | J6: =Examples!$G$18-(Examples!$G$10+Examples!$G$11)*$A6-(Examples!$G$6*Examples!$G$7*Examples!$G$8*EXP(-Examples!$G$9*$A6)*(1-(Examples!$G$12*(1-EXP(-Examples!$G$13*$A6))/(1+EXP(MIN(700,MAX(-700,(Examples!$G$14*$A6-Examples!$G$15)/Examples!$G$16))))))+Examples!$G$17*$A6^2) -> -444099.16 | K6: =(Examples!$G$6*Examples!$G$7*Examples!$G$8*EXP(-Examples!$G$9*$A6)*(1-(Examples!$G$12*(1-EXP(-Examples!$G$13*$A6))/(1+EXP(MIN(700,MAX(-700,(Examples!$G$14*$A6-Examples!$G$15)/Examples!$G$16))))))+Examples!$G$17*$A6^2) -> 1942099.2 | L6: =Examples!$H$18-(Examples!$H$10+Examples!$H$11)*$A6-(Examples!$H$6*Examples!$H$7*Examples!$H$8*EXP(-Examples!$H$9*$A6)*(1-(Examples!$H$12*(1-EXP(-Examples!$H$13*$A6))/(1+EXP(MIN(700,MAX(-700,(Examples!$H$14*$A6-Examples!$H$15)/Examples!$H$16))))))+Examples!$H$17*$A6^2) -> -442978.13 | M6: =(Examples!$H$6*Examples!$H$7*Examples!$H$8*EXP(-Examples!$H$9*$A6)*(1-(Examples!$H$12*(1-EXP(-Examples!$H$13*$A6))/(1+EXP(MIN(700,MAX(-700,(Examples!$H$14*$A6-Examples!$H$15)/Examples!$H$16))))))+Examples!$H$17*$A6^2) -> 1940978.1
A7: =(7-2)/100 -> 0.05 | B7: =Examples!$C$18-(Examples!$C$10+Examples!$C$11)*$A7-(Examples!$C$6*Examples!$C$7*Examples!$C$8*EXP(-Examples!$C$9*$A7)*(1-(Examples!$C$12*(1-EXP(-Examples!$C$13*$A7))/(1+EXP(MIN(700,MAX(-700,(Examples!$C$14*$A7-Examples!$C$15)/Examples!$C$16))))))+Examples!$C$17*$A7^2) -> 14135.759 | C7: =(Examples!$C$6*Examples!$C$7*Examples!$C$8*EXP(-Examples!$C$9*$A7)*(1-(Examples!$C$12*(1-EXP(-Examples!$C$13*$A7))/(1+EXP(MIN(700,MAX(-700,(Examples!$C$14*$A7-Examples!$C$15)/Examples!$C$16))))))+Examples!$C$17*$A7^2) -> 584114.24 | D7: =Examples!$D$18-(Examples!$D$10+Examples!$D$11)*$A7-(Examples!$D$6*Examples!$D$7*Examples!$D$8*EXP(-Examples!$D$9*$A7)*(1-(Examples!$D$12*(1-EXP(-Examples!$D$13*$A7))/(1+EXP(MIN(700,MAX(-700,(Examples!$D$14*$A7-Examples!$D$15)/Examples!$D$16))))))+Examples!$D$17*$A7^2) -> -3239663.7 | E7: =(Examples!$D$6*Examples!$D$7*Examples!$D$8*EXP(-Examples!$D$9*$A7)*(1-(Examples!$D$12*(1-EXP(-Examples!$D$13*$A7))/(1+EXP(MIN(700,MAX(-700,(Examples!$D$14*$A7-Examples!$D$15)/Examples!$D$16))))))+Examples!$D$17*$A7^2) -> 5737413.7 | F7: =Examples!$E$18-(Examples!$E$10+Examples!$E$11)*$A7-(Examples!$E$6*Examples!$E$7*Examples!$E$8*EXP(-Examples!$E$9*$A7)*(1-(Examples!$E$12*(1-EXP(-Examples!$E$13*$A7))/(1+EXP(MIN(700,MAX(-700,(Examples!$E$14*$A7-Examples!$E$15)/Examples!$E$16))))))+Examples!$E$17*$A7^2) -> 437952.23 | G7: =(Examples!$E$6*Examples!$E$7*Examples!$E$8*EXP(-Examples!$E$9*$A7)*(1-(Examples!$E$12*(1-EXP(-Examples!$E$13*$A7))/(1+EXP(MIN(700,MAX(-700,(Examples!$E$14*$A7-Examples!$E$15)/Examples!$E$16))))))+Examples!$E$17*$A7^2) -> 2557797.8 | H7: =Examples!$F$18-(Examples!$F$10+Examples!$F$11)*$A7-(Examples!$F$6*Examples!$F$7*Examples!$F$8*EXP(-Examples!$F$9*$A7)*(1-(Examples!$F$12*(1-EXP(-Examples!$F$13*$A7))/(1+EXP(MIN(700,MAX(-700,(Examples!$F$14*$A7-Examples!$F$15)/Examples!$F$16))))))+Examples!$F$17*$A7^2) -> 131812.6 | I7: =(Examples!$F$6*Examples!$F$7*Examples!$F$8*EXP(-Examples!$F$9*$A7)*(1-(Examples!$F$12*(1-EXP(-Examples!$F$13*$A7))/(1+EXP(MIN(700,MAX(-700,(Examples!$F$14*$A7-Examples!$F$15)/Examples!$F$16))))))+Examples!$F$17*$A7^2) -> 17187.396 | J7: =Examples!$G$18-(Examples!$G$10+Examples!$G$11)*$A7-(Examples!$G$6*Examples!$G$7*Examples!$G$8*EXP(-Examples!$G$9*$A7)*(1-(Examples!$G$12*(1-EXP(-Examples!$G$13*$A7))/(1+EXP(MIN(700,MAX(-700,(Examples!$G$14*$A7-Examples!$G$15)/Examples!$G$16))))))+Examples!$G$17*$A7^2) -> -430431.56 | K7: =(Examples!$G$6*Examples!$G$7*Examples!$G$8*EXP(-Examples!$G$9*$A7)*(1-(Examples!$G$12*(1-EXP(-Examples!$G$13*$A7))/(1+EXP(MIN(700,MAX(-700,(Examples!$G$14*$A7-Examples!$G$15)/Examples!$G$16))))))+Examples!$G$17*$A7^2) -> 1927931.6 | L7: =Examples!$H$18-(Examples!$H$10+Examples!$H$11)*$A7-(Examples!$H$6*Examples!$H$7*Examples!$H$8*EXP(-Examples!$H$9*$A7)*(1-(Examples!$H$12*(1-EXP(-Examples!$H$13*$A7))/(1+EXP(MIN(700,MAX(-700,(Examples!$H$14*$A7-Examples!$H$15)/Examples!$H$16))))))+Examples!$H$17*$A7^2) -> -429020.91 | M7: =(Examples!$H$6*Examples!$H$7*Examples!$H$8*EXP(-Examples!$H$9*$A7)*(1-(Examples!$H$12*(1-EXP(-Examples!$H$13*$A7))/(1+EXP(MIN(700,MAX(-700,(Examples!$H$14*$A7-Examples!$H$15)/Examples!$H$16))))))+Examples!$H$17*$A7^2) -> 1926520.9
A8: =(8-2)/100 -> 0.06 | B8: =Examples!$C$18-(Examples!$C$10+Examples!$C$11)*$A8-(Examples!$C$6*Examples!$C$7*Examples!$C$8*EXP(-Examples!$C$9*$A8)*(1-(Examples!$C$12*(1-EXP(-Examples!$C$13*$A8))/(1+EXP(MIN(700,MAX(-700,(Examples!$C$14*$A8-Examples!$C$15)/Examples!$C$16))))))+Examples!$C$17*$A8^2) -> 16894.825 | C8: =(Examples!$C$6*Examples!$C$7*Examples!$C$8*EXP(-Examples!$C$9*$A8)*(1-(Examples!$C$12*(1-EXP(-Examples!$C$13*$A8))/(1+EXP(MIN(700,MAX(-700,(Examples!$C$14*$A8-Examples!$C$15)/Examples!$C$16))))))+Examples!$C$17*$A8^2) -> 581005.17 | D8: =Examples!$D$18-(Examples!$D$10+Examples!$D$11)*$A8-(Examples!$D$6*Examples!$D$7*Examples!$D$8*EXP(-Examples!$D$9*$A8)*(1-(Examples!$D$12*(1-EXP(-Examples!$D$13*$A8))/(1+EXP(MIN(700,MAX(-700,(Examples!$D$14*$A8-Examples!$D$15)/Examples!$D$16))))))+Examples!$D$17*$A8^2) -> -3189127.8 | E8: =(Examples!$D$6*Examples!$D$7*Examples!$D$8*EXP(-Examples!$D$9*$A8)*(1-(Examples!$D$12*(1-EXP(-Examples!$D$13*$A8))/(1+EXP(MIN(700,MAX(-700,(Examples!$D$14*$A8-Examples!$D$15)/Examples!$D$16))))))+Examples!$D$17*$A8^2) -> 5686427.8 | F8: =Examples!$E$18-(Examples!$E$10+Examples!$E$11)*$A8-(Examples!$E$6*Examples!$E$7*Examples!$E$8*EXP(-Examples!$E$9*$A8)*(1-(Examples!$E$12*(1-EXP(-Examples!$E$13*$A8))/(1+EXP(MIN(700,MAX(-700,(Examples!$E$14*$A8-Examples!$E$15)/Examples!$E$16))))))+Examples!$E$17*$A8^2) -> 464563.26 | G8: =(Examples!$E$6*Examples!$E$7*Examples!$E$8*EXP(-Examples!$E$9*$A8)*(1-(Examples!$E$12*(1-EXP(-Examples!$E$13*$A8))/(1+EXP(MIN(700,MAX(-700,(Examples!$E$14*$A8-Examples!$E$15)/Examples!$E$16))))))+Examples!$E$17*$A8^2) -> 2530336.7 | H8: =Examples!$F$18-(Examples!$F$10+Examples!$F$11)*$A8-(Examples!$F$6*Examples!$F$7*Examples!$F$8*EXP(-Examples!$F$9*$A8)*(1-(Examples!$F$12*(1-EXP(-Examples!$F$13*$A8))/(1+EXP(MIN(700,MAX(-700,(Examples!$F$14*$A8-Examples!$F$15)/Examples!$F$16))))))+Examples!$F$17*$A8^2) -> 131662.08 | I8: =(Examples!$F$6*Examples!$F$7*Examples!$F$8*EXP(-Examples!$F$9*$A8)*(1-(Examples!$F$12*(1-EXP(-Examples!$F$13*$A8))/(1+EXP(MIN(700,MAX(-700,(Examples!$F$14*$A8-Examples!$F$15)/Examples!$F$16))))))+Examples!$F$17*$A8^2) -> 17137.921 | J8: =Examples!$G$18-(Examples!$G$10+Examples!$G$11)*$A8-(Examples!$G$6*Examples!$G$7*Examples!$G$8*EXP(-Examples!$G$9*$A8)*(1-(Examples!$G$12*(1-EXP(-Examples!$G$13*$A8))/(1+EXP(MIN(700,MAX(-700,(Examples!$G$14*$A8-Examples!$G$15)/Examples!$G$16))))))+Examples!$G$17*$A8^2) -> -416885.12 | K8: =(Examples!$G$6*Examples!$G$7*Examples!$G$8*EXP(-Examples!$G$9*$A8)*(1-(Examples!$G$12*(1-EXP(-Examples!$G$13*$A8))/(1+EXP(MIN(700,MAX(-700,(Examples!$G$14*$A8-Examples!$G$15)/Examples!$G$16))))))+Examples!$G$17*$A8^2) -> 1913885.1 | L8: =Examples!$H$18-(Examples!$H$10+Examples!$H$11)*$A8-(Examples!$H$6*Examples!$H$7*Examples!$H$8*EXP(-Examples!$H$9*$A8)*(1-(Examples!$H$12*(1-EXP(-Examples!$H$13*$A8))/(1+EXP(MIN(700,MAX(-700,(Examples!$H$14*$A8-Examples!$H$15)/Examples!$H$16))))))+Examples!$H$17*$A8^2) -> -415181.07 | M8: =(Examples!$H$6*Examples!$H$7*Examples!$H$8*EXP(-Examples!$H$9*$A8)*(1-(Examples!$H$12*(1-EXP(-Examples!$H$13*$A8))/(1+EXP(MIN(700,MAX(-700,(Examples!$H$14*$A8-Examples!$H$15)/Examples!$H$16))))))+Examples!$H$17*$A8^2) -> 1912181.1
A9: =(9-2)/100 -> 0.07 | B9: =Examples!$C$18-(Examples!$C$10+Examples!$C$11)*$A9-(Examples!$C$6*Examples!$C$7*Examples!$C$8*EXP(-Examples!$C$9*$A9)*(1-(Examples!$C$12*(1-EXP(-Examples!$C$13*$A9))/(1+EXP(MIN(700,MAX(-700,(Examples!$C$14*$A9-Examples!$C$15)/Examples!$C$16))))))+Examples!$C$17*$A9^2) -> 19631.454 | C9: =(Examples!$C$6*Examples!$C$7*Examples!$C$8*EXP(-Examples!$C$9*$A9)*(1-(Examples!$C$12*(1-EXP(-Examples!$C$13*$A9))/(1+EXP(MIN(700,MAX(-700,(Examples!$C$14*$A9-Examples!$C$15)/Examples!$C$16))))))+Examples!$C$17*$A9^2) -> 577918.55 | D9: =Examples!$D$18-(Examples!$D$10+Examples!$D$11)*$A9-(Examples!$D$6*Examples!$D$7*Examples!$D$8*EXP(-Examples!$D$9*$A9)*(1-(Examples!$D$12*(1-EXP(-Examples!$D$13*$A9))/(1+EXP(MIN(700,MAX(-700,(Examples!$D$14*$A9-Examples!$D$15)/Examples!$D$16))))))+Examples!$D$17*$A9^2) -> -3139090.5 | E9: =(Examples!$D$6*Examples!$D$7*Examples!$D$8*EXP(-Examples!$D$9*$A9)*(1-(Examples!$D$12*(1-EXP(-Examples!$D$13*$A9))/(1+EXP(MIN(700,MAX(-700,(Examples!$D$14*$A9-Examples!$D$15)/Examples!$D$16))))))+Examples!$D$17*$A9^2) -> 5635940.5 | F9: =Examples!$E$18-(Examples!$E$10+Examples!$E$11)*$A9-(Examples!$E$6*Examples!$E$7*Examples!$E$8*EXP(-Examples!$E$9*$A9)*(1-(Examples!$E$12*(1-EXP(-Examples!$E$13*$A9))/(1+EXP(MIN(700,MAX(-700,(Examples!$E$14*$A9-Examples!$E$15)/Examples!$E$16))))))+Examples!$E$17*$A9^2) -> 490856.69 | G9: =(Examples!$E$6*Examples!$E$7*Examples!$E$8*EXP(-Examples!$E$9*$A9)*(1-(Examples!$E$12*(1-EXP(-Examples!$E$13*$A9))/(1+EXP(MIN(700,MAX(-700,(Examples!$E$14*$A9-Examples!$E$15)/Examples!$E$16))))))+Examples!$E$17*$A9^2) -> 2503193.3 | H9: =Examples!$F$18-(Examples!$F$10+Examples!$F$11)*$A9-(Examples!$F$6*Examples!$F$7*Examples!$F$8*EXP(-Examples!$F$9*$A9)*(1-(Examples!$F$12*(1-EXP(-Examples!$F$13*$A9))/(1+EXP(MIN(700,MAX(-700,(Examples!$F$14*$A9-Examples!$F$15)/Examples!$F$16))))))+Examples!$F$17*$A9^2) -> 131507.21 | I9: =(Examples!$F$6*Examples!$F$7*Examples!$F$8*EXP(-Examples!$F$9*$A9)*(1-(Examples!$F$12*(1-EXP(-Examples!$F$13*$A9))/(1+EXP(MIN(700,MAX(-700,(Examples!$F$14*$A9-Examples!$F$15)/Examples!$F$16))))))+Examples!$F$17*$A9^2) -> 17092.792 | J9: =Examples!$G$18-(Examples!$G$10+Examples!$G$11)*$A9-(Examples!$G$6*Examples!$G$7*Examples!$G$8*EXP(-Examples!$G$9*$A9)*(1-(Examples!$G$12*(1-EXP(-Examples!$G$13*$A9))/(1+EXP(MIN(700,MAX(-700,(Examples!$G$14*$A9-Examples!$G$15)/Examples!$G$16))))))+Examples!$G$17*$A9^2) -> -403458.95 | K9: =(Examples!$G$6*Examples!$G$7*Examples!$G$8*EXP(-Examples!$G$9*$A9)*(1-(Examples!$G$12*(1-EXP(-Examples!$G$13*$A9))/(1+EXP(MIN(700,MAX(-700,(Examples!$G$14*$A9-Examples!$G$15)/Examples!$G$16))))))+Examples!$G$17*$A9^2) -> 1899958.9 | L9: =Examples!$H$18-(Examples!$H$10+Examples!$H$11)*$A9-(Examples!$H$6*Examples!$H$7*Examples!$H$8*EXP(-Examples!$H$9*$A9)*(1-(Examples!$H$12*(1-EXP(-Examples!$H$13*$A9))/(1+EXP(MIN(700,MAX(-700,(Examples!$H$14*$A9-Examples!$H$15)/Examples!$H$16))))))+Examples!$H$17*$A9^2) -> -401457.66 | M9: =(Examples!$H$6*Examples!$H$7*Examples!$H$8*EXP(-Examples!$H$9*$A9)*(1-(Examples!$H$12*(1-EXP(-Examples!$H$13*$A9))/(1+EXP(MIN(700,MAX(-700,(Examples!$H$14*$A9-Examples!$H$15)/Examples!$H$16))))))+Examples!$H$17*$A9^2) -> 1897957.7
A10: =(10-2)/100 -> 0.08 | B10: =Examples!$C$18-(Examples!$C$10+Examples!$C$11)*$A10-(Examples!$C$6*Examples!$C$7*Examples!$C$8*EXP(-Examples!$C$9*$A10)*(1-(Examples!$C$12*(1-EXP(-Examples!$C$13*$A10))/(1+EXP(MIN(700,MAX(-700,(Examples!$C$14*$A10-Examples!$C$15)/Examples!$C$16))))))+Examples!$C$17*$A10^2) -> 22345.753 | C10: =(Examples!$C$6*Examples!$C$7*Examples!$C$8*EXP(-Examples!$C$9*$A10)*(1-(Examples!$C$12*(1-EXP(-Examples!$C$13*$A10))/(1+EXP(MIN(700,MAX(-700,(Examples!$C$14*$A10-Examples!$C$15)/Examples!$C$16))))))+Examples!$C$17*$A10^2) -> 574854.25 | D10: =Examples!$D$18-(Examples!$D$10+Examples!$D$11)*$A10-(Examples!$D$6*Examples!$D$7*Examples!$D$8*EXP(-Examples!$D$9*$A10)*(1-(Examples!$D$12*(1-EXP(-Examples!$D$13*$A10))/(1+EXP(MIN(700,MAX(-700,(Examples!$D$14*$A10-Examples!$D$15)/Examples!$D$16))))))+Examples!$D$17*$A10^2) -> -3089546.8 | E10: =(Examples!$D$6*Examples!$D$7*Examples!$D$8*EXP(-Examples!$D$9*$A10)*(1-(Examples!$D$12*(1-EXP(-Examples!$D$13*$A10))/(1+EXP(MIN(700,MAX(-700,(Examples!$D$14*$A10-Examples!$D$15)/Examples!$D$16))))))+Examples!$D$17*$A10^2) -> 5585946.8 | F10: =Examples!$E$18-(Examples!$E$10+Examples!$E$11)*$A10-(Examples!$E$6*Examples!$E$7*Examples!$E$8*EXP(-Examples!$E$9*$A10)*(1-(Examples!$E$12*(1-EXP(-Examples!$E$13*$A10))/(1+EXP(MIN(700,MAX(-700,(Examples!$E$14*$A10-Examples!$E$15)/Examples!$E$16))))))+Examples!$E$17*$A10^2) -> 516836.23 | G10: =(Examples!$E$6*Examples!$E$7*Examples!$E$8*EXP(-Examples!$E$9*$A10)*(1-(Examples!$E$12*(1-EXP(-Examples!$E$13*$A10))/(1+EXP(MIN(700,MAX(-700,(Examples!$E$14*$A10-Examples!$E$15)/Examples!$E$16))))))+Examples!$E$17*$A10^2) -> 2476363.8 | H10: =Examples!$F$18-(Examples!$F$10+Examples!$F$11)*$A10-(Examples!$F$6*Examples!$F$7*Examples!$F$8*EXP(-Examples!$F$9*$A10)*(1-(Examples!$F$12*(1-EXP(-Examples!$F$13*$A10))/(1+EXP(MIN(700,MAX(-700,(Examples!$F$14*$A10-Examples!$F$15)/Examples!$F$16))))))+Examples!$F$17*$A10^2) -> 131347.99 | I10: =(Examples!$F$6*Examples!$F$7*Examples!$F$8*EXP(-Examples!$F$9*$A10)*(1-(Examples!$F$12*(1-EXP(-Examples!$F$13*$A10))/(1+EXP(MIN(700,MAX(-700,(Examples!$F$14*$A10-Examples!$F$15)/Examples!$F$16))))))+Examples!$F$17*$A10^2) -> 17052.007 | J10: =Examples!$G$18-(Examples!$G$10+Examples!$G$11)*$A10-(Examples!$G$6*Examples!$G$7*Examples!$G$8*EXP(-Examples!$G$9*$A10)*(1-(Examples!$G$12*(1-EXP(-Examples!$G$13*$A10))/(1+EXP(MIN(700,MAX(-700,(Examples!$G$14*$A10-Examples!$G$15)/Examples!$G$16))))))+Examples!$G$17*$A10^2) -> -390152.12 | K10: =(Examples!$G$6*Examples!$G$7*Examples!$G$8*EXP(-Examples!$G$9*$A10)*(1-(Examples!$G$12*(1-EXP(-Examples!$G$13*$A10))/(1+EXP(MIN(700,MAX(-700,(Examples!$G$14*$A10-Examples!$G$15)/Examples!$G$16))))))+Examples!$G$17*$A10^2) -> 1886152.1 | L10: =Examples!$H$18-(Examples!$H$10+Examples!$H$11)*$A10-(Examples!$H$6*Examples!$H$7*Examples!$H$8*EXP(-Examples!$H$9*$A10)*(1-(Examples!$H$12*(1-EXP(-Examples!$H$13*$A10))/(1+EXP(MIN(700,MAX(-700,(Examples!$H$14*$A10-Examples!$H$15)/Examples!$H$16))))))+Examples!$H$17*$A10^2) -> -387849.73 | M10: =(Examples!$H$6*Examples!$H$7*Examples!$H$8*EXP(-Examples!$H$9*$A10)*(1-(Examples!$H$12*(1-EXP(-Examples!$H$13*$A10))/(1+EXP(MIN(700,MAX(-700,(Examples!$H$14*$A10-Examples!$H$15)/Examples!$H$16))))))+Examples!$H$17*$A10^2) -> 1883849.7
A11: =(11-2)/100 -> 0.09 | B11: =Examples!$C$18-(Examples!$C$10+Examples!$C$11)*$A11-(Examples!$C$6*Examples!$C$7*Examples!$C$8*EXP(-Examples!$C$9*$A11)*(1-(Examples!$C$12*(1-EXP(-Examples!$C$13*$A11))/(1+EXP(MIN(700,MAX(-700,(Examples!$C$14*$A11-Examples!$C$15)/Examples!$C$16))))))+Examples!$C$17*$A11^2) -> 25037.829 | C11: =(Examples!$C$6*Examples!$C$7*Examples!$C$8*EXP(-Examples!$C$9*$A11)*(1-(Examples!$C$12*(1-EXP(-Examples!$C$13*$A11))/(1+EXP(MIN(700,MAX(-700,(Examples!$C$14*$A11-Examples!$C$15)/Examples!$C$16))))))+Examples!$C$17*$A11^2) -> 571812.17 | D11: =Examples!$D$18-(Examples!$D$10+Examples!$D$11)*$A11-(Examples!$D$6*Examples!$D$7*Examples!$D$8*EXP(-Examples!$D$9*$A11)*(1-(Examples!$D$12*(1-EXP(-Examples!$D$13*$A11))/(1+EXP(MIN(700,MAX(-700,(Examples!$D$14*$A11-Examples!$D$15)/Examples!$D$16))))))+Examples!$D$17*$A11^2) -> -3040491.8 | E11: =(Examples!$D$6*Examples!$D$7*Examples!$D$8*EXP(-Examples!$D$9*$A11)*(1-(Examples!$D$12*(1-EXP(-Examples!$D$13*$A11))/(1+EXP(MIN(700,MAX(-700,(Examples!$D$14*$A11-Examples!$D$15)/Examples!$D$16))))))+Examples!$D$17*$A11^2) -> 5536441.8 | F11: =Examples!$E$18-(Examples!$E$10+Examples!$E$11)*$A11-(Examples!$E$6*Examples!$E$7*Examples!$E$8*EXP(-Examples!$E$9*$A11)*(1-(Examples!$E$12*(1-EXP(-Examples!$E$13*$A11))/(1+EXP(MIN(700,MAX(-700,(Examples!$E$14*$A11-Examples!$E$15)/Examples!$E$16))))))+Examples!$E$17*$A11^2) -> 542505.57 | G11: =(Examples!$E$6*Examples!$E$7*Examples!$E$8*EXP(-Examples!$E$9*$A11)*(1-(Examples!$E$12*(1-EXP(-Examples!$E$13*$A11))/(1+EXP(MIN(700,MAX(-700,(Examples!$E$14*$A11-Examples!$E$15)/Examples!$E$16))))))+Examples!$E$17*$A11^2) -> 2449844.4 | H11: =Examples!$F$18-(Examples!$F$10+Examples!$F$11)*$A11-(Examples!$F$6*Examples!$F$7*Examples!$F$8*EXP(-Examples!$F$9*$A11)*(1-(Examples!$F$12*(1-EXP(-Examples!$F$13*$A11))/(1+EXP(MIN(700,MAX(-700,(Examples!$F$14*$A11-Examples!$F$15)/Examples!$F$16))))))+Examples!$F$17*$A11^2) -> 131184.43 | I11: =(Examples!$F$6*Examples!$F$7*Examples!$F$8*EXP(-Examples!$F$9*$A11)*(1-(Examples!$F$12*(1-EXP(-Examples!$F$13*$A11))/(1+EXP(MIN(700,MAX(-700,(Examples!$F$14*$A11-Examples!$F$15)/Examples!$F$16))))))+Examples!$F$17*$A11^2) -> 17015.565 | J11: =Examples!$G$18-(Examples!$G$10+Examples!$G$11)*$A11-(Examples!$G$6*Examples!$G$7*Examples!$G$8*EXP(-Examples!$G$9*$A11)*(1-(Examples!$G$12*(1-EXP(-Examples!$G$13*$A11))/(1+EXP(MIN(700,MAX(-700,(Examples!$G$14*$A11-Examples!$G$15)/Examples!$G$16))))))+Examples!$G$17*$A11^2) -> -376963.74 | K11: =(Examples!$G$6*Examples!$G$7*Examples!$G$8*EXP(-Examples!$G$9*$A11)*(1-(Examples!$G$12*(1-EXP(-Examples!$G$13*$A11))/(1+EXP(MIN(700,MAX(-700,(Examples!$G$14*$A11-Examples!$G$15)/Examples!$G$16))))))+Examples!$G$17*$A11^2) -> 1872463.7 | L11: =Examples!$H$18-(Examples!$H$10+Examples!$H$11)*$A11-(Examples!$H$6*Examples!$H$7*Examples!$H$8*EXP(-Examples!$H$9*$A11)*(1-(Examples!$H$12*(1-EXP(-Examples!$H$13*$A11))/(1+EXP(MIN(700,MAX(-700,(Examples!$H$14*$A11-Examples!$H$15)/Examples!$H$16))))))+Examples!$H$17*$A11^2) -> -374356.36 | M11: =(Examples!$H$6*Examples!$H$7*Examples!$H$8*EXP(-Examples!$H$9*$A11)*(1-(Examples!$H$12*(1-EXP(-Examples!$H$13*$A11))/(1+EXP(MIN(700,MAX(-700,(Examples!$H$14*$A11-Examples!$H$15)/Examples!$H$16))))))+Examples!$H$17*$A11^2) -> 1869856.4
A12: =(12-2)/100 -> 0.1 | B12: =Examples!$C$18-(Examples!$C$10+Examples!$C$11)*$A12-(Examples!$C$6*Examples!$C$7*Examples!$C$8*EXP(-Examples!$C$9*$A12)*(1-(Examples!$C$12*(1-EXP(-Examples!$C$13*$A12))/(1+EXP(MIN(700,MAX(-700,(Examples!$C$14*$A12-Examples!$C$15)/Examples!$C$16))))))+Examples!$C$17*$A12^2) -> 27707.785 | C12: =(Examples!$C$6*Examples!$C$7*Examples!$C$8*EXP(-Examples!$C$9*$A12)*(1-(Examples!$C$12*(1-EXP(-Examples!$C$13*$A12))/(1+EXP(MIN(700,MAX(-700,(Examples!$C$14*$A12-Examples!$C$15)/Examples!$C$16))))))+Examples!$C$17*$A12^2) -> 568792.22 | D12: =Examples!$D$18-(Examples!$D$10+Examples!$D$11)*$A12-(Examples!$D$6*Examples!$D$7*Examples!$D$8*EXP(-Examples!$D$9*$A12)*(1-(Examples!$D$12*(1-EXP(-Examples!$D$13*$A12))/(1+EXP(MIN(700,MAX(-700,(Examples!$D$14*$A12-Examples!$D$15)/Examples!$D$16))))))+Examples!$D$17*$A12^2) -> -2991920.7 | E12: =(Examples!$D$6*Examples!$D$7*Examples!$D$8*EXP(-Examples!$D$9*$A12)*(1-(Examples!$D$12*(1-EXP(-Examples!$D$13*$A12))/(1+EXP(MIN(700,MAX(-700,(Examples!$D$14*$A12-Examples!$D$15)/Examples!$D$16))))))+Examples!$D$17*$A12^2) -> 5487420.7 | F12: =Examples!$E$18-(Examples!$E$10+Examples!$E$11)*$A12-(Examples!$E$6*Examples!$E$7*Examples!$E$8*EXP(-Examples!$E$9*$A12)*(1-(Examples!$E$12*(1-EXP(-Examples!$E$13*$A12))/(1+EXP(MIN(700,MAX(-700,(Examples!$E$14*$A12-Examples!$E$15)/Examples!$E$16))))))+Examples!$E$17*$A12^2) -> 567868.32 | G12: =(Examples!$E$6*Examples!$E$7*Examples!$E$8*EXP(-Examples!$E$9*$A12)*(1-(Examples!$E$12*(1-EXP(-Examples!$E$13*$A12))/(1+EXP(MIN(700,MAX(-700,(Examples!$E$14*$A12-Examples!$E$15)/Examples!$E$16))))))+Examples!$E$17*$A12^2) -> 2423631.7 | H12: =Examples!$F$18-(Examples!$F$10+Examples!$F$11)*$A12-(Examples!$F$6*Examples!$F$7*Examples!$F$8*EXP(-Examples!$F$9*$A12)*(1-(Examples!$F$12*(1-EXP(-Examples!$F$13*$A12))/(1+EXP(MIN(700,MAX(-700,(Examples!$F$14*$A12-Examples!$F$15)/Examples!$F$16))))))+Examples!$F$17*$A12^2) -> 131016.53 | I12: =(Examples!$F$6*Examples!$F$7*Examples!$F$8*EXP(-Examples!$F$9*$A12)*(1-(Examples!$F$12*(1-EXP(-Examples!$F$13*$A12))/(1+EXP(MIN(700,MAX(-700,(Examples!$F$14*$A12-Examples!$F$15)/Examples!$F$16))))))+Examples!$F$17*$A12^2) -> 16983.466 | J12: =Examples!$G$18-(Examples!$G$10+Examples!$G$11)*$A12-(Examples!$G$6*Examples!$G$7*Examples!$G$8*EXP(-Examples!$G$9*$A12)*(1-(Examples!$G$12*(1-EXP(-Examples!$G$13*$A12))/(1+EXP(MIN(700,MAX(-700,(Examples!$G$14*$A12-Examples!$G$15)/Examples!$G$16))))))+Examples!$G$17*$A12^2) -> -363892.92 | K12: =(Examples!$G$6*Examples!$G$7*Examples!$G$8*EXP(-Examples!$G$9*$A12)*(1-(Examples!$G$12*(1-EXP(-Examples!$G$13*$A12))/(1+EXP(MIN(700,MAX(-700,(Examples!$G$14*$A12-Examples!$G$15)/Examples!$G$16))))))+Examples!$G$17*$A12^2) -> 1858892.9 | L12: =Examples!$H$18-(Examples!$H$10+Examples!$H$11)*$A12-(Examples!$H$6*Examples!$H$7*Examples!$H$8*EXP(-Examples!$H$9*$A12)*(1-(Examples!$H$12*(1-EXP(-Examples!$H$13*$A12))/(1+EXP(MIN(700,MAX(-700,(Examples!$H$14*$A12-Examples!$H$15)/Examples!$H$16))))))+Examples!$H$17*$A12^2) -> -360976.61 | M12: =(Examples!$H$6*Examples!$H$7*Examples!$H$8*EXP(-Examples!$H$9*$A12)*(1-(Examples!$H$12*(1-EXP(-Examples!$H$13*$A12))/(1+EXP(MIN(700,MAX(-700,(Examples!$H$14*$A12-Examples!$H$15)/Examples!$H$16))))))+Examples!$H$17*$A12^2) -> 1855976.6
A13: =(13-2)/100 -> 0.11 | B13: =Examples!$C$18-(Examples!$C$10+Examples!$C$11)*$A13-(Examples!$C$6*Examples!$C$7*Examples!$C$8*EXP(-Examples!$C$9*$A13)*(1-(Examples!$C$12*(1-EXP(-Examples!$C$13*$A13))/(1+EXP(MIN(700,MAX(-700,(Examples!$C$14*$A13-Examples!$C$15)/Examples!$C$16))))))+Examples!$C$17*$A13^2) -> 30355.725 | C13: =(Examples!$C$6*Examples!$C$7*Examples!$C$8*EXP(-Examples!$C$9*$A13)*(1-(Examples!$C$12*(1-EXP(-Examples!$C$13*$A13))/(1+EXP(MIN(700,MAX(-700,(Examples!$C$14*$A13-Examples!$C$15)/Examples!$C$16))))))+Examples!$C$17*$A13^2) -> 565794.27 | D13: =Examples!$D$18-(Examples!$D$10+Examples!$D$11)*$A13-(Examples!$D$6*Examples!$D$7*Examples!$D$8*EXP(-Examples!$D$9*$A13)*(1-(Examples!$D$12*(1-EXP(-Examples!$D$13*$A13))/(1+EXP(MIN(700,MAX(-700,(Examples!$D$14*$A13-Examples!$D$15)/Examples!$D$16))))))+Examples!$D$17*$A13^2) -> -2943828.5 | E13: =(Examples!$D$6*Examples!$D$7*Examples!$D$8*EXP(-Examples!$D$9*$A13)*(1-(Examples!$D$12*(1-EXP(-Examples!$D$13*$A13))/(1+EXP(MIN(700,MAX(-700,(Examples!$D$14*$A13-Examples!$D$15)/Examples!$D$16))))))+Examples!$D$17*$A13^2) -> 5438878.5 | F13: =Examples!$E$18-(Examples!$E$10+Examples!$E$11)*$A13-(Examples!$E$6*Examples!$E$7*Examples!$E$8*EXP(-Examples!$E$9*$A13)*(1-(Examples!$E$12*(1-EXP(-Examples!$E$13*$A13))/(1+EXP(MIN(700,MAX(-700,(Examples!$E$14*$A13-Examples!$E$15)/Examples!$E$16))))))+Examples!$E$17*$A13^2) -> 592928.07 | G13: =(Examples!$E$6*Examples!$E$7*Examples!$E$8*EXP(-Examples!$E$9*$A13)*(1-(Examples!$E$12*(1-EXP(-Examples!$E$13*$A13))/(1+EXP(MIN(700,MAX(-700,(Examples!$E$14*$A13-Examples!$E$15)/Examples!$E$16))))))+Examples!$E$17*$A13^2) -> 2397721.9 | H13: =Examples!$F$18-(Examples!$F$10+Examples!$F$11)*$A13-(Examples!$F$6*Examples!$F$7*Examples!$F$8*EXP(-Examples!$F$9*$A13)*(1-(Examples!$F$12*(1-EXP(-Examples!$F$13*$A13))/(1+EXP(MIN(700,MAX(-700,(Examples!$F$14*$A13-Examples!$F$15)/Examples!$F$16))))))+Examples!$F$17*$A13^2) -> 130844.29 | I13: =(Examples!$F$6*Examples!$F$7*Examples!$F$8*EXP(-Examples!$F$9*$A13)*(1-(Examples!$F$12*(1-EXP(-Examples!$F$13*$A13))/(1+EXP(MIN(700,MAX(-700,(Examples!$F$14*$A13-Examples!$F$15)/Examples!$F$16))))))+Examples!$F$17*$A13^2) -> 16955.707 | J13: =Examples!$G$18-(Examples!$G$10+Examples!$G$11)*$A13-(Examples!$G$6*Examples!$G$7*Examples!$G$8*EXP(-Examples!$G$9*$A13)*(1-(Examples!$G$12*(1-EXP(-Examples!$G$13*$A13))/(1+EXP(MIN(700,MAX(-700,(Examples!$G$14*$A13-Examples!$G$15)/Examples!$G$16))))))+Examples!$G$17*$A13^2) -> -350938.76 | K13: =(Examples!$G$6*Examples!$G$7*Examples!$G$8*EXP(-Examples!$G$9*$A13)*(1-(Examples!$G$12*(1-EXP(-Examples!$G$13*$A13))/(1+EXP(MIN(700,MAX(-700,(Examples!$G$14*$A13-Examples!$G$15)/Examples!$G$16))))))+Examples!$G$17*$A13^2) -> 1845438.8 | L13: =Examples!$H$18-(Examples!$H$10+Examples!$H$11)*$A13-(Examples!$H$6*Examples!$H$7*Examples!$H$8*EXP(-Examples!$H$9*$A13)*(1-(Examples!$H$12*(1-EXP(-Examples!$H$13*$A13))/(1+EXP(MIN(700,MAX(-700,(Examples!$H$14*$A13-Examples!$H$15)/Examples!$H$16))))))+Examples!$H$17*$A13^2) -> -347709.59 | M13: =(Examples!$H$6*Examples!$H$7*Examples!$H$8*EXP(-Examples!$H$9*$A13)*(1-(Examples!$H$12*(1-EXP(-Examples!$H$13*$A13))/(1+EXP(MIN(700,MAX(-700,(Examples!$H$14*$A13-Examples!$H$15)/Examples!$H$16))))))+Examples!$H$17*$A13^2) -> 1842209.6
A14: =(14-2)/100 -> 0.12 | B14: =Examples!$C$18-(Examples!$C$10+Examples!$C$11)*$A14-(Examples!$C$6*Examples!$C$7*Examples!$C$8*EXP(-Examples!$C$9*$A14)*(1-(Examples!$C$12*(1-EXP(-Examples!$C$13*$A14))/(1+EXP(MIN(700,MAX(-700,(Examples!$C$14*$A14-Examples!$C$15)/Examples!$C$16))))))+Examples!$C$17*$A14^2) -> 32981.752 | C14: =(Examples!$C$6*Examples!$C$7*Examples!$C$8*EXP(-Examples!$C$9*$A14)*(1-(Examples!$C$12*(1-EXP(-Examples!$C$13*$A14))/(1+EXP(MIN(700,MAX(-700,(Examples!$C$14*$A14-Examples!$C$15)/Examples!$C$16))))))+Examples!$C$17*$A14^2) -> 562818.25 | D14: =Examples!$D$18-(Examples!$D$10+Examples!$D$11)*$A14-(Examples!$D$6*Examples!$D$7*Examples!$D$8*EXP(-Examples!$D$9*$A14)*(1-(Examples!$D$12*(1-EXP(-Examples!$D$13*$A14))/(1+EXP(MIN(700,MAX(-700,(Examples!$D$14*$A14-Examples!$D$15)/Examples!$D$16))))))+Examples!$D$17*$A14^2) -> -2896210.5 | E14: =(Examples!$D$6*Examples!$D$7*Examples!$D$8*EXP(-Examples!$D$9*$A14)*(1-(Examples!$D$12*(1-EXP(-Examples!$D$13*$A14))/(1+EXP(MIN(700,MAX(-700,(Examples!$D$14*$A14-Examples!$D$15)/Examples!$D$16))))))+Examples!$D$17*$A14^2) -> 5390810.5 | F14: =Examples!$E$18-(Examples!$E$10+Examples!$E$11)*$A14-(Examples!$E$6*Examples!$E$7*Examples!$E$8*EXP(-Examples!$E$9*$A14)*(1-(Examples!$E$12*(1-EXP(-Examples!$E$13*$A14))/(1+EXP(MIN(700,MAX(-700,(Examples!$E$14*$A14-Examples!$E$15)/Examples!$E$16))))))+Examples!$E$17*$A14^2) -> 617688.37 | G14: =(Examples!$E$6*Examples!$E$7*Examples!$E$8*EXP(-Examples!$E$9*$A14)*(1-(Examples!$E$12*(1-EXP(-Examples!$E$13*$A14))/(1+EXP(MIN(700,MAX(-700,(Examples!$E$14*$A14-Examples!$E$15)/Examples!$E$16))))))+Examples!$E$17*$A14^2) -> 2372111.6 | H14: =Examples!$F$18-(Examples!$F$10+Examples!$F$11)*$A14-(Examples!$F$6*Examples!$F$7*Examples!$F$8*EXP(-Examples!$F$9*$A14)*(1-(Examples!$F$12*(1-EXP(-Examples!$F$13*$A14))/(1+EXP(MIN(700,MAX(-700,(Examples!$F$14*$A14-Examples!$F$15)/Examples!$F$16))))))+Examples!$F$17*$A14^2) -> 130667.71 | I14: =(Examples!$F$6*Examples!$F$7*Examples!$F$8*EXP(-Examples!$F$9*$A14)*(1-(Examples!$F$12*(1-EXP(-Examples!$F$13*$A14))/(1+EXP(MIN(700,MAX(-700,(Examples!$F$14*$A14-Examples!$F$15)/Examples!$F$16))))))+Examples!$F$17*$A14^2) -> 16932.288 | J14: =Examples!$G$18-(Examples!$G$10+Examples!$G$11)*$A14-(Examples!$G$6*Examples!$G$7*Examples!$G$8*EXP(-Examples!$G$9*$A14)*(1-(Examples!$G$12*(1-EXP(-Examples!$G$13*$A14))/(1+EXP(MIN(700,MAX(-700,(Examples!$G$14*$A14-Examples!$G$15)/Examples!$G$16))))))+Examples!$G$17*$A14^2) -> -338100.4 | K14: =(Examples!$G$6*Examples!$G$7*Examples!$G$8*EXP(-Examples!$G$9*$A14)*(1-(Examples!$G$12*(1-EXP(-Examples!$G$13*$A14))/(1+EXP(MIN(700,MAX(-700,(Examples!$G$14*$A14-Examples!$G$15)/Examples!$G$16))))))+Examples!$G$17*$A14^2) -> 1832100.4 | L14: =Examples!$H$18-(Examples!$H$10+Examples!$H$11)*$A14-(Examples!$H$6*Examples!$H$7*Examples!$H$8*EXP(-Examples!$H$9*$A14)*(1-(Examples!$H$12*(1-EXP(-Examples!$H$13*$A14))/(1+EXP(MIN(700,MAX(-700,(Examples!$H$14*$A14-Examples!$H$15)/Examples!$H$16))))))+Examples!$H$17*$A14^2) -> -334554.38 | M14: =(Examples!$H$6*Examples!$H$7*Examples!$H$8*EXP(-Examples!$H$9*$A14)*(1-(Examples!$H$12*(1-EXP(-Examples!$H$13*$A14))/(1+EXP(MIN(700,MAX(-700,(Examples!$H$14*$A14-Examples!$H$15)/Examples!$H$16))))))+Examples!$H$17*$A14^2) -> 1828554.4
A15: =(15-2)/100 -> 0.13 | B15: =Examples!$C$18-(Examples!$C$10+Examples!$C$11)*$A15-(Examples!$C$6*Examples!$C$7*Examples!$C$8*EXP(-Examples!$C$9*$A15)*(1-(Examples!$C$12*(1-EXP(-Examples!$C$13*$A15))/(1+EXP(MIN(700,MAX(-700,(Examples!$C$14*$A15-Examples!$C$15)/Examples!$C$16))))))+Examples!$C$17*$A15^2) -> 35585.964 | C15: =(Examples!$C$6*Examples!$C$7*Examples!$C$8*EXP(-Examples!$C$9*$A15)*(1-(Examples!$C$12*(1-EXP(-Examples!$C$13*$A15))/(1+EXP(MIN(700,MAX(-700,(Examples!$C$14*$A15-Examples!$C$15)/Examples!$C$16))))))+Examples!$C$17*$A15^2) -> 559864.04 | D15: =Examples!$D$18-(Examples!$D$10+Examples!$D$11)*$A15-(Examples!$D$6*Examples!$D$7*Examples!$D$8*EXP(-Examples!$D$9*$A15)*(1-(Examples!$D$12*(1-EXP(-Examples!$D$13*$A15))/(1+EXP(MIN(700,MAX(-700,(Examples!$D$14*$A15-Examples!$D$15)/Examples!$D$16))))))+Examples!$D$17*$A15^2) -> -2849062 | E15: =(Examples!$D$6*Examples!$D$7*Examples!$D$8*EXP(-Examples!$D$9*$A15)*(1-(Examples!$D$12*(1-EXP(-Examples!$D$13*$A15))/(1+EXP(MIN(700,MAX(-700,(Examples!$D$14*$A15-Examples!$D$15)/Examples!$D$16))))))+Examples!$D$17*$A15^2) -> 5343212 | F15: =Examples!$E$18-(Examples!$E$10+Examples!$E$11)*$A15-(Examples!$E$6*Examples!$E$7*Examples!$E$8*EXP(-Examples!$E$9*$A15)*(1-(Examples!$E$12*(1-EXP(-Examples!$E$13*$A15))/(1+EXP(MIN(700,MAX(-700,(Examples!$E$14*$A15-Examples!$E$15)/Examples!$E$16))))))+Examples!$E$17*$A15^2) -> 642152.7 | G15: =(Examples!$E$6*Examples!$E$7*Examples!$E$8*EXP(-Examples!$E$9*$A15)*(1-(Examples!$E$12*(1-EXP(-Examples!$E$13*$A15))/(1+EXP(MIN(700,MAX(-700,(Examples!$E$14*$A15-Examples!$E$15)/Examples!$E$16))))))+Examples!$E$17*$A15^2) -> 2346797.3 | H15: =Examples!$F$18-(Examples!$F$10+Examples!$F$11)*$A15-(Examples!$F$6*Examples!$F$7*Examples!$F$8*EXP(-Examples!$F$9*$A15)*(1-(Examples!$F$12*(1-EXP(-Examples!$F$13*$A15))/(1+EXP(MIN(700,MAX(-700,(Examples!$F$14*$A15-Examples!$F$15)/Examples!$F$16))))))+Examples!$F$17*$A15^2) -> 130486.79 | I15: =(Examples!$F$6*Examples!$F$7*Examples!$F$8*EXP(-Examples!$F$9*$A15)*(1-(Examples!$F$12*(1-EXP(-Examples!$F$13*$A15))/(1+EXP(MIN(700,MAX(-700,(Examples!$F$14*$A15-Examples!$F$15)/Examples!$F$16))))))+Examples!$F$17*$A15^2) -> 16913.208 | J15: =Examples!$G$18-(Examples!$G$10+Examples!$G$11)*$A15-(Examples!$G$6*Examples!$G$7*Examples!$G$8*EXP(-Examples!$G$9*$A15)*(1-(Examples!$G$12*(1-EXP(-Examples!$G$13*$A15))/(1+EXP(MIN(700,MAX(-700,(Examples!$G$14*$A15-Examples!$G$15)/Examples!$G$16))))))+Examples!$G$17*$A15^2) -> -325376.96 | K15: =(Examples!$G$6*Examples!$G$7*Examples!$G$8*EXP(-Examples!$G$9*$A15)*(1-(Examples!$G$12*(1-EXP(-Examples!$G$13*$A15))/(1+EXP(MIN(700,MAX(-700,(Examples!$G$14*$A15-Examples!$G$15)/Examples!$G$16))))))+Examples!$G$17*$A15^2) -> 1818877 | L15: =Examples!$H$18-(Examples!$H$10+Examples!$H$11)*$A15-(Examples!$H$6*Examples!$H$7*Examples!$H$8*EXP(-Examples!$H$9*$A15)*(1-(Examples!$H$12*(1-EXP(-Examples!$H$13*$A15))/(1+EXP(MIN(700,MAX(-700,(Examples!$H$14*$A15-Examples!$H$15)/Examples!$H$16))))))+Examples!$H$17*$A15^2) -> -321510.07 | M15: =(Examples!$H$6*Examples!$H$7*Examples!$H$8*EXP(-Examples!$H$9*$A15)*(1-(Examples!$H$12*(1-EXP(-Examples!$H$13*$A15))/(1+EXP(MIN(700,MAX(-700,(Examples!$H$14*$A15-Examples!$H$15)/Examples!$H$16))))))+Examples!$H$17*$A15^2) -> 1815010.1
A16: =(16-2)/100 -> 0.14 | B16: =Examples!$C$18-(Examples!$C$10+Examples!$C$11)*$A16-(Examples!$C$6*Examples!$C$7*Examples!$C$8*EXP(-Examples!$C$9*$A16)*(1-(Examples!$C$12*(1-EXP(-Examples!$C$13*$A16))/(1+EXP(MIN(700,MAX(-700,(Examples!$C$14*$A16-Examples!$C$15)/Examples!$C$16))))))+Examples!$C$17*$A16^2) -> 38168.461 | C16: =(Examples!$C$6*Examples!$C$7*Examples!$C$8*EXP(-Examples!$C$9*$A16)*(1-(Examples!$C$12*(1-EXP(-Examples!$C$13*$A16))/(1+EXP(MIN(700,MAX(-700,(Examples!$C$14*$A16-Examples!$C$15)/Examples!$C$16))))))+Examples!$C$17*$A16^2) -> 556931.54 | D16: =Examples!$D$18-(Examples!$D$10+Examples!$D$11)*$A16-(Examples!$D$6*Examples!$D$7*Examples!$D$8*EXP(-Examples!$D$9*$A16)*(1-(Examples!$D$12*(1-EXP(-Examples!$D$13*$A16))/(1+EXP(MIN(700,MAX(-700,(Examples!$D$14*$A16-Examples!$D$15)/Examples!$D$16))))))+Examples!$D$17*$A16^2) -> -2802378.3 | E16: =(Examples!$D$6*Examples!$D$7*Examples!$D$8*EXP(-Examples!$D$9*$A16)*(1-(Examples!$D$12*(1-EXP(-Examples!$D$13*$A16))/(1+EXP(MIN(700,MAX(-700,(Examples!$D$14*$A16-Examples!$D$15)/Examples!$D$16))))))+Examples!$D$17*$A16^2) -> 5296078.3 | F16: =Examples!$E$18-(Examples!$E$10+Examples!$E$11)*$A16-(Examples!$E$6*Examples!$E$7*Examples!$E$8*EXP(-Examples!$E$9*$A16)*(1-(Examples!$E$12*(1-EXP(-Examples!$E$13*$A16))/(1+EXP(MIN(700,MAX(-700,(Examples!$E$14*$A16-Examples!$E$15)/Examples!$E$16))))))+Examples!$E$17*$A16^2) -> 666324.53 | G16: =(Examples!$E$6*Examples!$E$7*Examples!$E$8*EXP(-Examples!$E$9*$A16)*(1-(Examples!$E$12*(1-EXP(-Examples!$E$13*$A16))/(1+EXP(MIN(700,MAX(-700,(Examples!$E$14*$A16-Examples!$E$15)/Examples!$E$16))))))+Examples!$E$17*$A16^2) -> 2321775.5 | H16: =Examples!$F$18-(Examples!$F$10+Examples!$F$11)*$A16-(Examples!$F$6*Examples!$F$7*Examples!$F$8*EXP(-Examples!$F$9*$A16)*(1-(Examples!$F$12*(1-EXP(-Examples!$F$13*$A16))/(1+EXP(MIN(700,MAX(-700,(Examples!$F$14*$A16-Examples!$F$15)/Examples!$F$16))))))+Examples!$F$17*$A16^2) -> 130301.53 | I16: =(Examples!$F$6*Examples!$F$7*Examples!$F$8*EXP(-Examples!$F$9*$A16)*(1-(Examples!$F$12*(1-EXP(-Examples!$F$13*$A16))/(1+EXP(MIN(700,MAX(-700,(Examples!$F$14*$A16-Examples!$F$15)/Examples!$F$16))))))+Examples!$F$17*$A16^2) -> 16898.465 | J16: =Examples!$G$18-(Examples!$G$10+Examples!$G$11)*$A16-(Examples!$G$6*Examples!$G$7*Examples!$G$8*EXP(-Examples!$G$9*$A16)*(1-(Examples!$G$12*(1-EXP(-Examples!$G$13*$A16))/(1+EXP(MIN(700,MAX(-700,(Examples!$G$14*$A16-Examples!$G$15)/Examples!$G$16))))))+Examples!$G$17*$A16^2) -> -312767.57 | K16: =(Examples!$G$6*Examples!$G$7*Examples!$G$8*EXP(-Examples!$G$9*$A16)*(1-(Examples!$G$12*(1-EXP(-Examples!$G$13*$A16))/(1+EXP(MIN(700,MAX(-700,(Examples!$G$14*$A16-Examples!$G$15)/Examples!$G$16))))))+Examples!$G$17*$A16^2) -> 1805767.6 | L16: =Examples!$H$18-(Examples!$H$10+Examples!$H$11)*$A16-(Examples!$H$6*Examples!$H$7*Examples!$H$8*EXP(-Examples!$H$9*$A16)*(1-(Examples!$H$12*(1-EXP(-Examples!$H$13*$A16))/(1+EXP(MIN(700,MAX(-700,(Examples!$H$14*$A16-Examples!$H$15)/Examples!$H$16))))))+Examples!$H$17*$A16^2) -> -308575.78 | M16: =(Examples!$H$6*Examples!$H$7*Examples!$H$8*EXP(-Examples!$H$9*$A16)*(1-(Examples!$H$12*(1-EXP(-Examples!$H$13*$A16))/(1+EXP(MIN(700,MAX(-700,(Examples!$H$14*$A16-Examples!$H$15)/Examples!$H$16))))))+Examples!$H$17*$A16^2) -> 1801575.8
A17: =(17-2)/100 -> 0.15 | B17: =Examples!$C$18-(Examples!$C$10+Examples!$C$11)*$A17-(Examples!$C$6*Examples!$C$7*Examples!$C$8*EXP(-Examples!$C$9*$A17)*(1-(Examples!$C$12*(1-EXP(-Examples!$C$13*$A17))/(1+EXP(MIN(700,MAX(-700,(Examples!$C$14*$A17-Examples!$C$15)/Examples!$C$16))))))+Examples!$C$17*$A17^2) -> 40729.339 | C17: =(Examples!$C$6*Examples!$C$7*Examples!$C$8*EXP(-Examples!$C$9*$A17)*(1-(Examples!$C$12*(1-EXP(-Examples!$C$13*$A17))/(1+EXP(MIN(700,MAX(-700,(Examples!$C$14*$A17-Examples!$C$15)/Examples!$C$16))))))+Examples!$C$17*$A17^2) -> 554020.66 | D17: =Examples!$D$18-(Examples!$D$10+Examples!$D$11)*$A17-(Examples!$D$6*Examples!$D$7*Examples!$D$8*EXP(-Examples!$D$9*$A17)*(1-(Examples!$D$12*(1-EXP(-Examples!$D$13*$A17))/(1+EXP(MIN(700,MAX(-700,(Examples!$D$14*$A17-Examples!$D$15)/Examples!$D$16))))))+Examples!$D$17*$A17^2) -> -2756154.8 | E17: =(Examples!$D$6*Examples!$D$7*Examples!$D$8*EXP(-Examples!$D$9*$A17)*(1-(Examples!$D$12*(1-EXP(-Examples!$D$13*$A17))/(1+EXP(MIN(700,MAX(-700,(Examples!$D$14*$A17-Examples!$D$15)/Examples!$D$16))))))+Examples!$D$17*$A17^2) -> 5249404.8 | F17: =Examples!$E$18-(Examples!$E$10+Examples!$E$11)*$A17-(Examples!$E$6*Examples!$E$7*Examples!$E$8*EXP(-Examples!$E$9*$A17)*(1-(Examples!$E$12*(1-EXP(-Examples!$E$13*$A17))/(1+EXP(MIN(700,MAX(-700,(Examples!$E$14*$A17-Examples!$E$15)/Examples!$E$16))))))+Examples!$E$17*$A17^2) -> 690207.28 | G17: =(Examples!$E$6*Examples!$E$7*Examples!$E$8*EXP(-Examples!$E$9*$A17)*(1-(Examples!$E$12*(1-EXP(-Examples!$E$13*$A17))/(1+EXP(MIN(700,MAX(-700,(Examples!$E$14*$A17-Examples!$E$15)/Examples!$E$16))))))+Examples!$E$17*$A17^2) -> 2297042.7 | H17: =Examples!$F$18-(Examples!$F$10+Examples!$F$11)*$A17-(Examples!$F$6*Examples!$F$7*Examples!$F$8*EXP(-Examples!$F$9*$A17)*(1-(Examples!$F$12*(1-EXP(-Examples!$F$13*$A17))/(1+EXP(MIN(700,MAX(-700,(Examples!$F$14*$A17-Examples!$F$15)/Examples!$F$16))))))+Examples!$F$17*$A17^2) -> 130111.94 | I17: =(Examples!$F$6*Examples!$F$7*Examples!$F$8*EXP(-Examples!$F$9*$A17)*(1-(Examples!$F$12*(1-EXP(-Examples!$F$13*$A17))/(1+EXP(MIN(700,MAX(-700,(Examples!$F$14*$A17-Examples!$F$15)/Examples!$F$16))))))+Examples!$F$17*$A17^2) -> 16888.06 | J17: =Examples!$G$18-(Examples!$G$10+Examples!$G$11)*$A17-(Examples!$G$6*Examples!$G$7*Examples!$G$8*EXP(-Examples!$G$9*$A17)*(1-(Examples!$G$12*(1-EXP(-Examples!$G$13*$A17))/(1+EXP(MIN(700,MAX(-700,(Examples!$G$14*$A17-Examples!$G$15)/Examples!$G$16))))))+Examples!$G$17*$A17^2) -> -300271.4 | K17: =(Examples!$G$6*Examples!$G$7*Examples!$G$8*EXP(-Examples!$G$9*$A17)*(1-(Examples!$G$12*(1-EXP(-Examples!$G$13*$A17))/(1+EXP(MIN(700,MAX(-700,(Examples!$G$14*$A17-Examples!$G$15)/Examples!$G$16))))))+Examples!$G$17*$A17^2) -> 1792771.4 | L17: =Examples!$H$18-(Examples!$H$10+Examples!$H$11)*$A17-(Examples!$H$6*Examples!$H$7*Examples!$H$8*EXP(-Examples!$H$9*$A17)*(1-(Examples!$H$12*(1-EXP(-Examples!$H$13*$A17))/(1+EXP(MIN(700,MAX(-700,(Examples!$H$14*$A17-Examples!$H$15)/Examples!$H$16))))))+Examples!$H$17*$A17^2) -> -295750.63 | M17: =(Examples!$H$6*Examples!$H$7*Examples!$H$8*EXP(-Examples!$H$9*$A17)*(1-(Examples!$H$12*(1-EXP(-Examples!$H$13*$A17))/(1+EXP(MIN(700,MAX(-700,(Examples!$H$14*$A17-Examples!$H$15)/Examples!$H$16))))))+Examples!$H$17*$A17^2) -> 1788250.6
A18: =(18-2)/100 -> 0.16 | B18: =Examples!$C$18-(Examples!$C$10+Examples!$C$11)*$A18-(Examples!$C$6*Examples!$C$7*Examples!$C$8*EXP(-Examples!$C$9*$A18)*(1-(Examples!$C$12*(1-EXP(-Examples!$C$13*$A18))/(1+EXP(MIN(700,MAX(-700,(Examples!$C$14*$A18-Examples!$C$15)/Examples!$C$16))))))+Examples!$C$17*$A18^2) -> 43268.695 | C18: =(Examples!$C$6*Examples!$C$7*Examples!$C$8*EXP(-Examples!$C$9*$A18)*(1-(Examples!$C$12*(1-EXP(-Examples!$C$13*$A18))/(1+EXP(MIN(700,MAX(-700,(Examples!$C$14*$A18-Examples!$C$15)/Examples!$C$16))))))+Examples!$C$17*$A18^2) -> 551131.31 | D18: =Examples!$D$18-(Examples!$D$10+Examples!$D$11)*$A18-(Examples!$D$6*Examples!$D$7*Examples!$D$8*EXP(-Examples!$D$9*$A18)*(1-(Examples!$D$12*(1-EXP(-Examples!$D$13*$A18))/(1+EXP(MIN(700,MAX(-700,(Examples!$D$14*$A18-Examples!$D$15)/Examples!$D$16))))))+Examples!$D$17*$A18^2) -> -2710386.9 | E18: =(Examples!$D$6*Examples!$D$7*Examples!$D$8*EXP(-Examples!$D$9*$A18)*(1-(Examples!$D$12*(1-EXP(-Examples!$D$13*$A18))/(1+EXP(MIN(700,MAX(-700,(Examples!$D$14*$A18-Examples!$D$15)/Examples!$D$16))))))+Examples!$D$17*$A18^2) -> 5203186.9 | F18: =Examples!$E$18-(Examples!$E$10+Examples!$E$11)*$A18-(Examples!$E$6*Examples!$E$7*Examples!$E$8*EXP(-Examples!$E$9*$A18)*(1-(Examples!$E$12*(1-EXP(-Examples!$E$13*$A18))/(1+EXP(MIN(700,MAX(-700,(Examples!$E$14*$A18-Examples!$E$15)/Examples!$E$16))))))+Examples!$E$17*$A18^2) -> 713804.32 | G18: =(Examples!$E$6*Examples!$E$7*Examples!$E$8*EXP(-Examples!$E$9*$A18)*(1-(Examples!$E$12*(1-EXP(-Examples!$E$13*$A18))/(1+EXP(MIN(700,MAX(-700,(Examples!$E$14*$A18-Examples!$E$15)/Examples!$E$16))))))+Examples!$E$17*$A18^2) -> 2272595.7 | H18: =Examples!$F$18-(Examples!$F$10+Examples!$F$11)*$A18-(Examples!$F$6*Examples!$F$7*Examples!$F$8*EXP(-Examples!$F$9*$A18)*(1-(Examples!$F$12*(1-EXP(-Examples!$F$13*$A18))/(1+EXP(MIN(700,MAX(-700,(Examples!$F$14*$A18-Examples!$F$15)/Examples!$F$16))))))+Examples!$F$17*$A18^2) -> 129918.01 | I18: =(Examples!$F$6*Examples!$F$7*Examples!$F$8*EXP(-Examples!$F$9*$A18)*(1-(Examples!$F$12*(1-EXP(-Examples!$F$13*$A18))/(1+EXP(MIN(700,MAX(-700,(Examples!$F$14*$A18-Examples!$F$15)/Examples!$F$16))))))+Examples!$F$17*$A18^2) -> 16881.99 | J18: =Examples!$G$18-(Examples!$G$10+Examples!$G$11)*$A18-(Examples!$G$6*Examples!$G$7*Examples!$G$8*EXP(-Examples!$G$9*$A18)*(1-(Examples!$G$12*(1-EXP(-Examples!$G$13*$A18))/(1+EXP(MIN(700,MAX(-700,(Examples!$G$14*$A18-Examples!$G$15)/Examples!$G$16))))))+Examples!$G$17*$A18^2) -> -287887.58 | K18: =(Examples!$G$6*Examples!$G$7*Examples!$G$8*EXP(-Examples!$G$9*$A18)*(1-(Examples!$G$12*(1-EXP(-Examples!$G$13*$A18))/(1+EXP(MIN(700,MAX(-700,(Examples!$G$14*$A18-Examples!$G$15)/Examples!$G$16))))))+Examples!$G$17*$A18^2) -> 1779887.6 | L18: =Examples!$H$18-(Examples!$H$10+Examples!$H$11)*$A18-(Examples!$H$6*Examples!$H$7*Examples!$H$8*EXP(-Examples!$H$9*$A18)*(1-(Examples!$H$12*(1-EXP(-Examples!$H$13*$A18))/(1+EXP(MIN(700,MAX(-700,(Examples!$H$14*$A18-Examples!$H$15)/Examples!$H$16))))))+Examples!$H$17*$A18^2) -> -283033.74 | M18: =(Examples!$H$6*Examples!$H$7*Examples!$H$8*EXP(-Examples!$H$9*$A18)*(1-(Examples!$H$12*(1-EXP(-Examples!$H$13*$A18))/(1+EXP(MIN(700,MAX(-700,(Examples!$H$14*$A18-Examples!$H$15)/Examples!$H$16))))))+Examples!$H$17*$A18^2) -> 1775033.7
A19: =(19-2)/100 -> 0.17 | B19: =Examples!$C$18-(Examples!$C$10+Examples!$C$11)*$A19-(Examples!$C$6*Examples!$C$7*Examples!$C$8*EXP(-Examples!$C$9*$A19)*(1-(Examples!$C$12*(1-EXP(-Examples!$C$13*$A19))/(1+EXP(MIN(700,MAX(-700,(Examples!$C$14*$A19-Examples!$C$15)/Examples!$C$16))))))+Examples!$C$17*$A19^2) -> 45786.621 | C19: =(Examples!$C$6*Examples!$C$7*Examples!$C$8*EXP(-Examples!$C$9*$A19)*(1-(Examples!$C$12*(1-EXP(-Examples!$C$13*$A19))/(1+EXP(MIN(700,MAX(-700,(Examples!$C$14*$A19-Examples!$C$15)/Examples!$C$16))))))+Examples!$C$17*$A19^2) -> 548263.38 | D19: =Examples!$D$18-(Examples!$D$10+Examples!$D$11)*$A19-(Examples!$D$6*Examples!$D$7*Examples!$D$8*EXP(-Examples!$D$9*$A19)*(1-(Examples!$D$12*(1-EXP(-Examples!$D$13*$A19))/(1+EXP(MIN(700,MAX(-700,(Examples!$D$14*$A19-Examples!$D$15)/Examples!$D$16))))))+Examples!$D$17*$A19^2) -> -2665070.1 | E19: =(Examples!$D$6*Examples!$D$7*Examples!$D$8*EXP(-Examples!$D$9*$A19)*(1-(Examples!$D$12*(1-EXP(-Examples!$D$13*$A19))/(1+EXP(MIN(700,MAX(-700,(Examples!$D$14*$A19-Examples!$D$15)/Examples!$D$16))))))+Examples!$D$17*$A19^2) -> 5157420.1 | F19: =Examples!$E$18-(Examples!$E$10+Examples!$E$11)*$A19-(Examples!$E$6*Examples!$E$7*Examples!$E$8*EXP(-Examples!$E$9*$A19)*(1-(Examples!$E$12*(1-EXP(-Examples!$E$13*$A19))/(1+EXP(MIN(700,MAX(-700,(Examples!$E$14*$A19-Examples!$E$15)/Examples!$E$16))))))+Examples!$E$17*$A19^2) -> 737119 | G19: =(Examples!$E$6*Examples!$E$7*Examples!$E$8*EXP(-Examples!$E$9*$A19)*(1-(Examples!$E$12*(1-EXP(-Examples!$E$13*$A19))/(1+EXP(MIN(700,MAX(-700,(Examples!$E$14*$A19-Examples!$E$15)/Examples!$E$16))))))+Examples!$E$17*$A19^2) -> 2248431 | H19: =Examples!$F$18-(Examples!$F$10+Examples!$F$11)*$A19-(Examples!$F$6*Examples!$F$7*Examples!$F$8*EXP(-Examples!$F$9*$A19)*(1-(Examples!$F$12*(1-EXP(-Examples!$F$13*$A19))/(1+EXP(MIN(700,MAX(-700,(Examples!$F$14*$A19-Examples!$F$15)/Examples!$F$16))))))+Examples!$F$17*$A19^2) -> 129719.74 | I19: =(Examples!$F$6*Examples!$F$7*Examples!$F$8*EXP(-Examples!$F$9*$A19)*(1-(Examples!$F$12*(1-EXP(-Examples!$F$13*$A19))/(1+EXP(MIN(700,MAX(-700,(Examples!$F$14*$A19-Examples!$F$15)/Examples!$F$16))))))+Examples!$F$17*$A19^2) -> 16880.255 | J19: =Examples!$G$18-(Examples!$G$10+Examples!$G$11)*$A19-(Examples!$G$6*Examples!$G$7*Examples!$G$8*EXP(-Examples!$G$9*$A19)*(1-(Examples!$G$12*(1-EXP(-Examples!$G$13*$A19))/(1+EXP(MIN(700,MAX(-700,(Examples!$G$14*$A19-Examples!$G$15)/Examples!$G$16))))))+Examples!$G$17*$A19^2) -> -275615.28 | K19: =(Examples!$G$6*Examples!$G$7*Examples!$G$8*EXP(-Examples!$G$9*$A19)*(1-(Examples!$G$12*(1-EXP(-Examples!$G$13*$A19))/(1+EXP(MIN(700,MAX(-700,(Examples!$G$14*$A19-Examples!$G$15)/Examples!$G$16))))))+Examples!$G$17*$A19^2) -> 1767115.3 | L19: =Examples!$H$18-(Examples!$H$10+Examples!$H$11)*$A19-(Examples!$H$6*Examples!$H$7*Examples!$H$8*EXP(-Examples!$H$9*$A19)*(1-(Examples!$H$12*(1-EXP(-Examples!$H$13*$A19))/(1+EXP(MIN(700,MAX(-700,(Examples!$H$14*$A19-Examples!$H$15)/Examples!$H$16))))))+Examples!$H$17*$A19^2) -> -270424.23 | M19: =(Examples!$H$6*Examples!$H$7*Examples!$H$8*EXP(-Examples!$H$9*$A19)*(1-(Examples!$H$12*(1-EXP(-Examples!$H$13*$A19))/(1+EXP(MIN(700,MAX(-700,(Examples!$H$14*$A19-Examples!$H$15)/Examples!$H$16))))))+Examples!$H$17*$A19^2) -> 1761924.2
A20: =(20-2)/100 -> 0.18 | B20: =Examples!$C$18-(Examples!$C$10+Examples!$C$11)*$A20-(Examples!$C$6*Examples!$C$7*Examples!$C$8*EXP(-Examples!$C$9*$A20)*(1-(Examples!$C$12*(1-EXP(-Examples!$C$13*$A20))/(1+EXP(MIN(700,MAX(-700,(Examples!$C$14*$A20-Examples!$C$15)/Examples!$C$16))))))+Examples!$C$17*$A20^2) -> 48283.211 | C20: =(Examples!$C$6*Examples!$C$7*Examples!$C$8*EXP(-Examples!$C$9*$A20)*(1-(Examples!$C$12*(1-EXP(-Examples!$C$13*$A20))/(1+EXP(MIN(700,MAX(-700,(Examples!$C$14*$A20-Examples!$C$15)/Examples!$C$16))))))+Examples!$C$17*$A20^2) -> 545416.79 | D20: =Examples!$D$18-(Examples!$D$10+Examples!$D$11)*$A20-(Examples!$D$6*Examples!$D$7*Examples!$D$8*EXP(-Examples!$D$9*$A20)*(1-(Examples!$D$12*(1-EXP(-Examples!$D$13*$A20))/(1+EXP(MIN(700,MAX(-700,(Examples!$D$14*$A20-Examples!$D$15)/Examples!$D$16))))))+Examples!$D$17*$A20^2) -> -2620199.9 | E20: =(Examples!$D$6*Examples!$D$7*Examples!$D$8*EXP(-Examples!$D$9*$A20)*(1-(Examples!$D$12*(1-EXP(-Examples!$D$13*$A20))/(1+EXP(MIN(700,MAX(-700,(Examples!$D$14*$A20-Examples!$D$15)/Examples!$D$16))))))+Examples!$D$17*$A20^2) -> 5112099.9 | F20: =Examples!$E$18-(Examples!$E$10+Examples!$E$11)*$A20-(Examples!$E$6*Examples!$E$7*Examples!$E$8*EXP(-Examples!$E$9*$A20)*(1-(Examples!$E$12*(1-EXP(-Examples!$E$13*$A20))/(1+EXP(MIN(700,MAX(-700,(Examples!$E$14*$A20-Examples!$E$15)/Examples!$E$16))))))+Examples!$E$17*$A20^2) -> 760154.6 | G20: =(Examples!$E$6*Examples!$E$7*Examples!$E$8*EXP(-Examples!$E$9*$A20)*(1-(Examples!$E$12*(1-EXP(-Examples!$E$13*$A20))/(1+EXP(MIN(700,MAX(-700,(Examples!$E$14*$A20-Examples!$E$15)/Examples!$E$16))))))+Examples!$E$17*$A20^2) -> 2224545.4 | H20: =Examples!$F$18-(Examples!$F$10+Examples!$F$11)*$A20-(Examples!$F$6*Examples!$F$7*Examples!$F$8*EXP(-Examples!$F$9*$A20)*(1-(Examples!$F$12*(1-EXP(-Examples!$F$13*$A20))/(1+EXP(MIN(700,MAX(-700,(Examples!$F$14*$A20-Examples!$F$15)/Examples!$F$16))))))+Examples!$F$17*$A20^2) -> 129517.15 | I20: =(Examples!$F$6*Examples!$F$7*Examples!$F$8*EXP(-Examples!$F$9*$A20)*(1-(Examples!$F$12*(1-EXP(-Examples!$F$13*$A20))/(1+EXP(MIN(700,MAX(-700,(Examples!$F$14*$A20-Examples!$F$15)/Examples!$F$16))))))+Examples!$F$17*$A20^2) -> 16882.854 | J20: =Examples!$G$18-(Examples!$G$10+Examples!$G$11)*$A20-(Examples!$G$6*Examples!$G$7*Examples!$G$8*EXP(-Examples!$G$9*$A20)*(1-(Examples!$G$12*(1-EXP(-Examples!$G$13*$A20))/(1+EXP(MIN(700,MAX(-700,(Examples!$G$14*$A20-Examples!$G$15)/Examples!$G$16))))))+Examples!$G$17*$A20^2) -> -263453.66 | K20: =(Examples!$G$6*Examples!$G$7*Examples!$G$8*EXP(-Examples!$G$9*$A20)*(1-(Examples!$G$12*(1-EXP(-Examples!$G$13*$A20))/(1+EXP(MIN(700,MAX(-700,(Examples!$G$14*$A20-Examples!$G$15)/Examples!$G$16))))))+Examples!$G$17*$A20^2) -> 1754453.7 | L20: =Examples!$H$18-(Examples!$H$10+Examples!$H$11)*$A20-(Examples!$H$6*Examples!$H$7*Examples!$H$8*EXP(-Examples!$H$9*$A20)*(1-(Examples!$H$12*(1-EXP(-Examples!$H$13*$A20))/(1+EXP(MIN(700,MAX(-700,(Examples!$H$14*$A20-Examples!$H$15)/Examples!$H$16))))))+Examples!$H$17*$A20^2) -> -257921.26 | M20: =(Examples!$H$6*Examples!$H$7*Examples!$H$8*EXP(-Examples!$H$9*$A20)*(1-(Examples!$H$12*(1-EXP(-Examples!$H$13*$A20))/(1+EXP(MIN(700,MAX(-700,(Examples!$H$14*$A20-Examples!$H$15)/Examples!$H$16))))))+Examples!$H$17*$A20^2) -> 1748921.3
A21: =(21-2)/100 -> 0.19 | B21: =Examples!$C$18-(Examples!$C$10+Examples!$C$11)*$A21-(Examples!$C$6*Examples!$C$7*Examples!$C$8*EXP(-Examples!$C$9*$A21)*(1-(Examples!$C$12*(1-EXP(-Examples!$C$13*$A21))/(1+EXP(MIN(700,MAX(-700,(Examples!$C$14*$A21-Examples!$C$15)/Examples!$C$16))))))+Examples!$C$17*$A21^2) -> 50758.555 | C21: =(Examples!$C$6*Examples!$C$7*Examples!$C$8*EXP(-Examples!$C$9*$A21)*(1-(Examples!$C$12*(1-EXP(-Examples!$C$13*$A21))/(1+EXP(MIN(700,MAX(-700,(Examples!$C$14*$A21-Examples!$C$15)/Examples!$C$16))))))+Examples!$C$17*$A21^2) -> 542591.45 | D21: =Examples!$D$18-(Examples!$D$10+Examples!$D$11)*$A21-(Examples!$D$6*Examples!$D$7*Examples!$D$8*EXP(-Examples!$D$9*$A21)*(1-(Examples!$D$12*(1-EXP(-Examples!$D$13*$A21))/(1+EXP(MIN(700,MAX(-700,(Examples!$D$14*$A21-Examples!$D$15)/Examples!$D$16))))))+Examples!$D$17*$A21^2) -> -2575771.8 | E21: =(Examples!$D$6*Examples!$D$7*Examples!$D$8*EXP(-Examples!$D$9*$A21)*(1-(Examples!$D$12*(1-EXP(-Examples!$D$13*$A21))/(1+EXP(MIN(700,MAX(-700,(Examples!$D$14*$A21-Examples!$D$15)/Examples!$D$16))))))+Examples!$D$17*$A21^2) -> 5067221.8 | F21: =Examples!$E$18-(Examples!$E$10+Examples!$E$11)*$A21-(Examples!$E$6*Examples!$E$7*Examples!$E$8*EXP(-Examples!$E$9*$A21)*(1-(Examples!$E$12*(1-EXP(-Examples!$E$13*$A21))/(1+EXP(MIN(700,MAX(-700,(Examples!$E$14*$A21-Examples!$E$15)/Examples!$E$16))))))+Examples!$E$17*$A21^2) -> 782914.38 | G21: =(Examples!$E$6*Examples!$E$7*Examples!$E$8*EXP(-Examples!$E$9*$A21)*(1-(Examples!$E$12*(1-EXP(-Examples!$E$13*$A21))/(1+EXP(MIN(700,MAX(-700,(Examples!$E$14*$A21-Examples!$E$15)/Examples!$E$16))))))+Examples!$E$17*$A21^2) -> 2200935.6 | H21: =Examples!$F$18-(Examples!$F$10+Examples!$F$11)*$A21-(Examples!$F$6*Examples!$F$7*Examples!$F$8*EXP(-Examples!$F$9*$A21)*(1-(Examples!$F$12*(1-EXP(-Examples!$F$13*$A21))/(1+EXP(MIN(700,MAX(-700,(Examples!$F$14*$A21-Examples!$F$15)/Examples!$F$16))))))+Examples!$F$17*$A21^2) -> 129310.21 | I21: =(Examples!$F$6*Examples!$F$7*Examples!$F$8*EXP(-Examples!$F$9*$A21)*(1-(Examples!$F$12*(1-EXP(-Examples!$F$13*$A21))/(1+EXP(MIN(700,MAX(-700,(Examples!$F$14*$A21-Examples!$F$15)/Examples!$F$16))))))+Examples!$F$17*$A21^2) -> 16889.787 | J21: =Examples!$G$18-(Examples!$G$10+Examples!$G$11)*$A21-(Examples!$G$6*Examples!$G$7*Examples!$G$8*EXP(-Examples!$G$9*$A21)*(1-(Examples!$G$12*(1-EXP(-Examples!$G$13*$A21))/(1+EXP(MIN(700,MAX(-700,(Examples!$G$14*$A21-Examples!$G$15)/Examples!$G$16))))))+Examples!$G$17*$A21^2) -> -251401.92 | K21: =(Examples!$G$6*Examples!$G$7*Examples!$G$8*EXP(-Examples!$G$9*$A21)*(1-(Examples!$G$12*(1-EXP(-Examples!$G$13*$A21))/(1+EXP(MIN(700,MAX(-700,(Examples!$G$14*$A21-Examples!$G$15)/Examples!$G$16))))))+Examples!$G$17*$A21^2) -> 1741901.9 | L21: =Examples!$H$18-(Examples!$H$10+Examples!$H$11)*$A21-(Examples!$H$6*Examples!$H$7*Examples!$H$8*EXP(-Examples!$H$9*$A21)*(1-(Examples!$H$12*(1-EXP(-Examples!$H$13*$A21))/(1+EXP(MIN(700,MAX(-700,(Examples!$H$14*$A21-Examples!$H$15)/Examples!$H$16))))))+Examples!$H$17*$A21^2) -> -245523.96 | M21: =(Examples!$H$6*Examples!$H$7*Examples!$H$8*EXP(-Examples!$H$9*$A21)*(1-(Examples!$H$12*(1-EXP(-Examples!$H$13*$A21))/(1+EXP(MIN(700,MAX(-700,(Examples!$H$14*$A21-Examples!$H$15)/Examples!$H$16))))))+Examples!$H$17*$A21^2) -> 1736024
A22: =(22-2)/100 -> 0.2 | B22: =Examples!$C$18-(Examples!$C$10+Examples!$C$11)*$A22-(Examples!$C$6*Examples!$C$7*Examples!$C$8*EXP(-Examples!$C$9*$A22)*(1-(Examples!$C$12*(1-EXP(-Examples!$C$13*$A22))/(1+EXP(MIN(700,MAX(-700,(Examples!$C$14*$A22-Examples!$C$15)/Examples!$C$16))))))+Examples!$C$17*$A22^2) -> 53212.741 | C22: =(Examples!$C$6*Examples!$C$7*Examples!$C$8*EXP(-Examples!$C$9*$A22)*(1-(Examples!$C$12*(1-EXP(-Examples!$C$13*$A22))/(1+EXP(MIN(700,MAX(-700,(Examples!$C$14*$A22-Examples!$C$15)/Examples!$C$16))))))+Examples!$C$17*$A22^2) -> 539787.26 | D22: =Examples!$D$18-(Examples!$D$10+Examples!$D$11)*$A22-(Examples!$D$6*Examples!$D$7*Examples!$D$8*EXP(-Examples!$D$9*$A22)*(1-(Examples!$D$12*(1-EXP(-Examples!$D$13*$A22))/(1+EXP(MIN(700,MAX(-700,(Examples!$D$14*$A22-Examples!$D$15)/Examples!$D$16))))))+Examples!$D$17*$A22^2) -> -2531781.4 | E22: =(Examples!$D$6*Examples!$D$7*Examples!$D$8*EXP(-Examples!$D$9*$A22)*(1-(Examples!$D$12*(1-EXP(-Examples!$D$13*$A22))/(1+EXP(MIN(700,MAX(-700,(Examples!$D$14*$A22-Examples!$D$15)/Examples!$D$16))))))+Examples!$D$17*$A22^2) -> 5022781.4 | F22: =Examples!$E$18-(Examples!$E$10+Examples!$E$11)*$A22-(Examples!$E$6*Examples!$E$7*Examples!$E$8*EXP(-Examples!$E$9*$A22)*(1-(Examples!$E$12*(1-EXP(-Examples!$E$13*$A22))/(1+EXP(MIN(700,MAX(-700,(Examples!$E$14*$A22-Examples!$E$15)/Examples!$E$16))))))+Examples!$E$17*$A22^2) -> 805401.58 | G22: =(Examples!$E$6*Examples!$E$7*Examples!$E$8*EXP(-Examples!$E$9*$A22)*(1-(Examples!$E$12*(1-EXP(-Examples!$E$13*$A22))/(1+EXP(MIN(700,MAX(-700,(Examples!$E$14*$A22-Examples!$E$15)/Examples!$E$16))))))+Examples!$E$17*$A22^2) -> 2177598.4 | H22: =Examples!$F$18-(Examples!$F$10+Examples!$F$11)*$A22-(Examples!$F$6*Examples!$F$7*Examples!$F$8*EXP(-Examples!$F$9*$A22)*(1-(Examples!$F$12*(1-EXP(-Examples!$F$13*$A22))/(1+EXP(MIN(700,MAX(-700,(Examples!$F$14*$A22-Examples!$F$15)/Examples!$F$16))))))+Examples!$F$17*$A22^2) -> 129098.95 | I22: =(Examples!$F$6*Examples!$F$7*Examples!$F$8*EXP(-Examples!$F$9*$A22)*(1-(Examples!$F$12*(1-EXP(-Examples!$F$13*$A22))/(1+EXP(MIN(700,MAX(-700,(Examples!$F$14*$A22-Examples!$F$15)/Examples!$F$16))))))+Examples!$F$17*$A22^2) -> 16901.052 | J22: =Examples!$G$18-(Examples!$G$10+Examples!$G$11)*$A22-(Examples!$G$6*Examples!$G$7*Examples!$G$8*EXP(-Examples!$G$9*$A22)*(1-(Examples!$G$12*(1-EXP(-Examples!$G$13*$A22))/(1+EXP(MIN(700,MAX(-700,(Examples!$G$14*$A22-Examples!$G$15)/Examples!$G$16))))))+Examples!$G$17*$A22^2) -> -239459.22 | K22: =(Examples!$G$6*Examples!$G$7*Examples!$G$8*EXP(-Examples!$G$9*$A22)*(1-(Examples!$G$12*(1-EXP(-Examples!$G$13*$A22))/(1+EXP(MIN(700,MAX(-700,(Examples!$G$14*$A22-Examples!$G$15)/Examples!$G$16))))))+Examples!$G$17*$A22^2) -> 1729459.2 | L22: =Examples!$H$18-(Examples!$H$10+Examples!$H$11)*$A22-(Examples!$H$6*Examples!$H$7*Examples!$H$8*EXP(-Examples!$H$9*$A22)*(1-(Examples!$H$12*(1-EXP(-Examples!$H$13*$A22))/(1+EXP(MIN(700,MAX(-700,(Examples!$H$14*$A22-Examples!$H$15)/Examples!$H$16))))))+Examples!$H$17*$A22^2) -> -233231.5 | M22: =(Examples!$H$6*Examples!$H$7*Examples!$H$8*EXP(-Examples!$H$9*$A22)*(1-(Examples!$H$12*(1-EXP(-Examples!$H$13*$A22))/(1+EXP(MIN(700,MAX(-700,(Examples!$H$14*$A22-Examples!$H$15)/Examples!$H$16))))))+Examples!$H$17*$A22^2) -> 1723231.5
A23: =(23-2)/100 -> 0.21 | B23: =Examples!$C$18-(Examples!$C$10+Examples!$C$11)*$A23-(Examples!$C$6*Examples!$C$7*Examples!$C$8*EXP(-Examples!$C$9*$A23)*(1-(Examples!$C$12*(1-EXP(-Examples!$C$13*$A23))/(1+EXP(MIN(700,MAX(-700,(Examples!$C$14*$A23-Examples!$C$15)/Examples!$C$16))))))+Examples!$C$17*$A23^2) -> 55645.857 | C23: =(Examples!$C$6*Examples!$C$7*Examples!$C$8*EXP(-Examples!$C$9*$A23)*(1-(Examples!$C$12*(1-EXP(-Examples!$C$13*$A23))/(1+EXP(MIN(700,MAX(-700,(Examples!$C$14*$A23-Examples!$C$15)/Examples!$C$16))))))+Examples!$C$17*$A23^2) -> 537004.14 | D23: =Examples!$D$18-(Examples!$D$10+Examples!$D$11)*$A23-(Examples!$D$6*Examples!$D$7*Examples!$D$8*EXP(-Examples!$D$9*$A23)*(1-(Examples!$D$12*(1-EXP(-Examples!$D$13*$A23))/(1+EXP(MIN(700,MAX(-700,(Examples!$D$14*$A23-Examples!$D$15)/Examples!$D$16))))))+Examples!$D$17*$A23^2) -> -2488224.4 | E23: =(Examples!$D$6*Examples!$D$7*Examples!$D$8*EXP(-Examples!$D$9*$A23)*(1-(Examples!$D$12*(1-EXP(-Examples!$D$13*$A23))/(1+EXP(MIN(700,MAX(-700,(Examples!$D$14*$A23-Examples!$D$15)/Examples!$D$16))))))+Examples!$D$17*$A23^2) -> 4978774.4 | F23: =Examples!$E$18-(Examples!$E$10+Examples!$E$11)*$A23-(Examples!$E$6*Examples!$E$7*Examples!$E$8*EXP(-Examples!$E$9*$A23)*(1-(Examples!$E$12*(1-EXP(-Examples!$E$13*$A23))/(1+EXP(MIN(700,MAX(-700,(Examples!$E$14*$A23-Examples!$E$15)/Examples!$E$16))))))+Examples!$E$17*$A23^2) -> 827619.36 | G23: =(Examples!$E$6*Examples!$E$7*Examples!$E$8*EXP(-Examples!$E$9*$A23)*(1-(Examples!$E$12*(1-EXP(-Examples!$E$13*$A23))/(1+EXP(MIN(700,MAX(-700,(Examples!$E$14*$A23-Examples!$E$15)/Examples!$E$16))))))+Examples!$E$17*$A23^2) -> 2154530.6 | H23: =Examples!$F$18-(Examples!$F$10+Examples!$F$11)*$A23-(Examples!$F$6*Examples!$F$7*Examples!$F$8*EXP(-Examples!$F$9*$A23)*(1-(Examples!$F$12*(1-EXP(-Examples!$F$13*$A23))/(1+EXP(MIN(700,MAX(-700,(Examples!$F$14*$A23-Examples!$F$15)/Examples!$F$16))))))+Examples!$F$17*$A23^2) -> 128883.35 | I23: =(Examples!$F$6*Examples!$F$7*Examples!$F$8*EXP(-Examples!$F$9*$A23)*(1-(Examples!$F$12*(1-EXP(-Examples!$F$13*$A23))/(1+EXP(MIN(700,MAX(-700,(Examples!$F$14*$A23-Examples!$F$15)/Examples!$F$16))))))+Examples!$F$17*$A23^2) -> 16916.649 | J23: =Examples!$G$18-(Examples!$G$10+Examples!$G$11)*$A23-(Examples!$G$6*Examples!$G$7*Examples!$G$8*EXP(-Examples!$G$9*$A23)*(1-(Examples!$G$12*(1-EXP(-Examples!$G$13*$A23))/(1+EXP(MIN(700,MAX(-700,(Examples!$G$14*$A23-Examples!$G$15)/Examples!$G$16))))))+Examples!$G$17*$A23^2) -> -227624.75 | K23: =(Examples!$G$6*Examples!$G$7*Examples!$G$8*EXP(-Examples!$G$9*$A23)*(1-(Examples!$G$12*(1-EXP(-Examples!$G$13*$A23))/(1+EXP(MIN(700,MAX(-700,(Examples!$G$14*$A23-Examples!$G$15)/Examples!$G$16))))))+Examples!$G$17*$A23^2) -> 1717124.8 | L23: =Examples!$H$18-(Examples!$H$10+Examples!$H$11)*$A23-(Examples!$H$6*Examples!$H$7*Examples!$H$8*EXP(-Examples!$H$9*$A23)*(1-(Examples!$H$12*(1-EXP(-Examples!$H$13*$A23))/(1+EXP(MIN(700,MAX(-700,(Examples!$H$14*$A23-Examples!$H$15)/Examples!$H$16))))))+Examples!$H$17*$A23^2) -> -221043.02 | M23: =(Examples!$H$6*Examples!$H$7*Examples!$H$8*EXP(-Examples!$H$9*$A23)*(1-(Examples!$H$12*(1-EXP(-Examples!$H$13*$A23))/(1+EXP(MIN(700,MAX(-700,(Examples!$H$14*$A23-Examples!$H$15)/Examples!$H$16))))))+Examples!$H$17*$A23^2) -> 1710543
A24: =(24-2)/100 -> 0.22 | B24: =Examples!$C$18-(Examples!$C$10+Examples!$C$11)*$A24-(Examples!$C$6*Examples!$C$7*Examples!$C$8*EXP(-Examples!$C$9*$A24)*(1-(Examples!$C$12*(1-EXP(-Examples!$C$13*$A24))/(1+EXP(MIN(700,MAX(-700,(Examples!$C$14*$A24-Examples!$C$15)/Examples!$C$16))))))+Examples!$C$17*$A24^2) -> 58057.988 | C24: =(Examples!$C$6*Examples!$C$7*Examples!$C$8*EXP(-Examples!$C$9*$A24)*(1-(Examples!$C$12*(1-EXP(-Examples!$C$13*$A24))/(1+EXP(MIN(700,MAX(-700,(Examples!$C$14*$A24-Examples!$C$15)/Examples!$C$16))))))+Examples!$C$17*$A24^2) -> 534242.01 | D24: =Examples!$D$18-(Examples!$D$10+Examples!$D$11)*$A24-(Examples!$D$6*Examples!$D$7*Examples!$D$8*EXP(-Examples!$D$9*$A24)*(1-(Examples!$D$12*(1-EXP(-Examples!$D$13*$A24))/(1+EXP(MIN(700,MAX(-700,(Examples!$D$14*$A24-Examples!$D$15)/Examples!$D$16))))))+Examples!$D$17*$A24^2) -> -2445096.6 | E24: =(Examples!$D$6*Examples!$D$7*Examples!$D$8*EXP(-Examples!$D$9*$A24)*(1-(Examples!$D$12*(1-EXP(-Examples!$D$13*$A24))/(1+EXP(MIN(700,MAX(-700,(Examples!$D$14*$A24-Examples!$D$15)/Examples!$D$16))))))+Examples!$D$17*$A24^2) -> 4935196.6 | F24: =Examples!$E$18-(Examples!$E$10+Examples!$E$11)*$A24-(Examples!$E$6*Examples!$E$7*Examples!$E$8*EXP(-Examples!$E$9*$A24)*(1-(Examples!$E$12*(1-EXP(-Examples!$E$13*$A24))/(1+EXP(MIN(700,MAX(-700,(Examples!$E$14*$A24-Examples!$E$15)/Examples!$E$16))))))+Examples!$E$17*$A24^2) -> 849570.87 | G24: =(Examples!$E$6*Examples!$E$7*Examples!$E$8*EXP(-Examples!$E$9*$A24)*(1-(Examples!$E$12*(1-EXP(-Examples!$E$13*$A24))/(1+EXP(MIN(700,MAX(-700,(Examples!$E$14*$A24-Examples!$E$15)/Examples!$E$16))))))+Examples!$E$17*$A24^2) -> 2131729.1 | H24: =Examples!$F$18-(Examples!$F$10+Examples!$F$11)*$A24-(Examples!$F$6*Examples!$F$7*Examples!$F$8*EXP(-Examples!$F$9*$A24)*(1-(Examples!$F$12*(1-EXP(-Examples!$F$13*$A24))/(1+EXP(MIN(700,MAX(-700,(Examples!$F$14*$A24-Examples!$F$15)/Examples!$F$16))))))+Examples!$F$17*$A24^2) -> 128663.42 | I24: =(Examples!$F$6*Examples!$F$7*Examples!$F$8*EXP(-Examples!$F$9*$A24)*(1-(Examples!$F$12*(1-EXP(-Examples!$F$13*$A24))/(1+EXP(MIN(700,MAX(-700,(Examples!$F$14*$A24-Examples!$F$15)/Examples!$F$16))))))+Examples!$F$17*$A24^2) -> 16936.577 | J24: =Examples!$G$18-(Examples!$G$10+Examples!$G$11)*$A24-(Examples!$G$6*Examples!$G$7*Examples!$G$8*EXP(-Examples!$G$9*$A24)*(1-(Examples!$G$12*(1-EXP(-Examples!$G$13*$A24))/(1+EXP(MIN(700,MAX(-700,(Examples!$G$14*$A24-Examples!$G$15)/Examples!$G$16))))))+Examples!$G$17*$A24^2) -> -215897.72 | K24: =(Examples!$G$6*Examples!$G$7*Examples!$G$8*EXP(-Examples!$G$9*$A24)*(1-(Examples!$G$12*(1-EXP(-Examples!$G$13*$A24))/(1+EXP(MIN(700,MAX(-700,(Examples!$G$14*$A24-Examples!$G$15)/Examples!$G$16))))))+Examples!$G$17*$A24^2) -> 1704897.7 | L24: =Examples!$H$18-(Examples!$H$10+Examples!$H$11)*$A24-(Examples!$H$6*Examples!$H$7*Examples!$H$8*EXP(-Examples!$H$9*$A24)*(1-(Examples!$H$12*(1-EXP(-Examples!$H$13*$A24))/(1+EXP(MIN(700,MAX(-700,(Examples!$H$14*$A24-Examples!$H$15)/Examples!$H$16))))))+Examples!$H$17*$A24^2) -> -208957.71 | M24: =(Examples!$H$6*Examples!$H$7*Examples!$H$8*EXP(-Examples!$H$9*$A24)*(1-(Examples!$H$12*(1-EXP(-Examples!$H$13*$A24))/(1+EXP(MIN(700,MAX(-700,(Examples!$H$14*$A24-Examples!$H$15)/Examples!$H$16))))))+Examples!$H$17*$A24^2) -> 1697957.7
A25: =(25-2)/100 -> 0.23 | B25: =Examples!$C$18-(Examples!$C$10+Examples!$C$11)*$A25-(Examples!$C$6*Examples!$C$7*Examples!$C$8*EXP(-Examples!$C$9*$A25)*(1-(Examples!$C$12*(1-EXP(-Examples!$C$13*$A25))/(1+EXP(MIN(700,MAX(-700,(Examples!$C$14*$A25-Examples!$C$15)/Examples!$C$16))))))+Examples!$C$17*$A25^2) -> 60449.219 | C25: =(Examples!$C$6*Examples!$C$7*Examples!$C$8*EXP(-Examples!$C$9*$A25)*(1-(Examples!$C$12*(1-EXP(-Examples!$C$13*$A25))/(1+EXP(MIN(700,MAX(-700,(Examples!$C$14*$A25-Examples!$C$15)/Examples!$C$16))))))+Examples!$C$17*$A25^2) -> 531500.78 | D25: =Examples!$D$18-(Examples!$D$10+Examples!$D$11)*$A25-(Examples!$D$6*Examples!$D$7*Examples!$D$8*EXP(-Examples!$D$9*$A25)*(1-(Examples!$D$12*(1-EXP(-Examples!$D$13*$A25))/(1+EXP(MIN(700,MAX(-700,(Examples!$D$14*$A25-Examples!$D$15)/Examples!$D$16))))))+Examples!$D$17*$A25^2) -> -2402393.6 | E25: =(Examples!$D$6*Examples!$D$7*Examples!$D$8*EXP(-Examples!$D$9*$A25)*(1-(Examples!$D$12*(1-EXP(-Examples!$D$13*$A25))/(1+EXP(MIN(700,MAX(-700,(Examples!$D$14*$A25-Examples!$D$15)/Examples!$D$16))))))+Examples!$D$17*$A25^2) -> 4892043.6 | F25: =Examples!$E$18-(Examples!$E$10+Examples!$E$11)*$A25-(Examples!$E$6*Examples!$E$7*Examples!$E$8*EXP(-Examples!$E$9*$A25)*(1-(Examples!$E$12*(1-EXP(-Examples!$E$13*$A25))/(1+EXP(MIN(700,MAX(-700,(Examples!$E$14*$A25-Examples!$E$15)/Examples!$E$16))))))+Examples!$E$17*$A25^2) -> 871259.22 | G25: =(Examples!$E$6*Examples!$E$7*Examples!$E$8*EXP(-Examples!$E$9*$A25)*(1-(Examples!$E$12*(1-EXP(-Examples!$E$13*$A25))/(1+EXP(MIN(700,MAX(-700,(Examples!$E$14*$A25-Examples!$E$15)/Examples!$E$16))))))+Examples!$E$17*$A25^2) -> 2109190.8 | H25: =Examples!$F$18-(Examples!$F$10+Examples!$F$11)*$A25-(Examples!$F$6*Examples!$F$7*Examples!$F$8*EXP(-Examples!$F$9*$A25)*(1-(Examples!$F$12*(1-EXP(-Examples!$F$13*$A25))/(1+EXP(MIN(700,MAX(-700,(Examples!$F$14*$A25-Examples!$F$15)/Examples!$F$16))))))+Examples!$F$17*$A25^2) -> 128439.17 | I25: =(Examples!$F$6*Examples!$F$7*Examples!$F$8*EXP(-Examples!$F$9*$A25)*(1-(Examples!$F$12*(1-EXP(-Examples!$F$13*$A25))/(1+EXP(MIN(700,MAX(-700,(Examples!$F$14*$A25-Examples!$F$15)/Examples!$F$16))))))+Examples!$F$17*$A25^2) -> 16960.835 | J25: =Examples!$G$18-(Examples!$G$10+Examples!$G$11)*$A25-(Examples!$G$6*Examples!$G$7*Examples!$G$8*EXP(-Examples!$G$9*$A25)*(1-(Examples!$G$12*(1-EXP(-Examples!$G$13*$A25))/(1+EXP(MIN(700,MAX(-700,(Examples!$G$14*$A25-Examples!$G$15)/Examples!$G$16))))))+Examples!$G$17*$A25^2) -> -204277.34 | K25: =(Examples!$G$6*Examples!$G$7*Examples!$G$8*EXP(-Examples!$G$9*$A25)*(1-(Examples!$G$12*(1-EXP(-Examples!$G$13*$A25))/(1+EXP(MIN(700,MAX(-700,(Examples!$G$14*$A25-Examples!$G$15)/Examples!$G$16))))))+Examples!$G$17*$A25^2) -> 1692777.3 | L25: =Examples!$H$18-(Examples!$H$10+Examples!$H$11)*$A25-(Examples!$H$6*Examples!$H$7*Examples!$H$8*EXP(-Examples!$H$9*$A25)*(1-(Examples!$H$12*(1-EXP(-Examples!$H$13*$A25))/(1+EXP(MIN(700,MAX(-700,(Examples!$H$14*$A25-Examples!$H$15)/Examples!$H$16))))))+Examples!$H$17*$A25^2) -> -196974.74 | M25: =(Examples!$H$6*Examples!$H$7*Examples!$H$8*EXP(-Examples!$H$9*$A25)*(1-(Examples!$H$12*(1-EXP(-Examples!$H$13*$A25))/(1+EXP(MIN(700,MAX(-700,(Examples!$H$14*$A25-Examples!$H$15)/Examples!$H$16))))))+Examples!$H$17*$A25^2) -> 1685474.7
A26: =(26-2)/100 -> 0.24 | B26: =Examples!$C$18-(Examples!$C$10+Examples!$C$11)*$A26-(Examples!$C$6*Examples!$C$7*Examples!$C$8*EXP(-Examples!$C$9*$A26)*(1-(Examples!$C$12*(1-EXP(-Examples!$C$13*$A26))/(1+EXP(MIN(700,MAX(-700,(Examples!$C$14*$A26-Examples!$C$15)/Examples!$C$16))))))+Examples!$C$17*$A26^2) -> 62819.631 | C26: =(Examples!$C$6*Examples!$C$7*Examples!$C$8*EXP(-Examples!$C$9*$A26)*(1-(Examples!$C$12*(1-EXP(-Examples!$C$13*$A26))/(1+EXP(MIN(700,MAX(-700,(Examples!$C$14*$A26-Examples!$C$15)/Examples!$C$16))))))+Examples!$C$17*$A26^2) -> 528780.37 | D26: =Examples!$D$18-(Examples!$D$10+Examples!$D$11)*$A26-(Examples!$D$6*Examples!$D$7*Examples!$D$8*EXP(-Examples!$D$9*$A26)*(1-(Examples!$D$12*(1-EXP(-Examples!$D$13*$A26))/(1+EXP(MIN(700,MAX(-700,(Examples!$D$14*$A26-Examples!$D$15)/Examples!$D$16))))))+Examples!$D$17*$A26^2) -> -2360111.2 | E26: =(Examples!$D$6*Examples!$D$7*Examples!$D$8*EXP(-Examples!$D$9*$A26)*(1-(Examples!$D$12*(1-EXP(-Examples!$D$13*$A26))/(1+EXP(MIN(700,MAX(-700,(Examples!$D$14*$A26-Examples!$D$15)/Examples!$D$16))))))+Examples!$D$17*$A26^2) -> 4849311.2 | F26: =Examples!$E$18-(Examples!$E$10+Examples!$E$11)*$A26-(Examples!$E$6*Examples!$E$7*Examples!$E$8*EXP(-Examples!$E$9*$A26)*(1-(Examples!$E$12*(1-EXP(-Examples!$E$13*$A26))/(1+EXP(MIN(700,MAX(-700,(Examples!$E$14*$A26-Examples!$E$15)/Examples!$E$16))))))+Examples!$E$17*$A26^2) -> 892687.48 | G26: =(Examples!$E$6*Examples!$E$7*Examples!$E$8*EXP(-Examples!$E$9*$A26)*(1-(Examples!$E$12*(1-EXP(-Examples!$E$13*$A26))/(1+EXP(MIN(700,MAX(-700,(Examples!$E$14*$A26-Examples!$E$15)/Examples!$E$16))))))+Examples!$E$17*$A26^2) -> 2086912.5 | H26: =Examples!$F$18-(Examples!$F$10+Examples!$F$11)*$A26-(Examples!$F$6*Examples!$F$7*Examples!$F$8*EXP(-Examples!$F$9*$A26)*(1-(Examples!$F$12*(1-EXP(-Examples!$F$13*$A26))/(1+EXP(MIN(700,MAX(-700,(Examples!$F$14*$A26-Examples!$F$15)/Examples!$F$16))))))+Examples!$F$17*$A26^2) -> 128210.58 | I26: =(Examples!$F$6*Examples!$F$7*Examples!$F$8*EXP(-Examples!$F$9*$A26)*(1-(Examples!$F$12*(1-EXP(-Examples!$F$13*$A26))/(1+EXP(MIN(700,MAX(-700,(Examples!$F$14*$A26-Examples!$F$15)/Examples!$F$16))))))+Examples!$F$17*$A26^2) -> 16989.423 | J26: =Examples!$G$18-(Examples!$G$10+Examples!$G$11)*$A26-(Examples!$G$6*Examples!$G$7*Examples!$G$8*EXP(-Examples!$G$9*$A26)*(1-(Examples!$G$12*(1-EXP(-Examples!$G$13*$A26))/(1+EXP(MIN(700,MAX(-700,(Examples!$G$14*$A26-Examples!$G$15)/Examples!$G$16))))))+Examples!$G$17*$A26^2) -> -192762.8 | K26: =(Examples!$G$6*Examples!$G$7*Examples!$G$8*EXP(-Examples!$G$9*$A26)*(1-(Examples!$G$12*(1-EXP(-Examples!$G$13*$A26))/(1+EXP(MIN(700,MAX(-700,(Examples!$G$14*$A26-Examples!$G$15)/Examples!$G$16))))))+Examples!$G$17*$A26^2) -> 1680762.8 | L26: =Examples!$H$18-(Examples!$H$10+Examples!$H$11)*$A26-(Examples!$H$6*Examples!$H$7*Examples!$H$8*EXP(-Examples!$H$9*$A26)*(1-(Examples!$H$12*(1-EXP(-Examples!$H$13*$A26))/(1+EXP(MIN(700,MAX(-700,(Examples!$H$14*$A26-Examples!$H$15)/Examples!$H$16))))))+Examples!$H$17*$A26^2) -> -185093.29 | M26: =(Examples!$H$6*Examples!$H$7*Examples!$H$8*EXP(-Examples!$H$9*$A26)*(1-(Examples!$H$12*(1-EXP(-Examples!$H$13*$A26))/(1+EXP(MIN(700,MAX(-700,(Examples!$H$14*$A26-Examples!$H$15)/Examples!$H$16))))))+Examples!$H$17*$A26^2) -> 1673093.3
A27: =(27-2)/100 -> 0.25 | B27: =Examples!$C$18-(Examples!$C$10+Examples!$C$11)*$A27-(Examples!$C$6*Examples!$C$7*Examples!$C$8*EXP(-Examples!$C$9*$A27)*(1-(Examples!$C$12*(1-EXP(-Examples!$C$13*$A27))/(1+EXP(MIN(700,MAX(-700,(Examples!$C$14*$A27-Examples!$C$15)/Examples!$C$16))))))+Examples!$C$17*$A27^2) -> 65169.305 | C27: =(Examples!$C$6*Examples!$C$7*Examples!$C$8*EXP(-Examples!$C$9*$A27)*(1-(Examples!$C$12*(1-EXP(-Examples!$C$13*$A27))/(1+EXP(MIN(700,MAX(-700,(Examples!$C$14*$A27-Examples!$C$15)/Examples!$C$16))))))+Examples!$C$17*$A27^2) -> 526080.69 | D27: =Examples!$D$18-(Examples!$D$10+Examples!$D$11)*$A27-(Examples!$D$6*Examples!$D$7*Examples!$D$8*EXP(-Examples!$D$9*$A27)*(1-(Examples!$D$12*(1-EXP(-Examples!$D$13*$A27))/(1+EXP(MIN(700,MAX(-700,(Examples!$D$14*$A27-Examples!$D$15)/Examples!$D$16))))))+Examples!$D$17*$A27^2) -> -2318245.2 | E27: =(Examples!$D$6*Examples!$D$7*Examples!$D$8*EXP(-Examples!$D$9*$A27)*(1-(Examples!$D$12*(1-EXP(-Examples!$D$13*$A27))/(1+EXP(MIN(700,MAX(-700,(Examples!$D$14*$A27-Examples!$D$15)/Examples!$D$16))))))+Examples!$D$17*$A27^2) -> 4806995.2 | F27: =Examples!$E$18-(Examples!$E$10+Examples!$E$11)*$A27-(Examples!$E$6*Examples!$E$7*Examples!$E$8*EXP(-Examples!$E$9*$A27)*(1-(Examples!$E$12*(1-EXP(-Examples!$E$13*$A27))/(1+EXP(MIN(700,MAX(-700,(Examples!$E$14*$A27-Examples!$E$15)/Examples!$E$16))))))+Examples!$E$17*$A27^2) -> 913858.69 | G27: =(Examples!$E$6*Examples!$E$7*Examples!$E$8*EXP(-Examples!$E$9*$A27)*(1-(Examples!$E$12*(1-EXP(-Examples!$E$13*$A27))/(1+EXP(MIN(700,MAX(-700,(Examples!$E$14*$A27-Examples!$E$15)/Examples!$E$16))))))+Examples!$E$17*$A27^2) -> 2064891.3 | H27: =Examples!$F$18-(Examples!$F$10+Examples!$F$11)*$A27-(Examples!$F$6*Examples!$F$7*Examples!$F$8*EXP(-Examples!$F$9*$A27)*(1-(Examples!$F$12*(1-EXP(-Examples!$F$13*$A27))/(1+EXP(MIN(700,MAX(-700,(Examples!$F$14*$A27-Examples!$F$15)/Examples!$F$16))))))+Examples!$F$17*$A27^2) -> 127977.66 | I27: =(Examples!$F$6*Examples!$F$7*Examples!$F$8*EXP(-Examples!$F$9*$A27)*(1-(Examples!$F$12*(1-EXP(-Examples!$F$13*$A27))/(1+EXP(MIN(700,MAX(-700,(Examples!$F$14*$A27-Examples!$F$15)/Examples!$F$16))))))+Examples!$F$17*$A27^2) -> 17022.341 | J27: =Examples!$G$18-(Examples!$G$10+Examples!$G$11)*$A27-(Examples!$G$6*Examples!$G$7*Examples!$G$8*EXP(-Examples!$G$9*$A27)*(1-(Examples!$G$12*(1-EXP(-Examples!$G$13*$A27))/(1+EXP(MIN(700,MAX(-700,(Examples!$G$14*$A27-Examples!$G$15)/Examples!$G$16))))))+Examples!$G$17*$A27^2) -> -181353.34 | K27: =(Examples!$G$6*Examples!$G$7*Examples!$G$8*EXP(-Examples!$G$9*$A27)*(1-(Examples!$G$12*(1-EXP(-Examples!$G$13*$A27))/(1+EXP(MIN(700,MAX(-700,(Examples!$G$14*$A27-Examples!$G$15)/Examples!$G$16))))))+Examples!$G$17*$A27^2) -> 1668853.3 | L27: =Examples!$H$18-(Examples!$H$10+Examples!$H$11)*$A27-(Examples!$H$6*Examples!$H$7*Examples!$H$8*EXP(-Examples!$H$9*$A27)*(1-(Examples!$H$12*(1-EXP(-Examples!$H$13*$A27))/(1+EXP(MIN(700,MAX(-700,(Examples!$H$14*$A27-Examples!$H$15)/Examples!$H$16))))))+Examples!$H$17*$A27^2) -> -173312.56 | M27: =(Examples!$H$6*Examples!$H$7*Examples!$H$8*EXP(-Examples!$H$9*$A27)*(1-(Examples!$H$12*(1-EXP(-Examples!$H$13*$A27))/(1+EXP(MIN(700,MAX(-700,(Examples!$H$14*$A27-Examples!$H$15)/Examples!$H$16))))))+Examples!$H$17*$A27^2) -> 1660812.6
A28: =(28-2)/100 -> 0.26 | B28: =Examples!$C$18-(Examples!$C$10+Examples!$C$11)*$A28-(Examples!$C$6*Examples!$C$7*Examples!$C$8*EXP(-Examples!$C$9*$A28)*(1-(Examples!$C$12*(1-EXP(-Examples!$C$13*$A28))/(1+EXP(MIN(700,MAX(-700,(Examples!$C$14*$A28-Examples!$C$15)/Examples!$C$16))))))+Examples!$C$17*$A28^2) -> 67498.319 | C28: =(Examples!$C$6*Examples!$C$7*Examples!$C$8*EXP(-Examples!$C$9*$A28)*(1-(Examples!$C$12*(1-EXP(-Examples!$C$13*$A28))/(1+EXP(MIN(700,MAX(-700,(Examples!$C$14*$A28-Examples!$C$15)/Examples!$C$16))))))+Examples!$C$17*$A28^2) -> 523401.68 | D28: =Examples!$D$18-(Examples!$D$10+Examples!$D$11)*$A28-(Examples!$D$6*Examples!$D$7*Examples!$D$8*EXP(-Examples!$D$9*$A28)*(1-(Examples!$D$12*(1-EXP(-Examples!$D$13*$A28))/(1+EXP(MIN(700,MAX(-700,(Examples!$D$14*$A28-Examples!$D$15)/Examples!$D$16))))))+Examples!$D$17*$A28^2) -> -2276791.6 | E28: =(Examples!$D$6*Examples!$D$7*Examples!$D$8*EXP(-Examples!$D$9*$A28)*(1-(Examples!$D$12*(1-EXP(-Examples!$D$13*$A28))/(1+EXP(MIN(700,MAX(-700,(Examples!$D$14*$A28-Examples!$D$15)/Examples!$D$16))))))+Examples!$D$17*$A28^2) -> 4765091.6 | F28: =Examples!$E$18-(Examples!$E$10+Examples!$E$11)*$A28-(Examples!$E$6*Examples!$E$7*Examples!$E$8*EXP(-Examples!$E$9*$A28)*(1-(Examples!$E$12*(1-EXP(-Examples!$E$13*$A28))/(1+EXP(MIN(700,MAX(-700,(Examples!$E$14*$A28-Examples!$E$15)/Examples!$E$16))))))+Examples!$E$17*$A28^2) -> 934775.83 | G28: =(Examples!$E$6*Examples!$E$7*Examples!$E$8*EXP(-Examples!$E$9*$A28)*(1-(Examples!$E$12*(1-EXP(-Examples!$E$13*$A28))/(1+EXP(MIN(700,MAX(-700,(Examples!$E$14*$A28-Examples!$E$15)/Examples!$E$16))))))+Examples!$E$17*$A28^2) -> 2043124.2 | H28: =Examples!$F$18-(Examples!$F$10+Examples!$F$11)*$A28-(Examples!$F$6*Examples!$F$7*Examples!$F$8*EXP(-Examples!$F$9*$A28)*(1-(Examples!$F$12*(1-EXP(-Examples!$F$13*$A28))/(1+EXP(MIN(700,MAX(-700,(Examples!$F$14*$A28-Examples!$F$15)/Examples!$F$16))))))+Examples!$F$17*$A28^2) -> 127740.41 | I28: =(Examples!$F$6*Examples!$F$7*Examples!$F$8*EXP(-Examples!$F$9*$A28)*(1-(Examples!$F$12*(1-EXP(-Examples!$F$13*$A28))/(1+EXP(MIN(700,MAX(-700,(Examples!$F$14*$A28-Examples!$F$15)/Examples!$F$16))))))+Examples!$F$17*$A28^2) -> 17059.588 | J28: =Examples!$G$18-(Examples!$G$10+Examples!$G$11)*$A28-(Examples!$G$6*Examples!$G$7*Examples!$G$8*EXP(-Examples!$G$9*$A28)*(1-(Examples!$G$12*(1-EXP(-Examples!$G$13*$A28))/(1+EXP(MIN(700,MAX(-700,(Examples!$G$14*$A28-Examples!$G$15)/Examples!$G$16))))))+Examples!$G$17*$A28^2) -> -170048.17 | K28: =(Examples!$G$6*Examples!$G$7*Examples!$G$8*EXP(-Examples!$G$9*$A28)*(1-(Examples!$G$12*(1-EXP(-Examples!$G$13*$A28))/(1+EXP(MIN(700,MAX(-700,(Examples!$G$14*$A28-Examples!$G$15)/Examples!$G$16))))))+Examples!$G$17*$A28^2) -> 1657048.2 | L28: =Examples!$H$18-(Examples!$H$10+Examples!$H$11)*$A28-(Examples!$H$6*Examples!$H$7*Examples!$H$8*EXP(-Examples!$H$9*$A28)*(1-(Examples!$H$12*(1-EXP(-Examples!$H$13*$A28))/(1+EXP(MIN(700,MAX(-700,(Examples!$H$14*$A28-Examples!$H$15)/Examples!$H$16))))))+Examples!$H$17*$A28^2) -> -161631.74 | M28: =(Examples!$H$6*Examples!$H$7*Examples!$H$8*EXP(-Examples!$H$9*$A28)*(1-(Examples!$H$12*(1-EXP(-Examples!$H$13*$A28))/(1+EXP(MIN(700,MAX(-700,(Examples!$H$14*$A28-Examples!$H$15)/Examples!$H$16))))))+Examples!$H$17*$A28^2) -> 1648631.7
A29: =(29-2)/100 -> 0.27 | B29: =Examples!$C$18-(Examples!$C$10+Examples!$C$11)*$A29-(Examples!$C$6*Examples!$C$7*Examples!$C$8*EXP(-Examples!$C$9*$A29)*(1-(Examples!$C$12*(1-EXP(-Examples!$C$13*$A29))/(1+EXP(MIN(700,MAX(-700,(Examples!$C$14*$A29-Examples!$C$15)/Examples!$C$16))))))+Examples!$C$17*$A29^2) -> 69806.75 | C29: =(Examples!$C$6*Examples!$C$7*Examples!$C$8*EXP(-Examples!$C$9*$A29)*(1-(Examples!$C$12*(1-EXP(-Examples!$C$13*$A29))/(1+EXP(MIN(700,MAX(-700,(Examples!$C$14*$A29-Examples!$C$15)/Examples!$C$16))))))+Examples!$C$17*$A29^2) -> 520743.25 | D29: =Examples!$D$18-(Examples!$D$10+Examples!$D$11)*$A29-(Examples!$D$6*Examples!$D$7*Examples!$D$8*EXP(-Examples!$D$9*$A29)*(1-(Examples!$D$12*(1-EXP(-Examples!$D$13*$A29))/(1+EXP(MIN(700,MAX(-700,(Examples!$D$14*$A29-Examples!$D$15)/Examples!$D$16))))))+Examples!$D$17*$A29^2) -> -2235746.2 | E29: =(Examples!$D$6*Examples!$D$7*Examples!$D$8*EXP(-Examples!$D$9*$A29)*(1-(Examples!$D$12*(1-EXP(-Examples!$D$13*$A29))/(1+EXP(MIN(700,MAX(-700,(Examples!$D$14*$A29-Examples!$D$15)/Examples!$D$16))))))+Examples!$D$17*$A29^2) -> 4723596.2 | F29: =Examples!$E$18-(Examples!$E$10+Examples!$E$11)*$A29-(Examples!$E$6*Examples!$E$7*Examples!$E$8*EXP(-Examples!$E$9*$A29)*(1-(Examples!$E$12*(1-EXP(-Examples!$E$13*$A29))/(1+EXP(MIN(700,MAX(-700,(Examples!$E$14*$A29-Examples!$E$15)/Examples!$E$16))))))+Examples!$E$17*$A29^2) -> 955441.88 | G29: =(Examples!$E$6*Examples!$E$7*Examples!$E$8*EXP(-Examples!$E$9*$A29)*(1-(Examples!$E$12*(1-EXP(-Examples!$E$13*$A29))/(1+EXP(MIN(700,MAX(-700,(Examples!$E$14*$A29-Examples!$E$15)/Examples!$E$16))))))+Examples!$E$17*$A29^2) -> 2021608.1 | H29: =Examples!$F$18-(Examples!$F$10+Examples!$F$11)*$A29-(Examples!$F$6*Examples!$F$7*Examples!$F$8*EXP(-Examples!$F$9*$A29)*(1-(Examples!$F$12*(1-EXP(-Examples!$F$13*$A29))/(1+EXP(MIN(700,MAX(-700,(Examples!$F$14*$A29-Examples!$F$15)/Examples!$F$16))))))+Examples!$F$17*$A29^2) -> 127498.84 | I29: =(Examples!$F$6*Examples!$F$7*Examples!$F$8*EXP(-Examples!$F$9*$A29)*(1-(Examples!$F$12*(1-EXP(-Examples!$F$13*$A29))/(1+EXP(MIN(700,MAX(-700,(Examples!$F$14*$A29-Examples!$F$15)/Examples!$F$16))))))+Examples!$F$17*$A29^2) -> 17101.163 | J29: =Examples!$G$18-(Examples!$G$10+Examples!$G$11)*$A29-(Examples!$G$6*Examples!$G$7*Examples!$G$8*EXP(-Examples!$G$9*$A29)*(1-(Examples!$G$12*(1-EXP(-Examples!$G$13*$A29))/(1+EXP(MIN(700,MAX(-700,(Examples!$G$14*$A29-Examples!$G$15)/Examples!$G$16))))))+Examples!$G$17*$A29^2) -> -158846.53 | K29: =(Examples!$G$6*Examples!$G$7*Examples!$G$8*EXP(-Examples!$G$9*$A29)*(1-(Examples!$G$12*(1-EXP(-Examples!$G$13*$A29))/(1+EXP(MIN(700,MAX(-700,(Examples!$G$14*$A29-Examples!$G$15)/Examples!$G$16))))))+Examples!$G$17*$A29^2) -> 1645346.5 | L29: =Examples!$H$18-(Examples!$H$10+Examples!$H$11)*$A29-(Examples!$H$6*Examples!$H$7*Examples!$H$8*EXP(-Examples!$H$9*$A29)*(1-(Examples!$H$12*(1-EXP(-Examples!$H$13*$A29))/(1+EXP(MIN(700,MAX(-700,(Examples!$H$14*$A29-Examples!$H$15)/Examples!$H$16))))))+Examples!$H$17*$A29^2) -> -150050.05 | M29: =(Examples!$H$6*Examples!$H$7*Examples!$H$8*EXP(-Examples!$H$9*$A29)*(1-(Examples!$H$12*(1-EXP(-Examples!$H$13*$A29))/(1+EXP(MIN(700,MAX(-700,(Examples!$H$14*$A29-Examples!$H$15)/Examples!$H$16))))))+Examples!$H$17*$A29^2) -> 1636550
A30: =(30-2)/100 -> 0.28 | B30: =Examples!$C$18-(Examples!$C$10+Examples!$C$11)*$A30-(Examples!$C$6*Examples!$C$7*Examples!$C$8*EXP(-Examples!$C$9*$A30)*(1-(Examples!$C$12*(1-EXP(-Examples!$C$13*$A30))/(1+EXP(MIN(700,MAX(-700,(Examples!$C$14*$A30-Examples!$C$15)/Examples!$C$16))))))+Examples!$C$17*$A30^2) -> 72094.672 | C30: =(Examples!$C$6*Examples!$C$7*Examples!$C$8*EXP(-Examples!$C$9*$A30)*(1-(Examples!$C$12*(1-EXP(-Examples!$C$13*$A30))/(1+EXP(MIN(700,MAX(-700,(Examples!$C$14*$A30-Examples!$C$15)/Examples!$C$16))))))+Examples!$C$17*$A30^2) -> 518105.33 | D30: =Examples!$D$18-(Examples!$D$10+Examples!$D$11)*$A30-(Examples!$D$6*Examples!$D$7*Examples!$D$8*EXP(-Examples!$D$9*$A30)*(1-(Examples!$D$12*(1-EXP(-Examples!$D$13*$A30))/(1+EXP(MIN(700,MAX(-700,(Examples!$D$14*$A30-Examples!$D$15)/Examples!$D$16))))))+Examples!$D$17*$A30^2) -> -2195105 | E30: =(Examples!$D$6*Examples!$D$7*Examples!$D$8*EXP(-Examples!$D$9*$A30)*(1-(Examples!$D$12*(1-EXP(-Examples!$D$13*$A30))/(1+EXP(MIN(700,MAX(-700,(Examples!$D$14*$A30-Examples!$D$15)/Examples!$D$16))))))+Examples!$D$17*$A30^2) -> 4682505 | F30: =Examples!$E$18-(Examples!$E$10+Examples!$E$11)*$A30-(Examples!$E$6*Examples!$E$7*Examples!$E$8*EXP(-Examples!$E$9*$A30)*(1-(Examples!$E$12*(1-EXP(-Examples!$E$13*$A30))/(1+EXP(MIN(700,MAX(-700,(Examples!$E$14*$A30-Examples!$E$15)/Examples!$E$16))))))+Examples!$E$17*$A30^2) -> 975859.76 | G30: =(Examples!$E$6*Examples!$E$7*Examples!$E$8*EXP(-Examples!$E$9*$A30)*(1-(Examples!$E$12*(1-EXP(-Examples!$E$13*$A30))/(1+EXP(MIN(700,MAX(-700,(Examples!$E$14*$A30-Examples!$E$15)/Examples!$E$16))))))+Examples!$E$17*$A30^2) -> 2000340.2 | H30: =Examples!$F$18-(Examples!$F$10+Examples!$F$11)*$A30-(Examples!$F$6*Examples!$F$7*Examples!$F$8*EXP(-Examples!$F$9*$A30)*(1-(Examples!$F$12*(1-EXP(-Examples!$F$13*$A30))/(1+EXP(MIN(700,MAX(-700,(Examples!$F$14*$A30-Examples!$F$15)/Examples!$F$16))))))+Examples!$F$17*$A30^2) -> 127252.93 | I30: =(Examples!$F$6*Examples!$F$7*Examples!$F$8*EXP(-Examples!$F$9*$A30)*(1-(Examples!$F$12*(1-EXP(-Examples!$F$13*$A30))/(1+EXP(MIN(700,MAX(-700,(Examples!$F$14*$A30-Examples!$F$15)/Examples!$F$16))))))+Examples!$F$17*$A30^2) -> 17147.066 | J30: =Examples!$G$18-(Examples!$G$10+Examples!$G$11)*$A30-(Examples!$G$6*Examples!$G$7*Examples!$G$8*EXP(-Examples!$G$9*$A30)*(1-(Examples!$G$12*(1-EXP(-Examples!$G$13*$A30))/(1+EXP(MIN(700,MAX(-700,(Examples!$G$14*$A30-Examples!$G$15)/Examples!$G$16))))))+Examples!$G$17*$A30^2) -> -147747.66 | K30: =(Examples!$G$6*Examples!$G$7*Examples!$G$8*EXP(-Examples!$G$9*$A30)*(1-(Examples!$G$12*(1-EXP(-Examples!$G$13*$A30))/(1+EXP(MIN(700,MAX(-700,(Examples!$G$14*$A30-Examples!$G$15)/Examples!$G$16))))))+Examples!$G$17*$A30^2) -> 1633747.7 | L30: =Examples!$H$18-(Examples!$H$10+Examples!$H$11)*$A30-(Examples!$H$6*Examples!$H$7*Examples!$H$8*EXP(-Examples!$H$9*$A30)*(1-(Examples!$H$12*(1-EXP(-Examples!$H$13*$A30))/(1+EXP(MIN(700,MAX(-700,(Examples!$H$14*$A30-Examples!$H$15)/Examples!$H$16))))))+Examples!$H$17*$A30^2) -> -138566.68 | M30: =(Examples!$H$6*Examples!$H$7*Examples!$H$8*EXP(-Examples!$H$9*$A30)*(1-(Examples!$H$12*(1-EXP(-Examples!$H$13*$A30))/(1+EXP(MIN(700,MAX(-700,(Examples!$H$14*$A30-Examples!$H$15)/Examples!$H$16))))))+Examples!$H$17*$A30^2) -> 1624566.7
